Workbook

Sheet Cover
B3: SchoolStack Budget
B4: 5-Year Financial Model
B8: Prepared for
B9: School
B12: Date Prepared | C12: March 27, 2026
B14: Lender Readiness | C14: Not Yet Ready
B17: TABLE OF CONTENTS
B18: Assumptions
B19: Financial Model
B20: Summary
B21: Consultant Notes
B24: Generated by SchoolStack Budget • budget.schoolstack.ai

Sheet Assumptions
A1: SchoolStack Budget - Assumptions
B2: Editable assumption — change this value | E2: Calculated — driven by formula
A3: SCHOOL INFORMATION
A4: School Name
A5: State
A6: School Type
A7: Entity Type
A8: School Stage | B8: New School
A9: Opening Year | B9: 0
A10: Current Students | B10: 0
A11: Max Student Capacity | B11: 0
A12: Fiscal Year Start | B12: July
A14: ENROLLMENT BY YEAR
A15: Year 1 Students | B15: 0
A16: Year 2 Students | B16: 0
A17: Year 3 Students | B17: 0
A18: Year 4 Students | B18: 0
A19: Year 5 Students | B19: 0
A21: GROWTH & ESCALATION ASSUMPTIONS
A22: Annual Salary Escalation | B22: 0
A23: General Cost Inflation | B23: 0
A24: Year 1 Proration Factor | B24: 1
A25: Projection Period | B25: 5 Years

Sheet Financial Model
A1: 5-Year Financial Model | B1: Year 1 | C1: Year 2 | D1: Year 3 | E1: Year 4 | F1: Year 5
A2: Students | B2: 0 | C2: 0 | D2: 0 | E2: 0 | F2: 0
A3: Net Revenue | B3: 0 | C3: 0 | D3: 0 | E3: 0 | F3: 0
A4: Staffing Costs | B4: 0 | C4: 0 | D4: 0 | E4: 0 | F4: 0
A5: Operating Expenses | B5: 0 | C5: 0 | D5: 0 | E5: 0 | F5: 0
A6: Total Expenses | B6: =B4+B5 -> 0 | C6: =C4+C5 -> 0 | D6: =D4+D5 -> 0 | E6: =E4+E5 -> 0 | F6: =F4+F5 -> 0
A7: Profit | B7: =B3-B6 -> 0 | C7: =C3-C6 -> 0 | D7: =D3-D6 -> 0 | E7: =E3-E6 -> 0 | F7: =F3-F6 -> 0
A8: Cumulative Profit | B8: =B7 -> 0 | C8: =B8+C7 -> 0 | D8: =C8+D7 -> 0 | E8: =D8+E7 -> 0 | F8: =E8+F7 -> 0
A9: Operating Reserve (Months) | B9: =IF(B6=0,0,IF(B8>0,B8/(B6/12),0)) -> 0 | C9: =IF(C6=0,0,IF(C8>0,C8/(C6/12),0)) -> 0 | D9: =IF(D6=0,0,IF(D8>0,D8/(D6/12),0)) -> 0 | E9: =IF(E6=0,0,IF(E8>0,E8/(E6/12),0)) -> 0 | F9: =IF(F6=0,0,IF(F8>0,F8/(F6/12),0)) -> 0
A10: Break-even | B10: =IF(B8>=0,"✓ Break-even","") -> ✓ Break-even | C10: =IF(AND(C8>=0,B8<0),"✓ Break-even","") -> 0 | D10: =IF(AND(D8>=0,C8<0),"✓ Break-even","") -> 0 | E10: =IF(AND(E8>=0,D8<0),"✓ Break-even","") -> 0 | F10: =IF(AND(F8>=0,E8<0),"✓ Break-even","") -> 0

Sheet Summary
A1: Financial Model Summary
A2: Prepared by SchoolStack Budget
A4: SCHOOL INFORMATION
A5: School Name
A6: School Type
A7: Entity Type
A8: School Stage | B8: New School
A9: State
A10: Fiscal Year Start | B10: July
A11: Max Student Capacity | B11: N/A
A13: ENROLLMENT TREND
B14: Year 1 | C14: Year 2 | D14: Year 3 | E14: Year 4 | F14: Year 5
A15: Students | B15: ='Financial Model'!B2 -> 0 | C15: ='Financial Model'!C2 -> 0 | D15: ='Financial Model'!D2 -> 0 | E15: ='Financial Model'!E2 -> 0 | F15: ='Financial Model'!F2 -> 0
A16: Enrollment Growth % | B16: - | C16: =IF(B15=0,0,(C15-B15)/B15) -> 0 | D16: =IF(C15=0,0,(D15-C15)/C15) -> 0 | E16: =IF(D15=0,0,(E15-D15)/D15) -> 0 | F16: =IF(E15=0,0,(F15-E15)/E15) -> 0
B18: Year 1 | C18: Year 2 | D18: Year 3 | E18: Year 4 | F18: Year 5
A19: Total Revenue | B19: ='Financial Model'!B3 -> 0 | C19: ='Financial Model'!C3 -> 0 | D19: ='Financial Model'!D3 -> 0 | E19: ='Financial Model'!E3 -> 0 | F19: ='Financial Model'!F3 -> 0
A20: Personnel Costs | B20: ='Financial Model'!B4 -> 0 | C20: ='Financial Model'!C4 -> 0 | D20: ='Financial Model'!D4 -> 0 | E20: ='Financial Model'!E4 -> 0 | F20: ='Financial Model'!F4 -> 0
A21: Operating Expenses | B21: ='Financial Model'!B5 -> 0 | C21: ='Financial Model'!C5 -> 0 | D21: ='Financial Model'!D5 -> 0 | E21: ='Financial Model'!E5 -> 0 | F21: ='Financial Model'!F5 -> 0
A22: Total Expenses | B22: ='Financial Model'!B6 -> 0 | C22: ='Financial Model'!C6 -> 0 | D22: ='Financial Model'!D6 -> 0 | E22: ='Financial Model'!E6 -> 0 | F22: ='Financial Model'!F6 -> 0
A23: Profit | B23: ='Financial Model'!B7 -> 0 | C23: ='Financial Model'!C7 -> 0 | D23: ='Financial Model'!D7 -> 0 | E23: ='Financial Model'!E7 -> 0 | F23: ='Financial Model'!F7 -> 0
A24: Cumulative Profit | B24: ='Financial Model'!B8 -> 0 | C24: ='Financial Model'!C8 -> 0 | D24: ='Financial Model'!D8 -> 0 | E24: ='Financial Model'!E8 -> 0 | F24: ='Financial Model'!F8 -> 0
A25: Operating Reserve (Months) | B25: ='Financial Model'!B9 -> 0 | C25: ='Financial Model'!C9 -> 0 | D25: ='Financial Model'!D9 -> 0 | E25: ='Financial Model'!E9 -> 0 | F25: ='Financial Model'!F9 -> 0
A27: KEY RATIOS
A28: Revenue per Student | B28: =IF('Financial Model'!B2=0,0,B19/'Financial Model'!B2) -> 0 | C28: =IF('Financial Model'!C2=0,0,C19/'Financial Model'!C2) -> 0 | D28: =IF('Financial Model'!D2=0,0,D19/'Financial Model'!D2) -> 0 | E28: =IF('Financial Model'!E2=0,0,E19/'Financial Model'!E2) -> 0 | F28: =IF('Financial Model'!F2=0,0,F19/'Financial Model'!F2) -> 0
A29: Personnel Cost as % of Revenue | B29: =IF(B19=0,0,'Financial Model'!B4/B19) -> 0 | C29: =IF(C19=0,0,'Financial Model'!C4/C19) -> 0 | D29: =IF(D19=0,0,'Financial Model'!D4/D19) -> 0 | E29: =IF(E19=0,0,'Financial Model'!E4/E19) -> 0 | F29: =IF(F19=0,0,'Financial Model'!F4/F19) -> 0
A30: Operating Cost as % of Revenue | B30: =IF(B19=0,0,'Financial Model'!B5/B19) -> 0 | C30: =IF(C19=0,0,'Financial Model'!C5/C19) -> 0 | D30: =IF(D19=0,0,'Financial Model'!D5/D19) -> 0 | E30: =IF(E19=0,0,'Financial Model'!E5/E19) -> 0 | F30: =IF(F19=0,0,'Financial Model'!F5/F19) -> 0
A31: Profit Margin % | B31: =IF(B19=0,0,B23/B19) -> 0 | C31: =IF(C19=0,0,C23/C19) -> 0 | D31: =IF(D19=0,0,D23/D19) -> 0 | E31: =IF(E19=0,0,E23/E19) -> 0 | F31: =IF(F19=0,0,F23/F19) -> 0
A33: LENDER READINESS ASSESSMENT
A34: Readiness Status | B34: Not Yet Ready
A35: Assessment | B35: Your model is a solid starting point, and now it's time to refine it. Focus on the high-priority recommendations first, and you'll see real progress. Every great school's financial story started as a first draft.
A36: Biggest Strength | B36: Well-controlled staffing costs
A37: Biggest Risk | B37: No facility location secured yet, so facility costs are estimated

Sheet Consultant Notes
A1: SchoolStack Budget - Consultant Notes
A3: EXECUTIVE SUMMARY
A4: Your school projects $0 in Year 5 revenue, with 4 of 9 key metrics that need attention. This is a starting point, and working through the recommendations below will help you build the financial story your mission deserves.
A6: LENDER READINESS
A7: Status | B7: Not Yet Ready
A8: Assessment | B8: Your model is a solid starting point, and now it's time to refine it. Focus on the high-priority recommendations first, and you'll see real progress. Every great school's financial story started as a first draft.
A10: Biggest Strength | B10: Well-controlled staffing costs
A11: Biggest Risk | B11: No facility location secured yet, so facility costs are estimated
A13: RECOMMENDATIONS
A14: [HIGH] Grow Your Per-Student Revenue
A15: At $0 per student, there's an opportunity to strengthen this number. Consider modest tuition adjustments, ESA/voucher programs in your state, or fee-based enrichment programs that add value for families.
A16: [MEDIUM] Grow Your Cash Reserve Over Time
A17: By Year 5, your projected reserve covers 0.0 months of expenses. The goal is 3–6 months, and you'll get there by building surplus in your early profit years. Every month of reserve you add makes your school more resilient.
A18: [HIGH] Secure Your Facility Location
A19: Your model is based on an estimated facility budget. Once you have a signed lease or purchase agreement, update your model with actual numbers because real lease terms make your projections far more reliable.
A20: [HIGH] No facility costs in your model
A21: Your model doesn't include rent or facility expenses. Use SchoolStack Space (space.schoolstack.ai) to calculate how much space your school needs and estimate facility costs before finalizing your budget.

Sheet Financial Health
B2: School — Financial Health Dashboard
B3: Generated March 27, 2026
B4: ● Green = healthy | D4: ◐ Yellow = monitor | F4: ○ Red = action needed
B6: Metric | C6: Year 1 | D6: Year 2 | E6: Year 3 | F6: Year 4 | G6: Year 5 | H6: Benchmark
B7: Enrollment | C7: 0 | D7: 0 | E7: 0 | F7: 0 | G7: 0
B8: Revenue | C8: 0 | D8: 0 | E8: 0 | F8: 0 | G8: 0
B9: Personnel | C9: 0 | D9: 0 | E9: 0 | F9: 0 | G9: 0
B10: Operating Expenses | C10: 0 | D10: 0 | E10: 0 | F10: 0 | G10: 0
B11: Debt Service | C11: 0 | D11: 0 | E11: 0 | F11: 0 | G11: 0
B12: Net Income | C12: 0 | D12: 0 | E12: 0 | F12: 0 | G12: 0
B13: Ending Cash | C13: 0 | D13: 0 | E13: 0 | F13: 0 | G13: 0
B14: Net Margin | C14: 0 | D14: 0 | E14: 0 | F14: 0 | G14: 0
B15: Revenue per Student | C15: 0 | D15: 0 | E15: 0 | F15: 0 | G15: 0 | H15: ≥ $10,000
B16: Cost per Student | C16: 0 | D16: 0 | E16: 0 | F16: 0 | G16: 0
B17: Instructional / Student | C17: 0 | D17: 0 | E17: 0 | F17: 0 | G17: 0
B18: Facility / Student | C18: 0 | D18: 0 | E18: 0 | F18: 0 | G18: 0 | H18: ≤ $2,000 / $2k–$3.5k / > $3,500
B19: Surplus per Student | C19: 0 | D19: 0 | E19: 0 | F19: 0 | G19: 0
B20: Payroll % | C20: 0 | D20: 0 | E20: 0 | F20: 0 | G20: 0 | H20: ≤ 55%
B21: Facility % | C21: 0 | D21: 0 | E21: 0 | F21: 0 | G21: 0 | H21: ≤ 15%
B22: Operating Margin | C22: 0 | D22: 0 | E22: 0 | F22: 0 | G22: 0 | H22: ≥ 10%
B23: Revenue Sources | C23: 0 | D23: 0 | E23: 0 | F23: 0 | G23: 0 | H23: ≥ 3 sources
B24: DSCR | C24: N/A | D24: N/A | E24: N/A | F24: N/A | G24: N/A | H24: N/A
B25: Break-even Year | C25: =IF('Financial Model'!B8>=0,"✓ Break-even","") -> ✓ Break-even | D25: =IF(AND('Financial Model'!C8>=0,'Financial Model'!B8<0),"✓ Break-even","") -> 0 | E25: =IF(AND('Financial Model'!D8>=0,'Financial Model'!C8<0),"✓ Break-even","") -> 0 | F25: =IF(AND('Financial Model'!E8>=0,'Financial Model'!D8<0),"✓ Break-even","") -> 0 | G25: =IF(AND('Financial Model'!F8>=0,'Financial Model'!E8<0),"✓ Break-even","") -> 0 | H25: Year 1
B26: Cash Runway (Months) | C26: 60+ | D26: 60+ | E26: 60+ | F26: 60+ | G26: 60+ | H26: ≥ 24 months
B27: Days Cash on Hand | C27: 365 | D27: 365 | E27: 365 | F27: 365 | G27: 365 | H27: ≥ 90 days
B29: FINANCIAL HEALTH SIGNALS | C29: Status | D29: Assessment | F29: Watch Item
B30: Viability | C30: ◐ Watch closely | D30: The model reaches break-even by Year 1, but margins remain thin. A revenue shortfall could push it negative. | F30: Track monthly revenue vs. budget and have a contingency plan if you miss targets.
B31: Liquidity | C31: ◐ Watch closely | D31: Cash stays positive but reserves are thin. Build a buffer before unexpected costs arise. | F31: Target at least 1 month of operating reserves.
B32: Staffing Burden | C32: ● Healthy | D32: Staffing at 0% of revenue leaves room for facilities, programs, and reserves. | F32: As you add staff, ensure staffing stays below 60% of revenue.
B33: Facility Burden | C33: ● Healthy | D33: Facility costs at 0% of revenue are well-managed and leave budget for programs. | F33: Watch for rent escalation clauses that could push this higher over time.
B34: Revenue Concentration | C34: ● Healthy | D34: Revenue is anchored to enrollment-driven income — the strongest foundation for a school model. A focused revenue stream is a strength when backed by dependable demand. | F34: Continue to pressure-test enrollment assumptions: recruitment pipeline, waitlist depth, retention rates, and collection reliability.
B35: Reserve Strength | C35: ○ Needs attention | D35: Less than 1 month of reserves by Year 5. The school has no financial cushion. | F35: Prioritize building reserves — even a small surplus each year compounds into meaningful protection.
B37: Summary | C37: 3 Healthy | 2 Watch | 1 Needs Attention
B39: Built by SchoolStack Budget • budget.schoolstack.ai
