Workbook

Sheet Cover
B3: SchoolStack Budget
B4: 5-Year Financial Model
B8: Prepared for
B9: Bright Horizons Microschool
B10: Microschool • LLC - Single Member • TX
B12: Date Prepared | C12: March 25, 2026
B15: KEY HIGHLIGHTS
B16: Year 5 Revenue | C16: 350000
B17: Year 5 Net Income | C17: 227367
B18: Year 5 Net Margin | C18: 0.64962
B19: Operating Reserve (Months) | C19: 71.887371
B20: Year 5 Enrollment | C20: 40
B22: Lender Readiness | C22: Strong
B25: TABLE OF CONTENTS
B26: Assumptions
B27: Revenue Schedule
B28: Staffing & Personnel
B29: Operating Expenses
B30: Capital & Debt
B31: Financial Model
B32: Summary
B33: Consultant Notes
B36: Generated by SchoolStack Budget • budget.schoolstack.ai

Sheet Assumptions
A1: SchoolStack Budget - Assumptions
A3: SCHOOL INFORMATION
A4: School Name | B4: Bright Horizons Microschool
A5: State | B5: TX
A6: School Type | B6: Microschool
A7: Entity Type | B7: LLC - Single Member
A8: School Stage | B8: New School
A9: Opening Year | B9: 0
A10: Current Students | B10: 0
A11: Max Student Capacity | B11: 40
A12: Fiscal Year Start | B12: July
A13: Year 1 Operating Months | B13: 10
A14: Location Secured | B14: Yes
A15: Facility Ownership | B15: Rented / Leased
A16: Monthly Rent | B16: $2,500
A17: Annual Rent Escalation | B17: 3%
A19: ENROLLMENT BY YEAR
A20: Year 1 Students | B20: 15
A21: Year 2 Students | B21: 22
A22: Year 3 Students | B22: 30
A23: Year 4 Students | B23: 35
A24: Year 5 Students | B24: 40
A26: GROWTH & ESCALATION ASSUMPTIONS
A27: Annual Salary Escalation | B27: 0
A28: General Cost Inflation | B28: 0
A29: Year 1 Proration Factor | B29: 0.83333333
A30: Projection Period | B30: 5 Years

Sheet Revenue Schedule
B1: Year 1 | C1: Year 2 | D1: Year 3 | E1: Year 4 | F1: Year 5
A2: Students | B2: =Assumptions!B20 -> 15 | C2: =Assumptions!B21 -> 22 | D2: =Assumptions!B22 -> 30 | E2: =Assumptions!B23 -> 35 | F2: =Assumptions!B24 -> 40
A3: TUITION & STUDENT FEES
A4: Annual Tuition | B4: =8500*Assumptions!B20 -> 127500 | C4: =8500*Assumptions!B21 -> 187000 | D4: =8500*Assumptions!B22 -> 255000 | E4: =8500*Assumptions!B23 -> 297500 | F4: =8500*Assumptions!B24 -> 340000
A5: Total TUITION & STUDENT FEES | B5: =SUM(B4:B4) -> 127500 | C5: =SUM(C4:C4) -> 187000 | D5: =SUM(D4:D4) -> 255000 | E5: =SUM(E4:E4) -> 297500 | F5: =SUM(F4:F4) -> 340000
A6: PHILANTHROPY
A7: Community Donations | B7: 25000 | C7: 20000 | D7: 15000 | E7: 12000 | F7: 10000
A8: Startup Grant | B8: 15000 | C8: 10000 | D8: 5000 | E8: 0 | F8: 0
A9: Total PHILANTHROPY | B9: =SUM(B7:B8) -> 25000 | C9: =SUM(C7:C8) -> 20000 | D9: =SUM(D7:D8) -> 15000 | E9: =SUM(E7:E8) -> 12000 | F9: =SUM(F7:F8) -> 10000
A11: TOTAL NET REVENUE | B11: =B5+B9 -> 167500 | C11: =C5+C9 -> 217000 | D11: =D5+D9 -> 275000 | E11: =E5+E9 -> 309500 | F11: =F5+F9 -> 350000

Sheet Staffing & Personnel
A1: SchoolStack Budget - Staffing & Personnel
A3: Role | B3: Function | C3: Type | D3: FTE | E3: Annual Rate | F3: Benefits % | G3: Payroll Tax % | H3: Total Annual Cost
A4: Lead Teacher / Founder | B4: Instructional | C4: Full-Time | D4: 1 | E4: 52000 | F4: 0 | G4: 0.0765 | H4: 55978
A5: Assistant Teacher | B5: Instructional | C5: Part-Time | D5: 0.75 | E5: 28000 | F5: 0 | G5: 0.0765 | H5: 22606.5
A6: Part-Time Aide | B6: Student Support | C6: Part-Time | D6: 0.5 | E6: 18000 | F6: 0 | G6: 0.0765 | H6: 9688.5
A8: PERSONNEL COST SUMMARY
A9: Total Headcount | B9: 3
A10: Total FTE | B10: 2.3
A11: Salaries & Wages | B11: 82000
A12: Benefits | B12: 0
A13: Payroll Taxes | B13: 6273
A14: Contracted Personnel | B14: 0
A15: Total Annual Personnel Cost | B15: 88273
A17: PERSONNEL COST PROJECTION
B18: Year 1 | C18: Year 2 | D18: Year 3 | E18: Year 4 | F18: Year 5
A19: Base Personnel Cost | B19: 88273 | C19: 88273 | D19: 88273 | E19: 88273 | F19: 88273
A20: Salary Escalation Factor | B20: =(1+Assumptions!B27)^0 -> 1 | C20: =(1+Assumptions!B27)^1 -> 1 | D20: =(1+Assumptions!B27)^2 -> 1 | E20: =(1+Assumptions!B27)^3 -> 1 | F20: =(1+Assumptions!B27)^4 -> 1
A21: Proration Factor | B21: =Assumptions!B29 -> 0.83333333 | C21: 1 | D21: 1 | E21: 1 | F21: 1
A22: Total Personnel Cost | B22: =B19*B20*B21 -> 73561 | C22: =C19*C20*C21 -> 88273 | D22: =D19*D20*D21 -> 88273 | E22: =E19*E20*E21 -> 88273 | F22: =F19*F20*F21 -> 88273

Sheet Operating Expenses
B1: Year 1 | C1: Year 2 | D1: Year 3 | E1: Year 4 | F1: Year 5
A2: Students | B2: =Assumptions!B20 -> 15 | C2: =Assumptions!B21 -> 22 | D2: =Assumptions!B22 -> 30 | E2: =Assumptions!B23 -> 35 | F2: =Assumptions!B24 -> 40
A3: INSTRUCTIONAL / PROGRAM
A4: Curriculum & Materials | B4: =400*Assumptions!B20 -> 6000 | C4: =400*Assumptions!B21 -> 8800 | D4: =400*Assumptions!B22 -> 12000 | E4: =400*Assumptions!B23 -> 14000 | F4: =400*Assumptions!B24 -> 16000
A5: Total INSTRUCTIONAL | B5: =SUM(B4:B4) -> 6000 | C5: =SUM(C4:C4) -> 8800 | D5: =SUM(D4:D4) -> 12000 | E5: =SUM(E4:E4) -> 14000 | F5: =SUM(F4:F4) -> 16000
A6: TECHNOLOGY
A7: Technology & Software | B7: 3000 | C7: 3200 | D7: 3400 | E7: 3600 | F7: 3800
A8: Total TECHNOLOGY | B8: =SUM(B7:B7) -> 3000 | C8: =SUM(C7:C7) -> 3200 | D8: =SUM(D7:D7) -> 3400 | E8: =SUM(E7:E7) -> 3600 | F8: =SUM(F7:F7) -> 3800
A9: OCCUPANCY / FACILITY
A10: Utilities | B10: =350*12 -> 4200 | C10: =370*12 -> 4440 | D10: =390*12 -> 4680 | E10: =410*12 -> 4920 | F10: =430*12 -> 5160
A11: Total OCCUPANCY | B11: =SUM(B10:B10) -> 4200 | C11: =SUM(C10:C10) -> 4440 | D11: =SUM(D10:D10) -> 4680 | E11: =SUM(E10:E10) -> 4920 | F11: =SUM(F10:F10) -> 5160
A12: ADMINISTRATIVE / GENERAL
A13: General Liability Insurance | B13: 2400 | C13: 2500 | D13: 2600 | E13: 2700 | F13: 2800
A14: Marketing & Outreach | B14: 2000 | C14: 1500 | D14: 1200 | E14: 1000 | F14: 800
A15: Total ADMINISTRATIVE | B15: =SUM(B13:B14) -> 4400 | C15: =SUM(C13:C14) -> 4000 | D15: =SUM(D13:D14) -> 3800 | E15: =SUM(E13:E14) -> 3700 | F15: =SUM(F13:F14) -> 3600
A17: TOTAL OPERATING EXPENSES | B17: =B5+B8+B11+B15 -> 17600 | C17: =C5+C8+C11+C15 -> 20440 | D17: =D5+D8+D11+D15 -> 23880 | E17: =E5+E8+E11+E15 -> 26220 | F17: =F5+F8+F11+F15 -> 28560

Sheet Capital & Debt
B1: Year 1 | C1: Year 2 | D1: Year 3 | E1: Year 4 | F1: Year 5
A2: CAPITAL EXPENDITURES & DEBT SERVICE
A3: Startup Equipment & Furnishing | B3: 12000 | C3: 0 | D3: 0 | E3: 0 | F3: 0
A4: Microschool Microloan | B4: 5799.8405 | C4: 5799.8405 | D4: 5799.8405 | E4: 5799.8405 | F4: 5799.8405
A5: TOTAL CAPITAL & DEBT | B5: =SUM(B3:B4) -> 17800 | C5: =SUM(C3:C4) -> 5800 | D5: =SUM(D3:D4) -> 5800 | E5: =SUM(E3:E4) -> 5800 | F5: =SUM(F3:F4) -> 5800

Sheet Financial Model
A1: 5-Year Financial Model | B1: Year 1 | C1: Year 2 | D1: Year 3 | E1: Year 4 | F1: Year 5
A2: Total Revenue | B2: ='Revenue Schedule'!B11 -> 167500 | C2: ='Revenue Schedule'!C11 -> 217000 | D2: ='Revenue Schedule'!D11 -> 275000 | E2: ='Revenue Schedule'!E11 -> 309500 | F2: ='Revenue Schedule'!F11 -> 350000
A3: Personnel Costs | B3: ='Staffing & Personnel'!B22 -> 73561 | C3: ='Staffing & Personnel'!C22 -> 88273 | D3: ='Staffing & Personnel'!D22 -> 88273 | E3: ='Staffing & Personnel'!E22 -> 88273 | F3: ='Staffing & Personnel'!F22 -> 88273
A4: Operating Expenses | B4: ='Operating Expenses'!B17 -> 17600 | C4: ='Operating Expenses'!C17 -> 20440 | D4: ='Operating Expenses'!D17 -> 23880 | E4: ='Operating Expenses'!E17 -> 26220 | F4: ='Operating Expenses'!F17 -> 28560
A5: Capital & Debt | B5: ='Capital & Debt'!B5 -> 17800 | C5: ='Capital & Debt'!C5 -> 5800 | D5: ='Capital & Debt'!D5 -> 5800 | E5: ='Capital & Debt'!E5 -> 5800 | F5: ='Capital & Debt'!F5 -> 5800
A6: Total Expenses | B6: =B3+B4+B5 -> 108961 | C6: =C3+C4+C5 -> 114513 | D6: =D3+D4+D5 -> 117953 | E6: =E3+E4+E5 -> 120293 | F6: =F3+F4+F5 -> 122633
A7: Profit | B7: =B2-B6 -> 58539 | C7: =C2-C6 -> 102487 | D7: =D2-D6 -> 157047 | E7: =E2-E6 -> 189207 | F7: =F2-F6 -> 227367
A8: Cumulative Profit | B8: =B7 -> 58539 | C8: =B8+C7 -> 161026 | D8: =C8+D7 -> 318073 | E8: =D8+E7 -> 507280 | F8: =E8+F7 -> 734647
A9: Operating Reserve (Months) | B9: =IF(B6=0,0,IF(B8>0,B8/(B6/12),0)) -> 6.4469673 | C9: =IF(C6=0,0,IF(C8>0,C8/(C6/12),0)) -> 16.874171 | D9: =IF(D6=0,0,IF(D8>0,D8/(D6/12),0)) -> 32.359296 | E9: =IF(E6=0,0,IF(E8>0,E8/(E6/12),0)) -> 50.604441 | F9: =IF(F6=0,0,IF(F8>0,F8/(F6/12),0)) -> 71.887371

Sheet Summary
A1: Financial Model Summary
A2: Prepared by SchoolStack Budget
A4: SCHOOL INFORMATION
A5: School Name | B5: Bright Horizons Microschool
A6: School Type | B6: Microschool
A7: Entity Type | B7: LLC - Single Member
A8: School Stage | B8: New School
A9: State | B9: TX
A10: Fiscal Year Start | B10: July
A11: Max Student Capacity | B11: 40
A13: ENROLLMENT TREND
B14: Year 1 | C14: Year 2 | D14: Year 3 | E14: Year 4 | F14: Year 5
A15: Students | B15: ='Revenue Schedule'!B2 -> 15 | C15: ='Revenue Schedule'!C2 -> 22 | D15: ='Revenue Schedule'!D2 -> 30 | E15: ='Revenue Schedule'!E2 -> 35 | F15: ='Revenue Schedule'!F2 -> 40
A16: Enrollment Growth % | B16: - | C16: =IF(B15=0,0,(C15-B15)/B15) -> 0.46666667 | D16: =IF(C15=0,0,(D15-C15)/C15) -> 0.36363636 | E16: =IF(D15=0,0,(E15-D15)/D15) -> 0.16666667 | F16: =IF(E15=0,0,(F15-E15)/E15) -> 0.14285714
B18: Year 1 | C18: Year 2 | D18: Year 3 | E18: Year 4 | F18: Year 5
A19: Total Revenue | B19: ='Financial Model'!B2 -> 167500 | C19: ='Financial Model'!C2 -> 217000 | D19: ='Financial Model'!D2 -> 275000 | E19: ='Financial Model'!E2 -> 309500 | F19: ='Financial Model'!F2 -> 350000
A20: Personnel Costs | B20: ='Financial Model'!B3 -> 73561 | C20: ='Financial Model'!C3 -> 88273 | D20: ='Financial Model'!D3 -> 88273 | E20: ='Financial Model'!E3 -> 88273 | F20: ='Financial Model'!F3 -> 88273
A21: Operating Expenses | B21: ='Financial Model'!B4 -> 17600 | C21: ='Financial Model'!C4 -> 20440 | D21: ='Financial Model'!D4 -> 23880 | E21: ='Financial Model'!E4 -> 26220 | F21: ='Financial Model'!F4 -> 28560
A22: Total Expenses | B22: ='Financial Model'!B6 -> 108961 | C22: ='Financial Model'!C6 -> 114513 | D22: ='Financial Model'!D6 -> 117953 | E22: ='Financial Model'!E6 -> 120293 | F22: ='Financial Model'!F6 -> 122633
A23: Profit | B23: ='Financial Model'!B7 -> 58539 | C23: ='Financial Model'!C7 -> 102487 | D23: ='Financial Model'!D7 -> 157047 | E23: ='Financial Model'!E7 -> 189207 | F23: ='Financial Model'!F7 -> 227367
A24: Cumulative Profit | B24: ='Financial Model'!B8 -> 58539 | C24: ='Financial Model'!C8 -> 161026 | D24: ='Financial Model'!D8 -> 318073 | E24: ='Financial Model'!E8 -> 507280 | F24: ='Financial Model'!F8 -> 734647
A25: Operating Reserve (Months) | B25: ='Financial Model'!B9 -> 6.4469673 | C25: ='Financial Model'!C9 -> 16.874171 | D25: ='Financial Model'!D9 -> 32.359296 | E25: ='Financial Model'!E9 -> 50.604441 | F25: ='Financial Model'!F9 -> 71.887371
A27: KEY RATIOS
A28: Revenue per Student | B28: =IF('Revenue Schedule'!B2=0,0,B19/'Revenue Schedule'!B2) -> 11166.667 | C28: =IF('Revenue Schedule'!C2=0,0,C19/'Revenue Schedule'!C2) -> 9863.6364 | D28: =IF('Revenue Schedule'!D2=0,0,D19/'Revenue Schedule'!D2) -> 9166.6667 | E28: =IF('Revenue Schedule'!E2=0,0,E19/'Revenue Schedule'!E2) -> 8842.8571 | F28: =IF('Revenue Schedule'!F2=0,0,F19/'Revenue Schedule'!F2) -> 8750
A29: Personnel Cost as % of Revenue | B29: =IF(B19=0,0,'Financial Model'!B3/B19) -> 0.43917015 | C29: =IF(C19=0,0,'Financial Model'!C3/C19) -> 0.40678802 | D29: =IF(D19=0,0,'Financial Model'!D3/D19) -> 0.32099273 | E29: =IF(E19=0,0,'Financial Model'!E3/E19) -> 0.28521163 | F29: =IF(F19=0,0,'Financial Model'!F3/F19) -> 0.25220857
A30: Operating Cost as % of Revenue | B30: =IF(B19=0,0,'Financial Model'!B4/B19) -> 0.10507463 | C30: =IF(C19=0,0,'Financial Model'!C4/C19) -> 0.094193548 | D30: =IF(D19=0,0,'Financial Model'!D4/D19) -> 0.086836364 | E30: =IF(E19=0,0,'Financial Model'!E4/E19) -> 0.084717286 | F30: =IF(F19=0,0,'Financial Model'!F4/F19) -> 0.0816
A31: Profit Margin % | B31: =IF(B19=0,0,B23/B19) -> 0.34948657 | C31: =IF(C19=0,0,C23/C19) -> 0.47229032 | D31: =IF(D19=0,0,D23/D19) -> 0.57108 | E31: =IF(E19=0,0,E23/E19) -> 0.61133118 | F31: =IF(F19=0,0,F23/F19) -> 0.64962
A33: REVENUE MIX TREND
A34: Tuition & Fees % | B34: 0.76119403 | C34: 0.86175115 | D34: 0.92727273 | E34: 0.96122779 | F34: 0.97142857
A35: Public Funding % | B35: 0 | C35: 0 | D35: 0 | E35: 0 | F35: 0
A36: Philanthropy % | B36: 0.23880597 | C36: 0.13824885 | D36: 0.072727273 | E36: 0.038772213 | F36: 0.028571429
A38: LENDER READINESS ASSESSMENT
A39: Readiness Status | B39: Strong
A40: Assessment | B40: This model demonstrates strong financial fundamentals: a clear path to profit, controlled costs, a sustainable revenue mix, and adequate debt coverage. Your projections are grounded and achievable.
A41: Biggest Strength | B41: Strong Year 5 profit
A42: Biggest Risk | B42: No major red flags detected, so continue refining assumptions as you gather real data.

Sheet Consultant Notes
A1: SchoolStack Budget - Consultant Notes
A3: EXECUTIVE SUMMARY
A4: Bright Horizons Microschool projects $392,673 in Year 5 revenue with a 61.1% profit margin. The model tells a strong financial story with 8 of 10 key metrics in healthy range, a great foundation for your mission.
A6: LENDER READINESS
A7: Status | B7: Strong
A8: Assessment | B8: This model demonstrates strong financial fundamentals: a clear path to profit, controlled costs, a sustainable revenue mix, and adequate debt coverage. Your projections are grounded and achievable.
A10: Biggest Strength | B10: Strong Year 5 profit
A11: Biggest Risk | B11: No major red flags detected, so continue refining assumptions as you gather real data.
A13: RECOMMENDATIONS
A14: [MEDIUM] Build a Cash Reserve
A15: Even with healthy projections, aim to build 3–6 months of operating expenses as a reserve fund. This gives you a safety net for unexpected expenses and keeps your school financially resilient.
A16: [MEDIUM] Stress-Test Your Enrollment Assumptions
A17: Model what happens if enrollment comes in 20% below plan. Understanding your downside scenario helps you prepare contingency plans.
A18: [LOW] Document Your Growth Strategy
A19: Great projections are backed by a clear plan. Document your marketing strategy, enrollment pipeline, and community outreach, as this is the roadmap that turns your numbers into reality.
