Workbook

Sheet Cover
B3: SchoolStack Budget
B4: 5-Year Financial Model
B8: Prepared for
B9: Riverside Christian Academy
B10: Private School • 501(c)(3) Nonprofit • FL
B12: Date Prepared | C12: March 25, 2026
B15: KEY HIGHLIGHTS
B16: Year 5 Revenue | C16: 5630000
B17: Year 5 Net Income | C17: 4564821
B18: Year 5 Net Margin | C18: 0.81080302
B19: Operating Reserve (Months) | C19: 185.23202
B20: Year 5 Enrollment | C20: 400
B22: Lender Readiness | C22: Strong
B25: TABLE OF CONTENTS
B26: Assumptions
B27: Revenue Schedule
B28: Staffing & Personnel
B29: Operating Expenses
B30: Capital & Debt
B31: Financial Model
B32: Summary
B33: Consultant Notes
B34: Prior-Year Snapshot
B37: Generated by SchoolStack Budget • budget.schoolstack.ai

Sheet Assumptions
A1: SchoolStack Budget - Assumptions
A3: SCHOOL INFORMATION
A4: School Name | B4: Riverside Christian Academy
A5: State | B5: FL
A6: School Type | B6: Private School
A7: Entity Type | B7: 501(c)(3) Nonprofit
A8: School Stage | B8: Operating School
A9: Opening Year | B9: 2023
A10: Current Students | B10: 185
A11: Max Student Capacity | B11: 400
A12: Fiscal Year Start | B12: July
A13: Accredited | B13: No
A14: Location Secured | B14: Yes
A15: Facility Ownership | B15: Owned
A16: Monthly Mortgage Payment | B16: $8,500
A18: ENROLLMENT BY YEAR
A19: Year 1 Students | B19: 200
A20: Year 2 Students | B20: 250
A21: Year 3 Students | B21: 300
A22: Year 4 Students | B22: 350
A23: Year 5 Students | B23: 400
A25: GROWTH & ESCALATION ASSUMPTIONS
A26: Annual Salary Escalation | B26: 0
A27: General Cost Inflation | B27: 0
A28: Year 1 Proration Factor | B28: 1
A29: Projection Period | B29: 5 Years

Sheet Revenue Schedule
B1: Year 1 | C1: Year 2 | D1: Year 3 | E1: Year 4 | F1: Year 5
A2: Students | B2: =Assumptions!B19 -> 200 | C2: =Assumptions!B20 -> 250 | D2: =Assumptions!B21 -> 300 | E2: =Assumptions!B22 -> 350 | F2: =Assumptions!B23 -> 400
A3: TUITION & STUDENT FEES
A4: Annual Tuition (K-8) | B4: =12500*Assumptions!B19 -> 2500000 | C4: =12500*Assumptions!B20 -> 3125000 | D4: =12500*Assumptions!B21 -> 3750000 | E4: =12500*Assumptions!B22 -> 4375000 | F4: =12500*Assumptions!B23 -> 5000000
A5: Registration & Activity Fees | B5: =750*Assumptions!B19 -> 150000 | C5: =750*Assumptions!B20 -> 187500 | D5: =750*Assumptions!B21 -> 225000 | E5: =750*Assumptions!B22 -> 262500 | F5: =750*Assumptions!B23 -> 300000
A6: Total TUITION & STUDENT FEES | B6: =SUM(B4:B5) -> 2650000 | C6: =SUM(C4:C5) -> 3312500 | D6: =SUM(D4:D5) -> 3975000 | E6: =SUM(E4:E5) -> 4637500 | F6: =SUM(F4:F5) -> 5300000
A7: PHILANTHROPY
A8: Annual Fund Donations | B8: 75000 | C8: 85000 | D8: 95000 | E8: 100000 | F8: 110000
A9: Foundation Grants | B9: 50000 | C9: 40000 | D9: 30000 | E9: 25000 | F9: 20000
A10: Total PHILANTHROPY | B10: =SUM(B8:B9) -> 75000 | C10: =SUM(C8:C9) -> 85000 | D10: =SUM(D8:D9) -> 95000 | E10: =SUM(E8:E9) -> 100000 | F10: =SUM(F8:F9) -> 110000
A11: OTHER REVENUE
A12: After-School Programs | B12: =500*Assumptions!B19 -> 100000 | C12: =500*Assumptions!B20 -> 125000 | D12: =500*Assumptions!B21 -> 150000 | E12: =500*Assumptions!B22 -> 175000 | F12: =500*Assumptions!B23 -> 200000
A13: Total OTHER REVENUE | B13: =SUM(B12:B12) -> 100000 | C13: =SUM(C12:C12) -> 125000 | D13: =SUM(D12:D12) -> 150000 | E13: =SUM(E12:E12) -> 175000 | F13: =SUM(F12:F12) -> 200000
A15: TOTAL NET REVENUE | B15: =B6+B10+B13 -> 2875000 | C15: =C6+C10+C13 -> 3562500 | D15: =D6+D10+D13 -> 4250000 | E15: =E6+E10+E13 -> 4937500 | F15: =F6+F10+F13 -> 5630000

Sheet Staffing & Personnel
A1: SchoolStack Budget - Staffing & Personnel
A3: Role | B3: Function | C3: Type | D3: FTE | E3: Annual Rate | F3: Benefits % | G3: Payroll Tax % | H3: Total Annual Cost
A4: Head of School | B4: School Leadership | C4: Full-Time | D4: 1 | E4: 95000 | F4: 0.22 | G4: 0.0765 | H4: 123167.5
A5: Assistant Principal | B5: School Leadership | C5: Full-Time | D5: 1 | E5: 72000 | F5: 0.22 | G5: 0.0765 | H5: 93348
A6: Lead Teachers (K-8) | B6: Instructional | C6: Full-Time | D6: 1 | E6: 48000 | F6: 0.2 | G6: 0.0765 | H6: 61272
A7: Teaching Assistants | B7: Instructional | C7: Full-Time | D7: 1 | E7: 30000 | F7: 0.15 | G7: 0.0765 | H7: 36795
A8: Counselor | B8: Student Support | C8: Full-Time | D8: 1 | E8: 55000 | F8: 0.2 | G8: 0.0765 | H8: 70207.5
A9: Maintenance / Custodial | B9: Operations | C9: Full-Time | D9: 1 | E9: 32000 | F9: 0 | G9: 0.0765 | H9: 34448
A10: Office Manager | B10: Administrative | C10: Full-Time | D10: 1 | E10: 42000 | F10: 0.2 | G10: 0.0765 | H10: 53613
A12: PERSONNEL COST SUMMARY
A13: Total Headcount | B13: 7
A14: Total FTE | B14: 7
A15: Salaries & Wages | B15: 374000
A16: Benefits | B16: 70240
A17: Payroll Taxes | B17: 28611
A18: Contracted Personnel | B18: 0
A19: Total Annual Personnel Cost | B19: 472851
A21: PERSONNEL COST PROJECTION
B22: Year 1 | C22: Year 2 | D22: Year 3 | E22: Year 4 | F22: Year 5
A23: Base Personnel Cost | B23: 472851 | C23: 472851 | D23: 472851 | E23: 472851 | F23: 472851
A24: Salary Escalation Factor | B24: =(1+Assumptions!B26)^0 -> 1 | C24: =(1+Assumptions!B26)^1 -> 1 | D24: =(1+Assumptions!B26)^2 -> 1 | E24: =(1+Assumptions!B26)^3 -> 1 | F24: =(1+Assumptions!B26)^4 -> 1
A25: Proration Factor | B25: =Assumptions!B28 -> 1 | C25: 1 | D25: 1 | E25: 1 | F25: 1
A26: Total Personnel Cost | B26: =B23*B24*B25 -> 472851 | C26: =C23*C24*C25 -> 472851 | D26: =D23*D24*D25 -> 472851 | E26: =E23*E24*E25 -> 472851 | F26: =F23*F24*F25 -> 472851

Sheet Operating Expenses
B1: Year 1 | C1: Year 2 | D1: Year 3 | E1: Year 4 | F1: Year 5
A2: Students | B2: =Assumptions!B19 -> 200 | C2: =Assumptions!B20 -> 250 | D2: =Assumptions!B21 -> 300 | E2: =Assumptions!B22 -> 350 | F2: =Assumptions!B23 -> 400
A3: INSTRUCTIONAL / PROGRAM
A4: Curriculum & Textbooks | B4: =600*Assumptions!B19 -> 120000 | C4: =600*Assumptions!B20 -> 150000 | D4: =600*Assumptions!B21 -> 180000 | E4: =600*Assumptions!B22 -> 210000 | F4: =600*Assumptions!B23 -> 240000
A5: Professional Development | B5: 8000 | C5: 10000 | D5: 12000 | E5: 14000 | F5: 15000
A6: Total INSTRUCTIONAL | B6: =SUM(B4:B5) -> 128000 | C6: =SUM(C4:C5) -> 160000 | D6: =SUM(D4:D5) -> 192000 | E6: =SUM(E4:E5) -> 224000 | F6: =SUM(F4:F5) -> 255000
A7: TECHNOLOGY
A8: Technology (Devices + Software) | B8: =350*Assumptions!B19 -> 70000 | C8: =350*Assumptions!B20 -> 87500 | D8: =350*Assumptions!B21 -> 105000 | E8: =350*Assumptions!B22 -> 122500 | F8: =350*Assumptions!B23 -> 140000
A9: Total TECHNOLOGY | B9: =SUM(B8:B8) -> 70000 | C9: =SUM(C8:C8) -> 87500 | D9: =SUM(D8:D8) -> 105000 | E9: =SUM(E8:E8) -> 122500 | F9: =SUM(F8:F8) -> 140000
A10: OCCUPANCY / FACILITY
A11: Utilities & Maintenance | B11: 36000 | C11: 38000 | D11: 40000 | E11: 42000 | F11: 44000
A12: Total OCCUPANCY | B12: =SUM(B11:B11) -> 36000 | C12: =SUM(C11:C11) -> 38000 | D12: =SUM(D11:D11) -> 40000 | E12: =SUM(E11:E11) -> 42000 | F12: =SUM(F11:F11) -> 44000
A13: ADMINISTRATIVE / GENERAL
A14: Insurance (General + D&O) | B14: 18000 | C14: 19000 | D14: 20000 | E14: 21000 | F14: 22000
A15: Marketing & Enrollment | B15: 15000 | C15: 12000 | D15: 10000 | E15: 8000 | F15: 8000
A16: Accounting & Legal | B16: 12000 | C16: 12500 | D16: 13000 | E16: 13500 | F16: 14000
A17: Total ADMINISTRATIVE | B17: =SUM(B14:B16) -> 45000 | C17: =SUM(C14:C16) -> 43500 | D17: =SUM(D14:D16) -> 43000 | E17: =SUM(E14:E16) -> 42500 | F17: =SUM(F14:F16) -> 44000
A19: TOTAL OPERATING EXPENSES | B19: =B6+B9+B12+B17 -> 279000 | C19: =C6+C9+C12+C17 -> 329000 | D19: =D6+D9+D12+D17 -> 380000 | E19: =E6+E9+E12+E17 -> 431000 | F19: =F6+F9+F12+F17 -> 483000

Sheet Capital & Debt
B1: Year 1 | C1: Year 2 | D1: Year 3 | E1: Year 4 | F1: Year 5
A2: CAPITAL EXPENDITURES & DEBT SERVICE
A3: Building Mortgage | B3: 88428.599 | C3: 88428.599 | D3: 88428.599 | E3: 88428.599 | F3: 88428.599
A4: Renovation Loan | B4: 20899.526 | C4: 20899.526 | D4: 20899.526 | E4: 20899.526 | F4: 20899.526
A5: TOTAL CAPITAL & DEBT | B5: =SUM(B3:B4) -> 109328 | C5: =SUM(C3:C4) -> 109328 | D5: =SUM(D3:D4) -> 109328 | E5: =SUM(E3:E4) -> 109328 | F5: =SUM(F3:F4) -> 109328

Sheet Financial Model
A1: 5-Year Financial Model | B1: Year 1 | C1: Year 2 | D1: Year 3 | E1: Year 4 | F1: Year 5
A2: Total Revenue | B2: ='Revenue Schedule'!B15 -> 2875000 | C2: ='Revenue Schedule'!C15 -> 3562500 | D2: ='Revenue Schedule'!D15 -> 4250000 | E2: ='Revenue Schedule'!E15 -> 4937500 | F2: ='Revenue Schedule'!F15 -> 5630000
A3: Personnel Costs | B3: ='Staffing & Personnel'!B26 -> 472851 | C3: ='Staffing & Personnel'!C26 -> 472851 | D3: ='Staffing & Personnel'!D26 -> 472851 | E3: ='Staffing & Personnel'!E26 -> 472851 | F3: ='Staffing & Personnel'!F26 -> 472851
A4: Operating Expenses | B4: ='Operating Expenses'!B19 -> 279000 | C4: ='Operating Expenses'!C19 -> 329000 | D4: ='Operating Expenses'!D19 -> 380000 | E4: ='Operating Expenses'!E19 -> 431000 | F4: ='Operating Expenses'!F19 -> 483000
A5: Capital & Debt | B5: ='Capital & Debt'!B5 -> 109328 | C5: ='Capital & Debt'!C5 -> 109328 | D5: ='Capital & Debt'!D5 -> 109328 | E5: ='Capital & Debt'!E5 -> 109328 | F5: ='Capital & Debt'!F5 -> 109328
A6: Total Expenses | B6: =B3+B4+B5 -> 861179 | C6: =C3+C4+C5 -> 911179 | D6: =D3+D4+D5 -> 962179 | E6: =E3+E4+E5 -> 1013179 | F6: =F3+F4+F5 -> 1065179
A7: Net Income | B7: =B2-B6 -> 2013821 | C7: =C2-C6 -> 2651321 | D7: =D2-D6 -> 3287821 | E7: =E2-E6 -> 3924321 | F7: =F2-F6 -> 4564821
A8: Cumulative Net Income | B8: =B7 -> 2013821 | C8: =B8+C7 -> 4665142 | D8: =C8+D7 -> 7952963 | E8: =D8+E7 -> 11877284 | F8: =E8+F7 -> 16442105
A9: Operating Reserve (Months) | B9: =IF(B6=0,0,IF(B8>0,B8/(B6/12),0)) -> 28.061358 | C9: =IF(C6=0,0,IF(C8>0,C8/(C6/12),0)) -> 61.438756 | D9: =IF(D6=0,0,IF(D8>0,D8/(D6/12),0)) -> 99.186904 | E9: =IF(E6=0,0,IF(E8>0,E8/(E6/12),0)) -> 140.67347 | F9: =IF(F6=0,0,IF(F8>0,F8/(F6/12),0)) -> 185.23202

Sheet Summary
A1: Financial Model Summary
A2: Prepared by SchoolStack Budget
A4: SCHOOL INFORMATION
A5: School Name | B5: Riverside Christian Academy
A6: School Type | B6: Private School
A7: Entity Type | B7: 501(c)(3) Nonprofit
A8: School Stage | B8: Operating School
A9: State | B9: FL
A10: Fiscal Year Start | B10: July
A11: Max Student Capacity | B11: 400
A13: ENROLLMENT TREND
B14: Year 1 | C14: Year 2 | D14: Year 3 | E14: Year 4 | F14: Year 5
A15: Students | B15: ='Revenue Schedule'!B2 -> 200 | C15: ='Revenue Schedule'!C2 -> 250 | D15: ='Revenue Schedule'!D2 -> 300 | E15: ='Revenue Schedule'!E2 -> 350 | F15: ='Revenue Schedule'!F2 -> 400
A16: Enrollment Growth % | B16: - | C16: =IF(B15=0,0,(C15-B15)/B15) -> 0.25 | D16: =IF(C15=0,0,(D15-C15)/C15) -> 0.2 | E16: =IF(D15=0,0,(E15-D15)/D15) -> 0.16666667 | F16: =IF(E15=0,0,(F15-E15)/E15) -> 0.14285714
B18: Year 1 | C18: Year 2 | D18: Year 3 | E18: Year 4 | F18: Year 5
A19: Total Revenue | B19: ='Financial Model'!B2 -> 2875000 | C19: ='Financial Model'!C2 -> 3562500 | D19: ='Financial Model'!D2 -> 4250000 | E19: ='Financial Model'!E2 -> 4937500 | F19: ='Financial Model'!F2 -> 5630000
A20: Personnel Costs | B20: ='Financial Model'!B3 -> 472851 | C20: ='Financial Model'!C3 -> 472851 | D20: ='Financial Model'!D3 -> 472851 | E20: ='Financial Model'!E3 -> 472851 | F20: ='Financial Model'!F3 -> 472851
A21: Operating Expenses | B21: ='Financial Model'!B4 -> 279000 | C21: ='Financial Model'!C4 -> 329000 | D21: ='Financial Model'!D4 -> 380000 | E21: ='Financial Model'!E4 -> 431000 | F21: ='Financial Model'!F4 -> 483000
A22: Total Expenses | B22: ='Financial Model'!B6 -> 861179 | C22: ='Financial Model'!C6 -> 911179 | D22: ='Financial Model'!D6 -> 962179 | E22: ='Financial Model'!E6 -> 1013179 | F22: ='Financial Model'!F6 -> 1065179
A23: Net Income | B23: ='Financial Model'!B7 -> 2013821 | C23: ='Financial Model'!C7 -> 2651321 | D23: ='Financial Model'!D7 -> 3287821 | E23: ='Financial Model'!E7 -> 3924321 | F23: ='Financial Model'!F7 -> 4564821
A24: Cumulative Net Income | B24: ='Financial Model'!B8 -> 2013821 | C24: ='Financial Model'!C8 -> 4665142 | D24: ='Financial Model'!D8 -> 7952963 | E24: ='Financial Model'!E8 -> 11877284 | F24: ='Financial Model'!F8 -> 16442105
A25: Operating Reserve (Months) | B25: ='Financial Model'!B9 -> 28.061358 | C25: ='Financial Model'!C9 -> 61.438756 | D25: ='Financial Model'!D9 -> 99.186904 | E25: ='Financial Model'!E9 -> 140.67347 | F25: ='Financial Model'!F9 -> 185.23202
A27: KEY RATIOS
A28: Revenue per Student | B28: =IF('Revenue Schedule'!B2=0,0,B19/'Revenue Schedule'!B2) -> 14375 | C28: =IF('Revenue Schedule'!C2=0,0,C19/'Revenue Schedule'!C2) -> 14250 | D28: =IF('Revenue Schedule'!D2=0,0,D19/'Revenue Schedule'!D2) -> 14166.667 | E28: =IF('Revenue Schedule'!E2=0,0,E19/'Revenue Schedule'!E2) -> 14107.143 | F28: =IF('Revenue Schedule'!F2=0,0,F19/'Revenue Schedule'!F2) -> 14075
A29: Personnel Cost as % of Revenue | B29: =IF(B19=0,0,'Financial Model'!B3/B19) -> 0.16446991 | C29: =IF(C19=0,0,'Financial Model'!C3/C19) -> 0.13273011 | D29: =IF(D19=0,0,'Financial Model'!D3/D19) -> 0.11125906 | E29: =IF(E19=0,0,'Financial Model'!E3/E19) -> 0.095767291 | F29: =IF(F19=0,0,'Financial Model'!F3/F19) -> 0.083987744
A30: Operating Cost as % of Revenue | B30: =IF(B19=0,0,'Financial Model'!B4/B19) -> 0.097043478 | C30: =IF(C19=0,0,'Financial Model'!C4/C19) -> 0.092350877 | D30: =IF(D19=0,0,'Financial Model'!D4/D19) -> 0.089411765 | E30: =IF(E19=0,0,'Financial Model'!E4/E19) -> 0.087291139 | F30: =IF(F19=0,0,'Financial Model'!F4/F19) -> 0.085790409
A31: Net Margin % | B31: =IF(B19=0,0,B23/B19) -> 0.70045948 | C31: =IF(C19=0,0,C23/C19) -> 0.74423046 | D31: =IF(D19=0,0,D23/D19) -> 0.77360494 | E31: =IF(E19=0,0,E23/E19) -> 0.79479919 | F31: =IF(F19=0,0,F23/F19) -> 0.81080302
A33: REVENUE MIX TREND
A34: Tuition & Fees % | B34: 0.95652174 | C34: 0.96491228 | D34: 0.97058824 | E34: 0.97468354 | F34: 0.97690941
A35: Public Funding % | B35: 0 | C35: 0 | D35: 0 | E35: 0 | F35: 0
A36: Philanthropy % | B36: 0.043478261 | C36: 0.035087719 | D36: 0.029411765 | E36: 0.025316456 | F36: 0.023090586
A38: LENDER READINESS ASSESSMENT
A39: Readiness Status | B39: Strong
A40: Assessment | B40: This model demonstrates strong financial fundamentals: a clear path to net income, controlled costs, a sustainable revenue mix, and adequate debt coverage. Your projections are grounded and achievable.
A41: Biggest Strength | B41: Strong Year 5 net income
A42: Biggest Risk | B42: No major red flags detected, so continue refining assumptions as you gather real data.

Sheet Consultant Notes
A1: SchoolStack Budget - Consultant Notes
A3: EXECUTIVE SUMMARY
A4: Riverside Christian Academy projects $6,529,124 in Year 5 revenue with a 82.0% net margin. The model tells a strong financial story with 9 of 9 key metrics in healthy range, a great foundation for your mission.
A6: LENDER READINESS
A7: Status | B7: Strong
A8: Assessment | B8: This model demonstrates strong financial fundamentals: a clear path to net income, controlled costs, a sustainable revenue mix, and adequate debt coverage. Your projections are grounded and achievable.
A10: Biggest Strength | B10: Strong Year 5 net income
A11: Biggest Risk | B11: No major red flags detected, so continue refining assumptions as you gather real data.
A13: RECOMMENDATIONS
A14: [LOW] Plan for Tuition Collection & Discount Risk
A15: Private schools face collection risk from late payments, withdrawals, and financial aid shortfalls. With 95.7% of revenue from tuition, build a 5–10% bad debt reserve into your budget. Factor in tuition discount rates for merit/need-based aid and maintain clear enrollment contracts with payment terms.
A16: [HIGH] Address Cash Reserve Deficit from Prior Year
A17: Last year ended with $120,000 in cash, only 0.7 months of expenses. Building reserves to 3+ months should be a priority. Consider a bridge line of credit while growing into net income.
A18: [LOW] Document Your Growth Strategy
A19: Great projections are backed by a clear plan. Document your marketing strategy, enrollment pipeline, and community outreach, as this is the roadmap that turns your numbers into reality.

Sheet Prior-Year Snapshot
A1: Prior-Year Snapshot
A3: PRIOR YEAR ACTUALS
A4: Ending Enrollment | B4: 185
A5: Total Revenue | B5: 2400000
A6: Total Expenses | B6: 2200000
A7: Ending Cash Balance | B7: 120000
A8: Net Income (Prior Year) | B8: 200000
A9: Cash Reserve (Months) | B9: 0.7
