Workbook

Sheet Assumptions
A1: Year 1 Budget Assumptions
B2: Editable assumption — change this value | E2: Calculated — driven by formula
A4: School Name | B4: Liberty Learning Co-Op
A5: School Type | B5: homeschool_coop
A7: KEY ASSUMPTIONS
A8: Enrollment | B8: 15
A9: Salary Escalation | B9: 0.03
A10: Cost Inflation | B10: 0.025
A11: Year 1 Proration Factor | B11: 0.83333333

Sheet Revenue
B1: July | C1: August | D1: September | E1: October | F1: November | G1: December | H1: January | I1: February | J1: March | K1: April | L1: May | M1: June | N1: Year 1 Total
A2: Co-Op Tuition | B2: 9000 | C2: 9000 | D2: 9000 | E2: 9000 | F2: 9000 | G2: 9000 | H2: 9000 | I2: 9000 | J2: 9000 | K2: 9000 | L2: 0 | M2: 0 | N2: =SUM(B2:M2) -> 75000
A3: Materials Fee | B3: 300 | C3: 300 | D3: 300 | E3: 300 | F3: 300 | G3: 300 | H3: 300 | I3: 300 | J3: 300 | K3: 300 | L3: 0 | M3: 0 | N3: =SUM(B3:M3) -> 2500
A4: ESA Revenue | B4: 10500 | C4: 10500 | D4: 10500 | E4: 10500 | F4: 10500 | G4: 10500 | H4: 10500 | I4: 10500 | J4: 10500 | K4: 10500 | L4: 0 | M4: 0 | N4: =SUM(B4:M4) -> 87500
A5: Refundable Tax Credit | B5: 0 | C5: 0 | D5: 0 | E5: 0 | F5: 0 | G5: 0 | H5: 0 | I5: 0 | J5: 0 | K5: 0 | L5: 0 | M5: 0 | N5: =SUM(B5:M5) -> 0
A6: Annual Fundraising | B6: 300 | C6: 300 | D6: 300 | E6: 300 | F6: 300 | G6: 300 | H6: 300 | I6: 300 | J6: 300 | K6: 300 | L6: 0 | M6: 0 | N6: =SUM(B6:M6) -> 2500
A7: TOTAL REVENUE | B7: =SUM(B2:B6) -> 103800 | C7: =SUM(C2:C6) -> 10800 | D7: =SUM(D2:D6) -> 10800 | E7: =SUM(E2:E6) -> 10800 | F7: =SUM(F2:F6) -> 10800 | G7: =SUM(G2:G6) -> 10800 | H7: =SUM(H2:H6) -> 10800 | I7: =SUM(I2:I6) -> 10800 | ... M7: =SUM(M2:M6) -> 0 | N7: =SUM(B7:M7) -> 201000

Sheet Personnel
B1: July | C1: August | D1: September | E1: October | F1: November | G1: December | H1: January | I1: February | J1: March | K1: April | L1: May | M1: June | N1: Year 1 Total
A2: Director / Lead Educator | B2: 114600 | C2: 114600 | D2: 114600 | E2: 114600 | F2: 114600 | G2: 114600 | H2: 114600 | I2: 114600 | J2: 114600 | K2: 114600 | L2: 0 | M2: 0 | N2: =SUM(B2:M2) -> 1146000
A3: Assistant Educator | B3: 10813 | C3: 10813 | D3: 10813 | E3: 10813 | F3: 10813 | G3: 10813 | H3: 10813 | I3: 10813 | J3: 10813 | K3: 10813 | L3: 0 | M3: 0 | N3: =SUM(B3:M3) -> 108125
A4: TOTAL PERSONNEL | B4: =SUM(B2:B3) -> 0 | C4: =SUM(C2:C3) -> 0 | D4: =SUM(D2:D3) -> 0 | E4: =SUM(E2:E3) -> 0 | F4: =SUM(F2:F3) -> 0 | G4: =SUM(G2:G3) -> 0 | H4: =SUM(H2:H3) -> 0 | I4: =SUM(I2:I3) -> 0 | ... M4: =SUM(M2:M3) -> 0 | N4: =SUM(B4:M4) -> 0

Sheet Operating Expenses
B1: July | C1: August | D1: September | E1: October | F1: November | G1: December | H1: January | I1: February | J1: March | K1: April | L1: May | M1: June | N1: Year 1 Total
A2: Rent | B2: 1800 | C2: 1800 | D2: 1800 | E2: 1800 | F2: 1800 | G2: 1800 | H2: 1800 | I2: 1800 | J2: 1800 | K2: 1800 | L2: 0 | M2: 0 | N2: =SUM(B2:M2) -> 18000
A3: Utilities | B3: 200 | C3: 200 | D3: 200 | E3: 200 | F3: 200 | G3: 200 | H3: 200 | I3: 200 | J3: 200 | K3: 200 | L3: 0 | M3: 0 | N3: =SUM(B3:M3) -> 2000
A4: Insurance | B4: 150 | C4: 150 | D4: 150 | E4: 150 | F4: 150 | G4: 150 | H4: 150 | I4: 150 | J4: 150 | K4: 150 | L4: 0 | M4: 0 | N4: =SUM(B4:M4) -> 1500
A5: Curriculum & Materials | B5: 500 | C5: 500 | D5: 500 | E5: 500 | F5: 500 | G5: 500 | H5: 500 | I5: 500 | J5: 500 | K5: 500 | L5: 0 | M5: 0 | N5: =SUM(B5:M5) -> 5000
A6: Technology | B6: 313 | C6: 313 | D6: 313 | E6: 313 | F6: 313 | G6: 313 | H6: 313 | I6: 313 | J6: 313 | K6: 313 | L6: 0 | M6: 0 | N6: =SUM(B6:M6) -> 3125
A7: TOTAL OPERATING EXPENSES | B7: =SUM(B2:B6) -> 0 | C7: =SUM(C2:C6) -> 0 | D7: =SUM(D2:D6) -> 0 | E7: =SUM(E2:E6) -> 0 | F7: =SUM(F2:F6) -> 0 | G7: =SUM(G2:G6) -> 0 | H7: =SUM(H2:H6) -> 0 | I7: =SUM(I2:I6) -> 0 | ... M7: =SUM(M2:M6) -> 0 | N7: =SUM(B7:M7) -> 0

Sheet P&L Summary
B1: July | C1: August | D1: September | E1: October | F1: November | G1: December | H1: January | I1: February | J1: March | K1: April | L1: May | M1: June | N1: Year 1 Total
A2: Total Revenue | B2: =Revenue!B7 -> 103800 | C2: =Revenue!C7 -> 10800 | D2: =Revenue!D7 -> 10800 | E2: =Revenue!E7 -> 10800 | F2: =Revenue!F7 -> 10800 | G2: =Revenue!G7 -> 10800 | H2: =Revenue!H7 -> 10800 | I2: =Revenue!I7 -> 10800 | ... M2: =Revenue!M7 -> 0 | N2: =SUM(B2:M2) -> 201000
A3: Personnel | B3: =Personnel!B4 -> 6452 | C3: =Personnel!C4 -> 6452 | D3: =Personnel!D4 -> 6452 | E3: =Personnel!E4 -> 6452 | F3: =Personnel!F4 -> 6452 | G3: =Personnel!G4 -> 6452 | H3: =Personnel!H4 -> 6452 | I3: =Personnel!I4 -> 6452 | ... M3: =Personnel!M4 -> 0 | N3: =SUM(B3:M3) -> 64516
A4: Operating Expenses | B4: ='Operating Expenses'!B7 -> 2963 | C4: ='Operating Expenses'!C7 -> 2963 | D4: ='Operating Expenses'!D7 -> 2963 | E4: ='Operating Expenses'!E7 -> 2963 | F4: ='Operating Expenses'!F7 -> 2963 | G4: ='Operating Expenses'!G7 -> 2963 | H4: ='Operating Expenses'!H7 -> 2963 | I4: ='Operating Expenses'!I7 -> 2963 | ... M4: ='Operating Expenses'!M7 -> 0 | N4: =SUM(B4:M4) -> 29625
A5: Capital & Debt | B5: 0 | C5: 0 | D5: 0 | E5: 0 | F5: 0 | G5: 0 | H5: 0 | I5: 0 | J5: 0 | K5: 0 | L5: 0 | M5: 0 | N5: =SUM(B5:M5) -> 0
A6: Total Expenses | B6: =SUM(B3:B5) -> 0 | C6: =SUM(C3:C5) -> 0 | D6: =SUM(D3:D5) -> 0 | E6: =SUM(E3:E5) -> 0 | F6: =SUM(F3:F5) -> 0 | G6: =SUM(G3:G5) -> 0 | H6: =SUM(H3:H5) -> 0 | I6: =SUM(I3:I5) -> 0 | ... M6: =SUM(M3:M5) -> 0 | N6: =SUM(B6:M6) -> 94141
A7: Profit / (Loss) | B7: =B2-B6 -> 0 | C7: =C2-C6 -> 0 | D7: =D2-D6 -> 0 | E7: =E2-E6 -> 0 | F7: =F2-F6 -> 0 | G7: =G2-G6 -> 0 | H7: =H2-H6 -> 0 | I7: =I2-I6 -> 0 | ... N7: =N2-N6 -> 73359
