Workbook

Sheet Assumptions
A1: Year 1 Budget Assumptions
B2: Editable assumption — change this value | E2: Calculated — driven by formula
A4: School Name | B4: Bright Horizons Microschool
A5: School Type | B5: microschool
A7: KEY ASSUMPTIONS
A8: Enrollment | B8: 12
A9: Salary Escalation | B9: 0.03
A10: Cost Inflation | B10: 0.025
A11: Year 1 Proration Factor | B11: 0.83333333

Sheet Revenue
B1: July | C1: August | D1: September | E1: October | F1: November | G1: December | H1: January | I1: February | J1: March | K1: April | L1: May | M1: June | N1: Year 1 Total
A2: Tuition | B2: 14400 | C2: 14400 | D2: 14400 | E2: 14400 | F2: 14400 | G2: 14400 | H2: 14400 | I2: 14400 | J2: 14400 | K2: 14400 | L2: 0 | M2: 0 | N2: =SUM(B2:M2) -> 120000
A3: Registration Fee | B3: 300 | C3: 300 | D3: 300 | E3: 300 | F3: 300 | G3: 300 | H3: 300 | I3: 300 | J3: 300 | K3: 300 | L3: 0 | M3: 0 | N3: =SUM(B3:M3) -> 2500
A4: AZ ESA Funds | B4: 8400 | C4: 8400 | D4: 8400 | E4: 8400 | F4: 8400 | G4: 8400 | H4: 8400 | I4: 8400 | J4: 8400 | K4: 8400 | L4: 0 | M4: 0 | N4: =SUM(B4:M4) -> 70000
A5: Annual Fundraising | B5: 500 | C5: 500 | D5: 500 | E5: 500 | F5: 500 | G5: 500 | H5: 500 | I5: 500 | J5: 500 | K5: 500 | L5: 0 | M5: 0 | N5: =SUM(B5:M5) -> 4167
A6: Scholarship Discount | B6: 1 | C6: 1 | D6: 1 | E6: 1 | F6: 1 | G6: 1 | H6: 1 | I6: 1 | J6: 1 | K6: 1 | L6: 0 | M6: 0 | N6: =SUM(B6:M6) -> 8
A7: TOTAL REVENUE | B7: =SUM(B2:B6) -> 155900 | C7: =SUM(C2:C6) -> 7460 | D7: =SUM(D2:D6) -> 7460 | E7: =SUM(E2:E6) -> 7460 | F7: =SUM(F2:F6) -> 7460 | G7: =SUM(G2:G6) -> 7460 | H7: =SUM(H2:H6) -> 7460 | I7: =SUM(I2:I6) -> 7460 | ... M7: =SUM(M2:M6) -> 0 | N7: =SUM(B7:M7) -> 221600

Sheet Personnel
B1: July | C1: August | D1: September | E1: October | F1: November | G1: December | H1: January | I1: February | J1: March | K1: April | L1: May | M1: June | N1: Year 1 Total
A2: Founder / Head of School | B2: 131313 | C2: 131313 | D2: 131313 | E2: 131313 | F2: 131313 | G2: 131313 | H2: 131313 | I2: 131313 | J2: 131313 | K2: 131313 | L2: 0 | M2: 0 | N2: =SUM(B2:M2) -> 1313125
A3: Lead Teacher | B3: 107438 | C3: 107438 | D3: 107438 | E3: 107438 | F3: 107438 | G3: 107438 | H3: 107438 | I3: 107438 | J3: 107438 | K3: 107438 | L3: 0 | M3: 0 | N3: =SUM(B3:M3) -> 1074375
A4: Teaching Assistant | B4: 10092 | C4: 10092 | D4: 10092 | E4: 10092 | F4: 10092 | G4: 10092 | H4: 10092 | I4: 10092 | J4: 10092 | K4: 10092 | L4: 0 | M4: 0 | N4: =SUM(B4:M4) -> 100917
A5: TOTAL PERSONNEL | B5: =SUM(B2:B4) -> 0 | C5: =SUM(C2:C4) -> 0 | D5: =SUM(D2:D4) -> 0 | E5: =SUM(E2:E4) -> 0 | F5: =SUM(F2:F4) -> 0 | G5: =SUM(G2:G4) -> 0 | H5: =SUM(H2:H4) -> 0 | I5: =SUM(I2:I4) -> 0 | ... M5: =SUM(M2:M4) -> 0 | N5: =SUM(B5:M5) -> 0

Sheet Operating Expenses
B1: July | C1: August | D1: September | E1: October | F1: November | G1: December | H1: January | I1: February | J1: March | K1: April | L1: May | M1: June | N1: Year 1 Total
A2: Rent | B2: 2500 | C2: 2500 | D2: 2500 | E2: 2500 | F2: 2500 | G2: 2500 | H2: 2500 | I2: 2500 | J2: 2500 | K2: 2500 | L2: 0 | M2: 0 | N2: =SUM(B2:M2) -> 25000
A3: Utilities | B3: 300 | C3: 300 | D3: 300 | E3: 300 | F3: 300 | G3: 300 | H3: 300 | I3: 300 | J3: 300 | K3: 300 | L3: 0 | M3: 0 | N3: =SUM(B3:M3) -> 3000
A4: Insurance | B4: 200 | C4: 200 | D4: 200 | E4: 200 | F4: 200 | G4: 200 | H4: 200 | I4: 200 | J4: 200 | K4: 200 | L4: 0 | M4: 0 | N4: =SUM(B4:M4) -> 2000
A5: Curriculum & Materials | B5: 500 | C5: 500 | D5: 500 | E5: 500 | F5: 500 | G5: 500 | H5: 500 | I5: 500 | J5: 500 | K5: 500 | L5: 0 | M5: 0 | N5: =SUM(B5:M5) -> 5000
A6: Technology | B6: 300 | C6: 300 | D6: 300 | E6: 300 | F6: 300 | G6: 300 | H6: 300 | I6: 300 | J6: 300 | K6: 300 | L6: 0 | M6: 0 | N6: =SUM(B6:M6) -> 3000
A7: Marketing | B7: 250 | C7: 250 | D7: 250 | E7: 250 | F7: 250 | G7: 250 | H7: 250 | I7: 250 | J7: 250 | K7: 250 | L7: 0 | M7: 0 | N7: =SUM(B7:M7) -> 2500
A8: TOTAL OPERATING EXPENSES | B8: =SUM(B2:B7) -> 0 | C8: =SUM(C2:C7) -> 0 | D8: =SUM(D2:D7) -> 0 | E8: =SUM(E2:E7) -> 0 | F8: =SUM(F2:F7) -> 0 | G8: =SUM(G2:G7) -> 0 | H8: =SUM(H2:H7) -> 0 | I8: =SUM(I2:I7) -> 0 | ... M8: =SUM(M2:M7) -> 0 | N8: =SUM(B8:M8) -> 0

Sheet P&L Summary
B1: July | C1: August | D1: September | E1: October | F1: November | G1: December | H1: January | I1: February | J1: March | K1: April | L1: May | M1: June | N1: Year 1 Total
A2: Total Revenue | B2: =Revenue!B7 -> 155900 | C2: =Revenue!C7 -> 7460 | D2: =Revenue!D7 -> 7460 | E2: =Revenue!E7 -> 7460 | F2: =Revenue!F7 -> 7460 | G2: =Revenue!G7 -> 7460 | H2: =Revenue!H7 -> 7460 | I2: =Revenue!I7 -> 7460 | ... M2: =Revenue!M7 -> 0 | N2: =SUM(B2:M2) -> 221600
A3: Personnel | B3: =Personnel!B5 -> 11893 | C3: =Personnel!C5 -> 11893 | D3: =Personnel!D5 -> 11893 | E3: =Personnel!E5 -> 11893 | F3: =Personnel!F5 -> 11893 | G3: =Personnel!G5 -> 11893 | H3: =Personnel!H5 -> 11893 | I3: =Personnel!I5 -> 11893 | ... M3: =Personnel!M5 -> 0 | N3: =SUM(B3:M3) -> 118934
A4: Operating Expenses | B4: ='Operating Expenses'!B8 -> 4050 | C4: ='Operating Expenses'!C8 -> 4050 | D4: ='Operating Expenses'!D8 -> 4050 | E4: ='Operating Expenses'!E8 -> 4050 | F4: ='Operating Expenses'!F8 -> 4050 | G4: ='Operating Expenses'!G8 -> 4050 | H4: ='Operating Expenses'!H8 -> 4050 | I4: ='Operating Expenses'!I8 -> 4050 | ... M4: ='Operating Expenses'!M8 -> 0 | N4: =SUM(B4:M4) -> 40500
A5: Capital & Debt | B5: 580 | C5: 580 | D5: 580 | E5: 580 | F5: 580 | G5: 580 | H5: 580 | I5: 580 | J5: 580 | K5: 580 | L5: 580 | M5: 580 | N5: =SUM(B5:M5) -> 6960
A6: Total Expenses | B6: =SUM(B3:B5) -> 0 | C6: =SUM(C3:C5) -> 0 | D6: =SUM(D3:D5) -> 0 | E6: =SUM(E3:E5) -> 0 | F6: =SUM(F3:F5) -> 0 | G6: =SUM(G3:G5) -> 0 | H6: =SUM(H3:H5) -> 0 | I6: =SUM(I3:I5) -> 0 | ... M6: =SUM(M3:M5) -> 0 | N6: =SUM(B6:M6) -> 166394
A7: Profit / (Loss) | B7: =B2-B6 -> 0 | C7: =C2-C6 -> 0 | D7: =D2-D6 -> 0 | E7: =E2-E6 -> 0 | F7: =F2-F6 -> 0 | G7: =G2-G6 -> 0 | H7: =H2-H6 -> 0 | I7: =I2-I6 -> 0 | ... N7: =N2-N6 -> 18273

Sheet Decision History
B1: Decision History
B2: Track record of 5 tracked decisions (2 pursued, 1 on hold, 2 declined). Each entry shows the modeled change, the outcome the team logged, and any retrospective notes captured after the fact.
B4: Decision | C4: Type | D4: Outcome | E4: Applied to base model? | F4: Outcome logged | G4: Modeled change | H4: What happened (retrospective)
B5: Add Middle School program | C5: Add a program | D5: Pursued | E5: [APPLIED] Folded into the base model on Apr 12, 2025 | F5: Apr 10, 2025 | G5: • Program: Middle School (6-8) • Tuition $14,000/yr • Adds 72 cumulative students (5 yrs) • +2 FTE | H5: Launched in fall 2025; enrollment hit plan within 1 student.
B6: Increase retention focus | C6: Change enrollment | D6: Pursued | E6: [PENDING] Pending apply to base model | F6: Mar 5, 2025 | G6: • Enrollment +14 cumulative • Retention 92% | H6: Retention initiatives approved; planner will reflect after Q2 board review.
B7: Evaluate downtown campus | C7: Evaluate a site | D7: On hold | E7: — | F7: Mar 25, 2025 | G7: • Rent $8,500/mo • Rent escalation 4% • Sqft +1500 • Fit-out $75,000 (Y1) | H7: Landlord negotiations paused while waiting on city zoning ruling.
B8: Reduce K cohort | C8: Change enrollment | D8: Declined | E8: — | F8: Mar 15, 2025 | G8: • Enrollment -8 cumulative • Tuition $-500/student | H8: Board declined; enrollment goals retained as originally modeled.
B9: Move to larger building | C9: Evaluate a site | D9: Declined | E9: — | F9: Feb 10, 2025 | G9: • Rent $12,000/mo • Sqft +4000 | H9: Costs out of reach; revisited next year after capital campaign.
B11: Generated by SchoolStack Budget (budget.schoolstack.ai)
