Workbook

Sheet Cover
B3: SchoolStack Budget
B4: 5-Year Financial Model
B8: Prepared for
B9: Liberty Learning Co-Op
B10: Homeschool Co-Op • LLC - Single Member • AZ
B12: Date Prepared | C12: March 27, 2026
B15: KEY HIGHLIGHTS
B16: Year 5 Revenue | C16: 598240
B17: Year 5 Net Income | C17: 452913
B18: Year 5 Net Margin | C18: 0.75707576
B19: Operating Reserve (Months) | C19: 116.89668
B20: Year 5 Enrollment | C20: 40
B23: TABLE OF CONTENTS
B24: Assumptions
B25: Revenue Schedule
B26: Staffing & Personnel
B27: Operating Expenses
B28: Capital & Debt
B29: Financial Model
B30: Summary
B33: Generated by SchoolStack Budget • budget.schoolstack.ai

Sheet Assumptions
A1: SchoolStack Budget - Assumptions
B2: Editable assumption — change this value | E2: Calculated — driven by formula
A3: SCHOOL INFORMATION
A4: School Name | B4: Liberty Learning Co-Op
A5: State | B5: AZ
A6: School Type | B6: Homeschool Co-Op
A7: Entity Type | B7: LLC - Single Member
A8: EIN | B8: 86-5551234
A9: School Stage | B9: New School
A10: Opening Year | B10: 2026
A11: Current Students | B11: 0
A12: Max Student Capacity | B12: 40
A13: Fiscal Year Start | B13: July
A14: Year 1 Operating Months | B14: 10
A15: Location Secured | B15: Yes
A16: Facility Address | B16: 789 Desert Way, Mesa, AZ, 85201
A17: Facility Ownership | B17: Rented / Leased
A18: Monthly Rent | B18: $1,800
A19: Annual Rent Escalation | B19: 3%
A21: ENROLLMENT BY YEAR
A22: Year 1 Students | B22: 15
A23: Year 2 Students | B23: 22
A24: Year 3 Students | B24: 30
A25: Year 4 Students | B25: 36
A26: Year 5 Students | B26: 40
A28: WEIGHTED ENROLLMENT POPULATIONS
A29: Special Education (SPED) | B29: 3 / 4 / 5 / 6 / 6
A30: English Language Learners (ELL) | B30: 2 / 3 / 4 / 5 / 5
A31: Economically Disadvantaged | B31: 5 / 7 / 9 / 10 / 12
A32: Total Weighted Students | B32: 10 / 14 / 18 / 21 / 23
A33: Weighted % of Enrollment | B33: 67% / 64% / 60% / 58% / 57%
A35: GROWTH & ESCALATION ASSUMPTIONS
A36: Annual Salary Escalation | B36: 0.03
A37: General Cost Inflation | B37: 0.025
A38: Year 1 Proration Factor | B38: 0.83333333
A39: Projection Period | B39: 5 Years

Sheet Revenue Schedule
B1: Year 1 | C1: Year 2 | D1: Year 3 | E1: Year 4 | F1: Year 5
A2: Students | B2: =Assumptions!B22 -> 15 | C2: =Assumptions!B23 -> 22 | D2: =Assumptions!B24 -> 30 | E2: =Assumptions!B25 -> 36 | F2: =Assumptions!B26 -> 40
A3: TUITION & STUDENT FEES
A4: Co-Op Tuition | B4: =6000*Assumptions!B22 -> 90000 | C4: =6180*Assumptions!B23 -> 135960 | D4: =6365*Assumptions!B24 -> 190950 | E4: =6556*Assumptions!B25 -> 236016 | F4: =6753*Assumptions!B26 -> 270120
A5: Materials Fee | B5: =200*Assumptions!B22 -> 3000 | C5: =200*Assumptions!B23 -> 4400 | D5: =200*Assumptions!B24 -> 6000 | E5: =200*Assumptions!B25 -> 7200 | F5: =200*Assumptions!B26 -> 8000
A6: Total TUITION & STUDENT FEES | B6: =SUM(B4:B5) -> 93000 | C6: =SUM(C4:C5) -> 140360 | D6: =SUM(D4:D5) -> 196950 | E6: =SUM(E4:E5) -> 243216 | F6: =SUM(F4:F5) -> 278120
A7: SCHOOL CHOICE / CHOICE FUNDING
A8: ESA Revenue | B8: =7000*Assumptions!B22 -> 105000 | C8: =7210*Assumptions!B23 -> 158620 | D8: =7426*Assumptions!B24 -> 222780 | E8: =7649*Assumptions!B25 -> 275364 | F8: =7878*Assumptions!B26 -> 315120
A9: Total SCHOOL CHOICE / CHOICE FUNDING | B9: =SUM(B8:B8) -> 105000 | C9: =SUM(C8:C8) -> 158620 | D9: =SUM(D8:D8) -> 222780 | E9: =SUM(E8:E8) -> 275364 | F9: =SUM(F8:F8) -> 315120
A10: PHILANTHROPY
A11: Annual Fundraising | B11: 3000 | C11: 4000 | D11: 5000 | E11: 5000 | F11: 5000
A12: Total PHILANTHROPY | B12: =SUM(B11:B11) -> 3000 | C12: =SUM(C11:C11) -> 4000 | D12: =SUM(D11:D11) -> 5000 | E12: =SUM(E11:E11) -> 5000 | F12: =SUM(F11:F11) -> 5000
A14: TOTAL NET REVENUE | B14: =B6+B9+B12 -> 201000 | C14: =C6+C9+C12 -> 302980 | D14: =D6+D9+D12 -> 424730 | E14: =E6+E9+E12 -> 523580 | F14: =F6+F9+F12 -> 598240

Sheet Staffing & Personnel
A1: SchoolStack Budget - Staffing & Personnel
A3: Role | B3: Function | C3: Type | D3: FTE | E3: Annual Rate | F3: Benefits % | G3: Payroll Tax % | H3: Total Annual Cost
A4: Director / Lead Educator | B4: School Leadership | C4: Full-Time | D4: 1 | E4: 48000 | F4: 0.2 | G4: 0.0765 | H4: 61272
A5: Assistant Educator | B5: Instructional | C5: Part-Time | D5: 0.5 | E5: 30000 | F5: 0 | G5: 0.0765 | H5: 16147.5
A7: PERSONNEL COST SUMMARY
A8: Total Headcount | B8: 2
A9: Total FTE | B9: 1.5
A10: Salaries & Wages | B10: 63000
A11: Benefits | B11: 9600
A12: Payroll Taxes | B12: 4820
A13: Contracted Personnel | B13: 0
A14: Total Annual Personnel Cost | B14: 77420
A16: PERSONNEL COST PROJECTION
B17: Year 1 | C17: Year 2 | D17: Year 3 | E17: Year 4 | F17: Year 5
A18: Base Personnel Cost | B18: 77420 | C18: 77420 | D18: 77420 | E18: 77420 | F18: 77420
A19: Salary Escalation Factor | B19: =(1+Assumptions!B36)^0 -> 1 | C19: =(1+Assumptions!B36)^1 -> 1.03 | D19: =(1+Assumptions!B36)^2 -> 1.0609 | E19: =(1+Assumptions!B36)^3 -> 1.092727 | F19: =(1+Assumptions!B36)^4 -> 1.1255088
A20: Proration Factor | B20: =Assumptions!B38 -> 0.83333333 | C20: 1 | D20: 1 | E20: 1 | F20: 1
A21: Total Personnel Cost | B21: =B18*B19*B20 -> 64516 | C21: =C18*C19*C20 -> 79742 | D21: =D18*D19*D20 -> 82134 | E21: =E18*E19*E20 -> 84598 | F21: =F18*F19*F20 -> 87136

Sheet Operating Expenses
B1: Year 1 | C1: Year 2 | D1: Year 3 | E1: Year 4 | F1: Year 5
A2: Students | B2: =Assumptions!B22 -> 15 | C2: =Assumptions!B23 -> 22 | D2: =Assumptions!B24 -> 30 | E2: =Assumptions!B25 -> 36 | F2: =Assumptions!B26 -> 40
A3: INSTRUCTIONAL / PROGRAM
A4: Curriculum & Materials | B4: =400*Assumptions!B22 -> 6000 | C4: =412*Assumptions!B23 -> 9064 | D4: =424*Assumptions!B24 -> 12720 | E4: =437*Assumptions!B25 -> 15732 | F4: =450*Assumptions!B26 -> 18000
A5: Total INSTRUCTIONAL | B5: =SUM(B4:B4) -> 6000 | C5: =SUM(C4:C4) -> 9064 | D5: =SUM(D4:D4) -> 12720 | E5: =SUM(E4:E4) -> 15732 | F5: =SUM(F4:F4) -> 18000
A6: TECHNOLOGY
A7: Technology | B7: =250*Assumptions!B22 -> 3750 | C7: =258*Assumptions!B23 -> 5676 | D7: =265*Assumptions!B24 -> 7950 | E7: =273*Assumptions!B25 -> 9828 | F7: =281*Assumptions!B26 -> 11240
A8: Total TECHNOLOGY | B8: =SUM(B7:B7) -> 3750 | C8: =SUM(C7:C7) -> 5676 | D8: =SUM(D7:D7) -> 7950 | E8: =SUM(E7:E7) -> 9828 | F8: =SUM(F7:F7) -> 11240
A9: OCCUPANCY / FACILITY
A10: Rent | B10: =1800*12 -> 21600 | C10: =1854*12 -> 22248 | D10: =1910*12 -> 22920 | E10: =1967*12 -> 23604 | F10: =2026*12 -> 24312
A11: Utilities | B11: =200*12 -> 2400 | C11: =205*12 -> 2460 | D11: =210*12 -> 2520 | E11: =215*12 -> 2580 | F11: =221*12 -> 2652
A12: Insurance | B12: 1800 | C12: 1845 | D12: 1891 | E12: 1938 | F12: 1987
A13: Total OCCUPANCY | B13: =SUM(B10:B12) -> 25800 | C13: =SUM(C10:C12) -> 26553 | D13: =SUM(D10:D12) -> 27331 | E13: =SUM(E10:E12) -> 28122 | F13: =SUM(F10:F12) -> 28951
A15: TOTAL OPERATING EXPENSES | B15: =B5+B8+B13 -> 35550 | C15: =C5+C8+C13 -> 41293 | D15: =D5+D8+D13 -> 48001 | E15: =E5+E8+E13 -> 53682 | F15: =F5+F8+F13 -> 58191

Sheet Capital & Debt
B1: Year 1 | C1: Year 2 | D1: Year 3 | E1: Year 4 | F1: Year 5
A2: CAPITAL EXPENDITURES & DEBT SERVICE
A3: (No capital or debt items) | B3: 0 | C3: 0 | D3: 0 | E3: 0 | F3: 0
A4: TOTAL CAPITAL & DEBT | B4: 0 | C4: 0 | D4: 0 | E4: 0 | F4: 0

Sheet Financial Model
A1: 5-Year Financial Model | B1: Year 1 | C1: Year 2 | D1: Year 3 | E1: Year 4 | F1: Year 5
A2: Total Revenue | B2: ='Revenue Schedule'!B14 -> 201000 | C2: ='Revenue Schedule'!C14 -> 302980 | D2: ='Revenue Schedule'!D14 -> 424730 | E2: ='Revenue Schedule'!E14 -> 523580 | F2: ='Revenue Schedule'!F14 -> 598240
A3: Personnel Costs | B3: ='Staffing & Personnel'!B21 -> 64516 | C3: ='Staffing & Personnel'!C21 -> 79742 | D3: ='Staffing & Personnel'!D21 -> 82134 | E3: ='Staffing & Personnel'!E21 -> 84598 | F3: ='Staffing & Personnel'!F21 -> 87136
A4: Operating Expenses | B4: ='Operating Expenses'!B15 -> 35550 | C4: ='Operating Expenses'!C15 -> 41293 | D4: ='Operating Expenses'!D15 -> 48001 | E4: ='Operating Expenses'!E15 -> 53682 | F4: ='Operating Expenses'!F15 -> 58191
A5: Capital & Debt | B5: ='Capital & Debt'!B4 -> 0 | C5: ='Capital & Debt'!C4 -> 0 | D5: ='Capital & Debt'!D4 -> 0 | E5: ='Capital & Debt'!E4 -> 0 | F5: ='Capital & Debt'!F4 -> 0
A6: Total Expenses | B6: =B3+B4+B5 -> 100066 | C6: =C3+C4+C5 -> 121035 | D6: =D3+D4+D5 -> 130135 | E6: =E3+E4+E5 -> 138280 | F6: =F3+F4+F5 -> 145327
A7: Profit | B7: =B2-B6 -> 100934 | C7: =C2-C6 -> 181945 | D7: =D2-D6 -> 294595 | E7: =E2-E6 -> 385300 | F7: =F2-F6 -> 452913
A8: Cumulative Profit | B8: =B7 -> 100934 | C8: =B8+C7 -> 282879 | D8: =C8+D7 -> 577474 | E8: =D8+E7 -> 962774 | F8: =E8+F7 -> 1415687
A9: Operating Reserve (Months) | B9: =IF(B6=0,0,IF(B8>0,B8/(B6/12),0)) -> 12.104091 | C9: =IF(C6=0,0,IF(C8>0,C8/(C6/12),0)) -> 28.046003 | D9: =IF(D6=0,0,IF(D8>0,D8/(D6/12),0)) -> 53.249994 | E9: =IF(E6=0,0,IF(E8>0,E8/(E6/12),0)) -> 83.549957 | F9: =IF(F6=0,0,IF(F8>0,F8/(F6/12),0)) -> 116.89668
A10: Break-even | B10: ✓ Break-even

Sheet Summary
A1: Financial Model Summary
A2: Prepared by SchoolStack Budget
A4: SCHOOL INFORMATION
A5: School Name | B5: Liberty Learning Co-Op
A6: School Type | B6: Homeschool Co-Op
A7: Entity Type | B7: LLC - Single Member
A8: EIN | B8: 86-5551234
A9: School Stage | B9: New School
A10: State | B10: AZ
A11: Fiscal Year Start | B11: July
A12: Max Student Capacity | B12: 40
A14: ENROLLMENT TREND
B15: Year 1 | C15: Year 2 | D15: Year 3 | E15: Year 4 | F15: Year 5
A16: Students | B16: ='Revenue Schedule'!B2 -> 15 | C16: ='Revenue Schedule'!C2 -> 22 | D16: ='Revenue Schedule'!D2 -> 30 | E16: ='Revenue Schedule'!E2 -> 36 | F16: ='Revenue Schedule'!F2 -> 40
A17: Enrollment Growth % | B17: - | C17: =IF(B16=0,0,(C16-B16)/B16) -> 0.46666667 | D17: =IF(C16=0,0,(D16-C16)/C16) -> 0.36363636 | E17: =IF(D16=0,0,(E16-D16)/D16) -> 0.2 | F17: =IF(E16=0,0,(F16-E16)/E16) -> 0.11111111
B19: Year 1 | C19: Year 2 | D19: Year 3 | E19: Year 4 | F19: Year 5
A20: Total Revenue | B20: ='Financial Model'!B2 -> 201000 | C20: ='Financial Model'!C2 -> 302980 | D20: ='Financial Model'!D2 -> 424730 | E20: ='Financial Model'!E2 -> 523580 | F20: ='Financial Model'!F2 -> 598240
A21: Personnel Costs | B21: ='Financial Model'!B3 -> 64516 | C21: ='Financial Model'!C3 -> 79742 | D21: ='Financial Model'!D3 -> 82134 | E21: ='Financial Model'!E3 -> 84598 | F21: ='Financial Model'!F3 -> 87136
A22: Operating Expenses | B22: ='Financial Model'!B4 -> 35550 | C22: ='Financial Model'!C4 -> 41293 | D22: ='Financial Model'!D4 -> 48001 | E22: ='Financial Model'!E4 -> 53682 | F22: ='Financial Model'!F4 -> 58191
A23: Total Expenses | B23: ='Financial Model'!B6 -> 100066 | C23: ='Financial Model'!C6 -> 121035 | D23: ='Financial Model'!D6 -> 130135 | E23: ='Financial Model'!E6 -> 138280 | F23: ='Financial Model'!F6 -> 145327
A24: Profit | B24: ='Financial Model'!B7 -> 100934 | C24: ='Financial Model'!C7 -> 181945 | D24: ='Financial Model'!D7 -> 294595 | E24: ='Financial Model'!E7 -> 385300 | F24: ='Financial Model'!F7 -> 452913
A25: Cumulative Profit | B25: ='Financial Model'!B8 -> 100934 | C25: ='Financial Model'!C8 -> 282879 | D25: ='Financial Model'!D8 -> 577474 | E25: ='Financial Model'!E8 -> 962774 | F25: ='Financial Model'!F8 -> 1415687
A26: Operating Reserve (Months) | B26: ='Financial Model'!B9 -> 12.104091 | C26: ='Financial Model'!C9 -> 28.046003 | D26: ='Financial Model'!D9 -> 53.249994 | E26: ='Financial Model'!E9 -> 83.549957 | F26: ='Financial Model'!F9 -> 116.89668
A28: KEY RATIOS
A29: Revenue per Student | B29: =IF('Revenue Schedule'!B2=0,0,B20/'Revenue Schedule'!B2) -> 13400 | C29: =IF('Revenue Schedule'!C2=0,0,C20/'Revenue Schedule'!C2) -> 13771.818 | D29: =IF('Revenue Schedule'!D2=0,0,D20/'Revenue Schedule'!D2) -> 14157.667 | E29: =IF('Revenue Schedule'!E2=0,0,E20/'Revenue Schedule'!E2) -> 14543.889 | F29: =IF('Revenue Schedule'!F2=0,0,F20/'Revenue Schedule'!F2) -> 14956
A30: Personnel Cost as % of Revenue | B30: =IF(B20=0,0,'Financial Model'!B3/B20) -> 0.32097512 | C30: =IF(C20=0,0,'Financial Model'!C3/C20) -> 0.26319229 | D30: =IF(D20=0,0,'Financial Model'!D3/D20) -> 0.19337932 | E30: =IF(E20=0,0,'Financial Model'!E3/E20) -> 0.16157607 | F30: =IF(F20=0,0,'Financial Model'!F3/F20) -> 0.14565392
A31: Operating Cost as % of Revenue | B31: =IF(B20=0,0,'Financial Model'!B4/B20) -> 0.17686567 | C31: =IF(C20=0,0,'Financial Model'!C4/C20) -> 0.13628952 | D31: =IF(D20=0,0,'Financial Model'!D4/D20) -> 0.11301533 | E31: =IF(E20=0,0,'Financial Model'!E4/E20) -> 0.10252874 | F31: =IF(F20=0,0,'Financial Model'!F4/F20) -> 0.097270326
A32: Profit Margin % | B32: =IF(B20=0,0,B24/B20) -> 0.5021592 | C32: =IF(C20=0,0,C24/C20) -> 0.60051819 | D32: =IF(D20=0,0,D24/D20) -> 0.69360535 | E32: =IF(E20=0,0,E24/E20) -> 0.73589518 | F32: =IF(F20=0,0,F24/F20) -> 0.75707576
A34: REVENUE MIX TREND
A35: Tuition & Fees % | B35: 0.46268657 | C35: 0.4632649 | D35: 0.46370635 | E35: 0.464525 | F35: 0.46489703
A36: Public Funding % | B36: 0.52238806 | C36: 0.52353291 | D36: 0.52452146 | E36: 0.52592536 | F36: 0.52674512
A37: Philanthropy % | B37: 0.014925373 | C37: 0.013202192 | D37: 0.011772185 | E37: 0.009549639 | F37: 0.0083578497

Sheet Financial Health
B2: Liberty Learning Co-Op — Financial Health Dashboard
B3: Generated March 27, 2026
B4: ● Green = healthy | D4: ◐ Yellow = monitor | F4: ○ Red = action needed
B6: Metric | C6: Year 1 | D6: Year 2 | E6: Year 3 | F6: Year 4 | G6: Year 5 | H6: Benchmark
B7: Enrollment | C7: 15 | D7: 22 | E7: 30 | F7: 36 | G7: 40
B8: Revenue | C8: 201000 | D8: 302980 | E8: 424730 | F8: 523580 | G8: 598240
B9: Personnel | C9: 64516 | D9: 79742 | E9: 82134 | F9: 84598 | G9: 87136
B10: Operating Expenses | C10: 35550 | D10: 41293 | E10: 48001 | F10: 53682 | G10: 58191
B11: Debt Service | C11: 0 | D11: 0 | E11: 0 | F11: 0 | G11: 0
B12: Net Income | C12: 100934 | D12: 181945 | E12: 294595 | F12: 385300 | G12: 452913
B13: Ending Cash | C13: 100934 | D13: 282879 | E13: 577474 | F13: 962774 | G13: 1415687
B14: Net Margin | C14: 0.5021592 | D14: 0.60051819 | E14: 0.69360535 | F14: 0.73589518 | G14: 0.75707576
B15: Revenue per Student | C15: 13400 | D15: 13771.818 | E15: 14157.667 | F15: 14543.889 | G15: 14956 | H15: ≥ $10,000
B16: Payroll % | C16: 0.32097512 | D16: 0.26319229 | E16: 0.19337932 | F16: 0.16157607 | G16: 0.14565392 | H16: ≤ 55%
B17: Facility % | C17: 0.12835821 | D17: 0.087639448 | E17: 0.06433838 | F17: 0.053708895 | G17: 0.048391933 | H17: ≤ 15%
B18: Operating Margin | C18: 0.5021592 | D18: 0.60051819 | E18: 0.69360535 | F18: 0.73589518 | G18: 0.75707576 | H18: ≥ 10%
B19: Revenue Sources | C19: 3 | D19: 3 | E19: 3 | F19: 3 | G19: 3 | H19: ≥ 3 sources
B20: DSCR | C20: N/A | D20: N/A | E20: N/A | F20: N/A | G20: N/A | H20: N/A
B21: Break-even Year | C21: =IF('Financial Model'!B8>=0,"✓ Break-even","") -> ✓ Break-even | D21: =IF(AND('Financial Model'!C8>=0,'Financial Model'!B8<0),"✓ Break-even","") -> 0 | E21: =IF(AND('Financial Model'!D8>=0,'Financial Model'!C8<0),"✓ Break-even","") -> 0 | F21: =IF(AND('Financial Model'!E8>=0,'Financial Model'!D8<0),"✓ Break-even","") -> 0 | G21: =IF(AND('Financial Model'!F8>=0,'Financial Model'!E8<0),"✓ Break-even","") -> 0 | H21: Year 1
B22: Cash Runway (Months) | C22: 12 | D22: 28 | E22: 53 | F22: 60+ | G22: 60+ | H22: ≥ 24 months
B24: FINANCIAL HEALTH SIGNALS | C24: Status | D24: Assessment | F24: Watch Item
B25: Viability | C25: ● Healthy | D25: The model reaches profit early and sustains strong margins through Year 5. | F25: Monitor enrollment actuals vs. projections in Year 1.
B26: Liquidity | C26: ● Healthy | D26: Cash stays positive throughout the projection and reserves exceed 3 months of expenses. | F26: Maintain reserves as a buffer against seasonal revenue dips.
B27: Staffing Burden | C27: ● Healthy | D27: Staffing at 15% of revenue leaves room for facilities, programs, and reserves. | F27: As you add staff, ensure staffing stays below 60% of revenue.
B28: Facility Burden | C28: ● Healthy | D28: Facility costs at 5% of revenue are well-managed and leave budget for programs. | F28: Watch for rent escalation clauses that could push this higher over time.
B29: Revenue Concentration | C29: ● Healthy | D29: Revenue is anchored to enrollment-driven income — the strongest foundation for a school model. A focused revenue stream is a strength when backed by dependable demand. | F29: Continue to pressure-test enrollment assumptions: recruitment pipeline, waitlist depth, retention rates, and collection reliability.
B30: Reserve Strength | C30: ● Healthy | D30: 116.9 months of reserves by Year 5 — a strong buffer for unexpected costs. | F30: Continue growing reserves toward 6 months for best-in-class financial health.
B32: Summary | C32: 6 Healthy | 0 Watch | 0 Needs Attention
B34: Built by SchoolStack Budget • budget.schoolstack.ai
