Workbook

Sheet Cover
B3: SchoolStack Budget
B4: 5-Year Financial Model
B8: Prepared for
B9: Heritage Academy
B10: Private School • 501(c)(3) Nonprofit • FL
B12: Date Prepared | C12: March 27, 2026
B15: KEY HIGHLIGHTS
B16: Year 5 Revenue | C16: 4323000
B17: Year 5 Net Income | C17: 3011257
B18: Year 5 Net Margin | C18: 0.6965665
B19: Operating Reserve (Months) | C19: 90.131463
B20: Year 5 Enrollment | C20: 200
B23: TABLE OF CONTENTS
B24: Assumptions
B25: Revenue Schedule
B26: Staffing & Personnel
B27: Operating Expenses
B28: Capital & Debt
B29: Financial Model
B30: Summary
B31: Prior-Year Snapshot
B34: Generated by SchoolStack Budget • budget.schoolstack.ai

Sheet Assumptions
A1: SchoolStack Budget - Assumptions
B2: Editable assumption — change this value | E2: Calculated — driven by formula
A3: SCHOOL INFORMATION
A4: School Name | B4: Heritage Academy
A5: State | B5: FL
A6: School Type | B6: Private School
A7: Entity Type | B7: 501(c)(3) Nonprofit
A8: EIN | B8: 59-9876543
A9: School Stage | B9: Operating School
A10: Opening Year | B10: 2023
A11: Current Students | B11: 85
A12: Max Student Capacity | B12: 200
A13: Fiscal Year Start | B13: July
A14: Accredited | B14: No
A15: Location Secured | B15: Yes
A16: Facility Address | B16: 456 Oak Ave, Tampa, FL, 33602
A17: Facility Ownership | B17: Rented / Leased
A18: Monthly Rent | B18: $8,500
A19: Annual Rent Escalation | B19: 3%
A21: ENROLLMENT BY YEAR
A22: Year 1 Students | B22: 100
A23: Year 2 Students | B23: 130
A24: Year 3 Students | B24: 160
A25: Year 4 Students | B25: 185
A26: Year 5 Students | B26: 200
A28: GROWTH & ESCALATION ASSUMPTIONS
A29: Annual Salary Escalation | B29: 0
A30: General Cost Inflation | B30: 0
A31: Year 1 Proration Factor | B31: 1
A32: Projection Period | B32: 5 Years

Sheet Revenue Schedule
B1: Year 1 | C1: Year 2 | D1: Year 3 | E1: Year 4 | F1: Year 5
A2: Students | B2: =Assumptions!B22 -> 100 | C2: =Assumptions!B23 -> 130 | D2: =Assumptions!B24 -> 160 | E2: =Assumptions!B25 -> 185 | F2: =Assumptions!B26 -> 200
A3: TUITION & STUDENT FEES
A4: Tuition | B4: =10500*Assumptions!B22 -> 1050000 | C4: =10815*Assumptions!B23 -> 1405950 | D4: =11140*Assumptions!B24 -> 1782400 | E4: =11474*Assumptions!B25 -> 2122690 | F4: =11818*Assumptions!B26 -> 2363600
A5: Registration Fee | B5: =350*Assumptions!B22 -> 35000 | C5: =350*Assumptions!B23 -> 45500 | D5: =350*Assumptions!B24 -> 56000 | E5: =350*Assumptions!B25 -> 64750 | F5: =350*Assumptions!B26 -> 70000
A6: Total TUITION & STUDENT FEES | B6: =SUM(B4:B5) -> 1085000 | C6: =SUM(C4:C5) -> 1451450 | D6: =SUM(D4:D5) -> 1838400 | E6: =SUM(E4:E5) -> 2187440 | F6: =SUM(F4:F5) -> 2433600
A7: TUITION OFFSETS
A8: Scholarship Discount | B8: =--1050*Assumptions!B22 -> -105000 | C8: =--1082*Assumptions!B23 -> -140660 | D8: =--1114*Assumptions!B24 -> -178240 | E8: =--1147*Assumptions!B25 -> -212195 | F8: =--1182*Assumptions!B26 -> -236400
A9: Total TUITION OFFSETS | B9: =SUM(B8:B8) -> -105000 | C9: =SUM(C8:C8) -> -140660 | D9: =SUM(D8:D8) -> -178240 | E9: =SUM(E8:E8) -> -212195 | F9: =SUM(F8:F8) -> -236400
A10: SCHOOL CHOICE / CHOICE FUNDING
A11: FL FTC Scholarship | B11: =8700*Assumptions!B22 -> 870000 | C11: =8961*Assumptions!B23 -> 1164930 | D11: =9230*Assumptions!B24 -> 1476800 | E11: =9507*Assumptions!B25 -> 1758795 | F11: =9792*Assumptions!B26 -> 1958400
A12: Total SCHOOL CHOICE / CHOICE FUNDING | B12: =SUM(B11:B11) -> 870000 | C12: =SUM(C11:C11) -> 1164930 | D12: =SUM(D11:D11) -> 1476800 | E12: =SUM(E11:E11) -> 1758795 | F12: =SUM(F11:F11) -> 1958400
A13: PHILANTHROPY
A14: Foundation Grant | B14: 50000 | C14: 40000 | D14: 30000 | E14: 20000 | F14: 10000
A15: Annual Fund | B15: 25000 | C15: 30000 | D15: 35000 | E15: 40000 | F15: 45000
A16: Total PHILANTHROPY | B16: =SUM(B14:B15) -> 75000 | C16: =SUM(C14:C15) -> 70000 | D16: =SUM(D14:D15) -> 65000 | E16: =SUM(E14:E15) -> 60000 | F16: =SUM(F14:F15) -> 55000
A17: OTHER REVENUE
A18: After-School Programs | B18: =500*Assumptions!B22 -> 50000 | C18: =515*Assumptions!B23 -> 66950 | D18: =530*Assumptions!B24 -> 84800 | E18: =546*Assumptions!B25 -> 101010 | F18: =562*Assumptions!B26 -> 112400
A19: Total OTHER REVENUE | B19: =SUM(B18:B18) -> 50000 | C19: =SUM(C18:C18) -> 66950 | D19: =SUM(D18:D18) -> 84800 | E19: =SUM(E18:E18) -> 101010 | F19: =SUM(F18:F18) -> 112400
A21: TOTAL NET REVENUE | B21: =B6+B9+B12+B16+B19 -> 1975000 | C21: =C6+C9+C12+C16+C19 -> 2612670 | D21: =D6+D9+D12+D16+D19 -> 3286760 | E21: =E6+E9+E12+E16+E19 -> 3895050 | F21: =F6+F9+F12+F16+F19 -> 4323000

Sheet Staffing & Personnel
A1: SchoolStack Budget - Staffing & Personnel
A3: Role | B3: Function | C3: Type | D3: FTE | E3: Annual Rate | F3: Benefits % | G3: Payroll Tax % | H3: Total Annual Cost
A4: Head of School | B4: School Leadership | C4: Full-Time | D4: 1 | E4: 95000 | F4: 0.25 | G4: 0.0765 | H4: 126017.5
A5: Assistant Principal | B5: School Leadership | C5: Full-Time | D5: 1 | E5: 75000 | F5: 0.25 | G5: 0.0765 | H5: 99487.5
A6: Teachers | B6: Instructional | C6: Full-Time | D6: 6 | E6: 48000 | F6: 0.25 | G6: 0.0765 | H6: 382032
A7: Paraprofessionals | B7: Instructional | C7: Full-Time | D7: 3 | E7: 32000 | F7: 0.2 | G7: 0.0765 | H7: 122544
A8: School Counselor | B8: Student Support | C8: Full-Time | D8: 1 | E8: 52000 | F8: 0.25 | G8: 0.0765 | H8: 68978
A9: Office Manager | B9: Administrative | C9: Full-Time | D9: 1 | E9: 42000 | F9: 0.25 | G9: 0.0765 | H9: 55713
A11: PERSONNEL COST SUMMARY
A12: Total Headcount | B12: 6
A13: Total FTE | B13: 13
A14: Salaries & Wages | B14: 648000
A15: Benefits | B15: 157200
A16: Payroll Taxes | B16: 49572
A17: Contracted Personnel | B17: 0
A18: Total Annual Personnel Cost | B18: 854772
A20: PERSONNEL COST PROJECTION
B21: Year 1 | C21: Year 2 | D21: Year 3 | E21: Year 4 | F21: Year 5
A22: Base Personnel Cost | B22: 854772 | C22: 854772 | D22: 854772 | E22: 854772 | F22: 854772
A23: Salary Escalation Factor | B23: =(1+Assumptions!B29)^0 -> 1 | C23: =(1+Assumptions!B29)^1 -> 1 | D23: =(1+Assumptions!B29)^2 -> 1 | E23: =(1+Assumptions!B29)^3 -> 1 | F23: =(1+Assumptions!B29)^4 -> 1
A24: Proration Factor | B24: =Assumptions!B31 -> 1 | C24: 1 | D24: 1 | E24: 1 | F24: 1
A25: Total Personnel Cost | B25: =B22*B23*B24 -> 854772 | C25: =C22*C23*C24 -> 854772 | D25: =D22*D23*D24 -> 854772 | E25: =E22*E23*E24 -> 854772 | F25: =F22*F23*F24 -> 854772

Sheet Operating Expenses
B1: Year 1 | C1: Year 2 | D1: Year 3 | E1: Year 4 | F1: Year 5
A2: Students | B2: =Assumptions!B22 -> 100 | C2: =Assumptions!B23 -> 130 | D2: =Assumptions!B24 -> 160 | E2: =Assumptions!B25 -> 185 | F2: =Assumptions!B26 -> 200
A3: INSTRUCTIONAL / PROGRAM
A4: Curriculum | B4: =600*Assumptions!B22 -> 60000 | C4: =618*Assumptions!B23 -> 80340 | D4: =637*Assumptions!B24 -> 101920 | E4: =656*Assumptions!B25 -> 121360 | F4: =675*Assumptions!B26 -> 135000
A5: Total INSTRUCTIONAL | B5: =SUM(B4:B4) -> 60000 | C5: =SUM(C4:C4) -> 80340 | D5: =SUM(D4:D4) -> 101920 | E5: =SUM(E4:E4) -> 121360 | F5: =SUM(F4:F4) -> 135000
A6: TECHNOLOGY
A7: Technology | B7: =400*Assumptions!B22 -> 40000 | C7: =412*Assumptions!B23 -> 53560 | D7: =424*Assumptions!B24 -> 67840 | E7: =437*Assumptions!B25 -> 80845 | F7: =450*Assumptions!B26 -> 90000
A8: Total TECHNOLOGY | B8: =SUM(B7:B7) -> 40000 | C8: =SUM(C7:C7) -> 53560 | D8: =SUM(D7:D7) -> 67840 | E8: =SUM(E7:E7) -> 80845 | F8: =SUM(F7:F7) -> 90000
A9: OCCUPANCY / FACILITY
A10: Rent | B10: =8500*12 -> 102000 | C10: =8755*12 -> 105060 | D10: =9018*12 -> 108216 | E10: =9289*12 -> 111468 | F10: =9567*12 -> 114804
A11: Utilities | B11: =1200*12 -> 14400 | C11: =1236*12 -> 14832 | D11: =1273*12 -> 15276 | E11: =1311*12 -> 15732 | F11: =1350*12 -> 16200
A12: Insurance | B12: 12000 | C12: 12360 | D12: 12731 | E12: 13113 | F12: 13506
A13: Maintenance | B13: 8000 | C13: 8240 | D13: 8487 | E13: 8742 | F13: 9004
A14: Total OCCUPANCY | B14: =SUM(B10:B13) -> 136400 | C14: =SUM(C10:C13) -> 140492 | D14: =SUM(D10:D13) -> 144710 | E14: =SUM(E10:E13) -> 149055 | F14: =SUM(F10:F13) -> 153514
A15: ADMINISTRATIVE / GENERAL
A16: Marketing | B16: 15000 | C16: 15450 | D16: 15914 | E16: 16391 | F16: 16883
A17: Professional Development | B17: 8000 | C17: 8240 | D17: 8487 | E17: 8742 | F17: 9004
A18: Accounting & Legal | B18: 12000 | C18: 12360 | D18: 12731 | E18: 13113 | F18: 13506
A19: Total ADMINISTRATIVE | B19: =SUM(B16:B18) -> 35000 | C19: =SUM(C16:C18) -> 36050 | D19: =SUM(D16:D18) -> 37132 | E19: =SUM(E16:E18) -> 38246 | F19: =SUM(F16:F18) -> 39393
A21: TOTAL OPERATING EXPENSES | B21: =B5+B8+B14+B19 -> 271400 | C21: =C5+C8+C14+C19 -> 310442 | D21: =D5+D8+D14+D19 -> 351602 | E21: =E5+E8+E14+E19 -> 389506 | F21: =F5+F8+F14+F19 -> 417907

Sheet Capital & Debt
B1: Year 1 | C1: Year 2 | D1: Year 3 | E1: Year 4 | F1: Year 5
A2: CAPITAL EXPENDITURES & DEBT SERVICE
A3: Facility Buildout Loan | B3: 34064.393 | C3: 34064.393 | D3: 34064.393 | E3: 34064.393 | F3: 34064.393
A4: Furniture & Equipment | B4: 25000 | C4: 10000 | D4: 10000 | E4: 5000 | F4: 5000
A5: TOTAL CAPITAL & DEBT | B5: =SUM(B3:B4) -> 59064 | C5: =SUM(C3:C4) -> 44064 | D5: =SUM(D3:D4) -> 44064 | E5: =SUM(E3:E4) -> 39064 | F5: =SUM(F3:F4) -> 39064

Sheet Financial Model
A1: 5-Year Financial Model | B1: Year 1 | C1: Year 2 | D1: Year 3 | E1: Year 4 | F1: Year 5
A2: Total Revenue | B2: ='Revenue Schedule'!B21 -> 1975000 | C2: ='Revenue Schedule'!C21 -> 2612670 | D2: ='Revenue Schedule'!D21 -> 3286760 | E2: ='Revenue Schedule'!E21 -> 3895050 | F2: ='Revenue Schedule'!F21 -> 4323000
A3: Personnel Costs | B3: ='Staffing & Personnel'!B25 -> 854772 | C3: ='Staffing & Personnel'!C25 -> 854772 | D3: ='Staffing & Personnel'!D25 -> 854772 | E3: ='Staffing & Personnel'!E25 -> 854772 | F3: ='Staffing & Personnel'!F25 -> 854772
A4: Operating Expenses | B4: ='Operating Expenses'!B21 -> 271400 | C4: ='Operating Expenses'!C21 -> 310442 | D4: ='Operating Expenses'!D21 -> 351602 | E4: ='Operating Expenses'!E21 -> 389506 | F4: ='Operating Expenses'!F21 -> 417907
A5: Capital & Debt | B5: ='Capital & Debt'!B5 -> 59064 | C5: ='Capital & Debt'!C5 -> 44064 | D5: ='Capital & Debt'!D5 -> 44064 | E5: ='Capital & Debt'!E5 -> 39064 | F5: ='Capital & Debt'!F5 -> 39064
A6: Total Expenses | B6: =B3+B4+B5 -> 1185236 | C6: =C3+C4+C5 -> 1209278 | D6: =D3+D4+D5 -> 1250438 | E6: =E3+E4+E5 -> 1283342 | F6: =F3+F4+F5 -> 1311743
A7: Net Income | B7: =B2-B6 -> 789764 | C7: =C2-C6 -> 1403392 | D7: =D2-D6 -> 2036322 | E7: =E2-E6 -> 2611708 | F7: =F2-F6 -> 3011257
A8: Cumulative Net Income | B8: =B7 -> 789764 | C8: =B8+C7 -> 2193156 | D8: =C8+D7 -> 4229478 | E8: =D8+E7 -> 6841186 | F8: =E8+F7 -> 9852443
A9: Operating Reserve (Months) | B9: =IF(B6=0,0,IF(B8>0,B8/(B6/12),0)) -> 7.9960177 | C9: =IF(C6=0,0,IF(C8>0,C8/(C6/12),0)) -> 21.763293 | D9: =IF(D6=0,0,IF(D8>0,D8/(D6/12),0)) -> 40.588766 | E9: =IF(E6=0,0,IF(E8>0,E8/(E6/12),0)) -> 63.969099 | F9: =IF(F6=0,0,IF(F8>0,F8/(F6/12),0)) -> 90.131463
A10: Break-even | B10: ✓ Break-even

Sheet Summary
A1: Financial Model Summary
A2: Prepared by SchoolStack Budget
A4: SCHOOL INFORMATION
A5: School Name | B5: Heritage Academy
A6: School Type | B6: Private School
A7: Entity Type | B7: 501(c)(3) Nonprofit
A8: EIN | B8: 59-9876543
A9: School Stage | B9: Operating School
A10: State | B10: FL
A11: Fiscal Year Start | B11: July
A12: Max Student Capacity | B12: 200
A14: ENROLLMENT TREND
B15: Year 1 | C15: Year 2 | D15: Year 3 | E15: Year 4 | F15: Year 5
A16: Students | B16: ='Revenue Schedule'!B2 -> 100 | C16: ='Revenue Schedule'!C2 -> 130 | D16: ='Revenue Schedule'!D2 -> 160 | E16: ='Revenue Schedule'!E2 -> 185 | F16: ='Revenue Schedule'!F2 -> 200
A17: Enrollment Growth % | B17: - | C17: =IF(B16=0,0,(C16-B16)/B16) -> 0.3 | D17: =IF(C16=0,0,(D16-C16)/C16) -> 0.23076923 | E17: =IF(D16=0,0,(E16-D16)/D16) -> 0.15625 | F17: =IF(E16=0,0,(F16-E16)/E16) -> 0.081081081
B19: Year 1 | C19: Year 2 | D19: Year 3 | E19: Year 4 | F19: Year 5
A20: Total Revenue | B20: ='Financial Model'!B2 -> 1975000 | C20: ='Financial Model'!C2 -> 2612670 | D20: ='Financial Model'!D2 -> 3286760 | E20: ='Financial Model'!E2 -> 3895050 | F20: ='Financial Model'!F2 -> 4323000
A21: Personnel Costs | B21: ='Financial Model'!B3 -> 854772 | C21: ='Financial Model'!C3 -> 854772 | D21: ='Financial Model'!D3 -> 854772 | E21: ='Financial Model'!E3 -> 854772 | F21: ='Financial Model'!F3 -> 854772
A22: Operating Expenses | B22: ='Financial Model'!B4 -> 271400 | C22: ='Financial Model'!C4 -> 310442 | D22: ='Financial Model'!D4 -> 351602 | E22: ='Financial Model'!E4 -> 389506 | F22: ='Financial Model'!F4 -> 417907
A23: Total Expenses | B23: ='Financial Model'!B6 -> 1185236 | C23: ='Financial Model'!C6 -> 1209278 | D23: ='Financial Model'!D6 -> 1250438 | E23: ='Financial Model'!E6 -> 1283342 | F23: ='Financial Model'!F6 -> 1311743
A24: Net Income | B24: ='Financial Model'!B7 -> 789764 | C24: ='Financial Model'!C7 -> 1403392 | D24: ='Financial Model'!D7 -> 2036322 | E24: ='Financial Model'!E7 -> 2611708 | F24: ='Financial Model'!F7 -> 3011257
A25: Cumulative Net Income | B25: ='Financial Model'!B8 -> 789764 | C25: ='Financial Model'!C8 -> 2193156 | D25: ='Financial Model'!D8 -> 4229478 | E25: ='Financial Model'!E8 -> 6841186 | F25: ='Financial Model'!F8 -> 9852443
A26: Operating Reserve (Months) | B26: ='Financial Model'!B9 -> 7.9960177 | C26: ='Financial Model'!C9 -> 21.763293 | D26: ='Financial Model'!D9 -> 40.588766 | E26: ='Financial Model'!E9 -> 63.969099 | F26: ='Financial Model'!F9 -> 90.131463
A28: KEY RATIOS
A29: Revenue per Student | B29: =IF('Revenue Schedule'!B2=0,0,B20/'Revenue Schedule'!B2) -> 19750 | C29: =IF('Revenue Schedule'!C2=0,0,C20/'Revenue Schedule'!C2) -> 20097.462 | D29: =IF('Revenue Schedule'!D2=0,0,D20/'Revenue Schedule'!D2) -> 20542.25 | E29: =IF('Revenue Schedule'!E2=0,0,E20/'Revenue Schedule'!E2) -> 21054.324 | F29: =IF('Revenue Schedule'!F2=0,0,F20/'Revenue Schedule'!F2) -> 21615
A30: Personnel Cost as % of Revenue | B30: =IF(B20=0,0,'Financial Model'!B3/B20) -> 0.43279595 | C30: =IF(C20=0,0,'Financial Model'!C3/C20) -> 0.32716417 | D30: =IF(D20=0,0,'Financial Model'!D3/D20) -> 0.26006523 | E30: =IF(E20=0,0,'Financial Model'!E3/E20) -> 0.21945084 | F30: =IF(F20=0,0,'Financial Model'!F3/F20) -> 0.19772658
A31: Operating Cost as % of Revenue | B31: =IF(B20=0,0,'Financial Model'!B4/B20) -> 0.13741772 | C31: =IF(C20=0,0,'Financial Model'!C4/C20) -> 0.11882174 | D31: =IF(D20=0,0,'Financial Model'!D4/D20) -> 0.10697526 | E31: =IF(E20=0,0,'Financial Model'!E4/E20) -> 0.10000026 | F31: =IF(F20=0,0,'Financial Model'!F4/F20) -> 0.096670599
A32: Net Margin % | B32: =IF(B20=0,0,B24/B20) -> 0.39988051 | C32: =IF(C20=0,0,C24/C20) -> 0.53714859 | D32: =IF(D20=0,0,D24/D20) -> 0.61955299 | E32: =IF(E20=0,0,E24/E20) -> 0.67051976 | F32: =IF(F20=0,0,F24/F20) -> 0.6965665
A34: REVENUE MIX TREND
A35: Tuition & Fees % | B35: 0.56750572 | C35: 0.57327772 | D35: 0.57680526 | E35: 0.57892806 | F35: 0.58017432
A36: Public Funding % | B36: 0.39816934 | C36: 0.40253422 | D36: 0.40535348 | E36: 0.40718125 | F36: 0.40835731
A37: Philanthropy % | B37: 0.034324943 | C37: 0.024188059 | D37: 0.017841262 | E37: 0.01389069 | F37: 0.011468368

Sheet Prior-Year Snapshot
A1: Prior-Year Snapshot
A3: PRIOR YEAR ACTUALS
A4: Ending Enrollment | B4: 85
A5: Total Revenue | B5: 1200000
A6: Total Expenses | B6: 1150000
A7: Ending Cash Balance | B7: 75000
A8: Net Income (Prior Year) | B8: 50000
A9: Cash Reserve (Months) | B9: 0.8

Sheet Financial Health
B2: Heritage Academy — Financial Health Dashboard
B3: Generated March 27, 2026
B4: ● Green = healthy | D4: ◐ Yellow = monitor | F4: ○ Red = action needed
B6: Metric | C6: Year 1 | D6: Year 2 | E6: Year 3 | F6: Year 4 | G6: Year 5 | H6: Benchmark
B7: Enrollment | C7: 100 | D7: 130 | E7: 160 | F7: 185 | G7: 200
B8: Revenue | C8: 1975000 | D8: 2612670 | E8: 3286760 | F8: 3895050 | G8: 4323000
B9: Personnel | C9: 854772 | D9: 854772 | E9: 854772 | F9: 854772 | G9: 854772
B10: Operating Expenses | C10: 271400 | D10: 310442 | E10: 351602 | F10: 389506 | G10: 417907
B11: Debt Service | C11: 34064.393 | D11: 34064.393 | E11: 34064.393 | F11: 34064.393 | G11: 34064.393
B12: Net Income | C12: 789764 | D12: 1403392 | E12: 2036322 | F12: 2611708 | G12: 3011257
B13: Ending Cash | C13: 864764 | D13: 2268156 | E13: 4304478 | F13: 6916186 | G13: 9927443
B14: Net Margin | C14: 0.39988051 | D14: 0.53714859 | E14: 0.61955299 | F14: 0.67051976 | G14: 0.6965665
B15: Revenue per Student | C15: 19750 | D15: 20097.462 | E15: 20542.25 | F15: 21054.324 | G15: 21615 | H15: ≥ $10,000
B16: Cost per Student | C16: 11602.364 | D16: 9225.2184 | E16: 7752.74 | F16: 6909.9589 | G16: 6533.717
B17: Instructional / Student | C17: 600 | D17: 618 | E17: 637 | F17: 656 | G17: 675
B18: Facility / Student | C18: 1364 | D18: 1080.7077 | E18: 904.41125 | F18: 805.64948 | G18: 767.55949 | H18: ≤ $2,000 / $2k–$3.5k / > $3,500
B19: Surplus per Student | C19: 7897.64 | D19: 10795.323 | E19: 12727.013 | F19: 14117.341 | G19: 15056.285
B20: Payroll % | C20: 0.43279595 | D20: 0.32716417 | E20: 0.26006523 | F20: 0.21945084 | G20: 0.19772658 | H20: ≤ 55%
B21: Facility % | C21: 0.069063291 | D21: 0.053773343 | E21: 0.044026884 | F21: 0.038265274 | G21: 0.035510502 | H21: ≤ 15%
B22: Operating Margin | C22: 0.42978633 | D22: 0.55401409 | E22: 0.63295951 | F22: 0.6805489 | G22: 0.70560282 | H22: ≥ 10%
B23: Revenue Sources | C23: 4 | D23: 4 | E23: 4 | F23: 4 | G23: 4 | H23: ≥ 3 sources
B24: DSCR | C24: 24.918336 | D24: 42.491759 | E24: 61.072158 | F24: 77.816504 | G24: 89.545731 | H24: ≥ 1.25x
B25: Break-even Year | C25: =IF('Financial Model'!B8>=0,"✓ Break-even","") -> ✓ Break-even | D25: =IF(AND('Financial Model'!C8>=0,'Financial Model'!B8<0),"✓ Break-even","") -> 0 | E25: =IF(AND('Financial Model'!D8>=0,'Financial Model'!C8<0),"✓ Break-even","") -> 0 | F25: =IF(AND('Financial Model'!E8>=0,'Financial Model'!D8<0),"✓ Break-even","") -> 0 | G25: =IF(AND('Financial Model'!F8>=0,'Financial Model'!E8<0),"✓ Break-even","") -> 0 | H25: Year 1
B26: Cash Runway (Months) | C26: 9 | D26: 23 | E26: 42 | F26: 60+ | G26: 60+ | H26: ≥ 24 months
B27: Days Cash on Hand | C27: 272 | D27: 690 | E27: 1267 | F27: 1975 | G27: 2773 | H27: ≥ 90 days
B29: FINANCIAL HEALTH SIGNALS | C29: Status | D29: Assessment | F29: Watch Item
B30: Viability | C30: ● Healthy | D30: The model reaches net income early and sustains strong margins through Year 5. | F30: Monitor enrollment actuals vs. projections in Year 1.
B31: Liquidity | C31: ● Healthy | D31: Cash stays positive throughout the projection and reserves exceed 3 months of expenses. | F31: Maintain reserves as a buffer against seasonal revenue dips.
B32: Staffing Burden | C32: ● Healthy | D32: Staffing at 20% of revenue leaves room for facilities, programs, and reserves. | F32: As you add staff, ensure staffing stays below 60% of revenue.
B33: Facility Burden | C33: ● Healthy | D33: Facility costs at 4% of revenue are well-managed and leave budget for programs. | F33: Watch for rent escalation clauses that could push this higher over time.
B34: Debt Affordability | C34: ● Healthy | D34: DSCR of 89.55x provides comfortable coverage of debt payments with room to spare. | F34: Maintain this ratio as you take on any additional debt.
B35: Revenue Concentration | C35: ● Healthy | D35: Revenue is anchored to enrollment-driven income — the strongest foundation for a school model. A focused revenue stream is a strength when backed by dependable demand. | F35: Continue to pressure-test enrollment assumptions: recruitment pipeline, waitlist depth, retention rates, and collection reliability.
B36: Reserve Strength | C36: ● Healthy | D36: 91.2 months of reserves by Year 5 — a strong buffer for unexpected costs. | F36: Continue growing reserves toward 6 months for best-in-class financial health.
B38: Summary | C38: 7 Healthy | 0 Watch | 0 Needs Attention
B40: Built by SchoolStack Budget • budget.schoolstack.ai
