Workbook

Sheet Cover
B3: SchoolStack Budget
B4: 5-Year Financial Model
B8: Prepared for
B9: Bright Horizons Microschool
B10: Microschool • LLC - Single Member • AZ
B12: Date Prepared | C12: May 7, 2026
B15: KEY HIGHLIGHTS
B16: Year 5 Revenue | C16: 516085
B17: Year 5 Net Income | C17: 282277
B18: Year 5 Net Margin | C18: 0.54695835
B19: Operating Reserve (Months) | C19: 48.442876
B20: Year 5 Enrollment | C20: 25
B23: TABLE OF CONTENTS
B24: Assumptions
B25: Revenue Schedule
B26: Staffing & Personnel
B27: Operating Expenses
B28: Capital & Debt
B29: Financial Model
B30: Summary
B31: Decision History
B34: Generated by SchoolStack Budget • budget.schoolstack.ai

Sheet Assumptions
A1: SchoolStack Budget - Assumptions
B2: Editable assumption — change this value | E2: Calculated — driven by formula
A3: SCHOOL INFORMATION
A4: School Name | B4: Bright Horizons Microschool
A5: State | B5: AZ
A6: School Type | B6: Microschool
A7: Entity Type | B7: LLC - Single Member
A8: EIN | B8: 88-1234567
A9: School Stage | B9: New School
A10: Opening Year | B10: 2026
A11: Current Students | B11: 0
A12: Max Student Capacity | B12: 25
A13: Fiscal Year Start | B13: July
A14: Accounting Basis
A15: Year 1 Operating Months | B15: 10
A16: Location Secured | B16: Yes
A17: Facility Address | B17: 123 Main St, Scottsdale, AZ, 85251
A18: Facility Ownership | B18: Rented / Leased
A19: Monthly Rent | B19: $2,500
A20: Annual Rent Escalation | B20: 3%
A22: ENROLLMENT BY YEAR
A23: Year 1 Students | B23: 12
A24: Year 2 Students | B24: 18
A25: Year 3 Students | B25: 22
A26: Year 4 Students | B26: 25
A27: Year 5 Students | B27: 25
A29: GROWTH & ESCALATION ASSUMPTIONS
A30: Annual Salary Escalation | B30: 0.03
A31: General Cost Inflation | B31: 0.025
A32: Year 1 Proration Factor | B32: 0.83333333
A33: Projection Period | B33: 5 Years

Sheet Revenue Schedule
B1: Year 1 | C1: Year 2 | D1: Year 3 | E1: Year 4 | F1: Year 5
A2: Students | B2: =Assumptions!B23 -> 12 | C2: =Assumptions!B24 -> 18 | D2: =Assumptions!B25 -> 22 | E2: =Assumptions!B26 -> 25 | F2: =Assumptions!B27 -> 25
A3: TUITION & STUDENT FEES
A4: Tuition | B4: =12000*Assumptions!B23 -> 144000 | C4: =12360*Assumptions!B24 -> 222480 | D4: =12731*Assumptions!B25 -> 280082 | E4: =13113*Assumptions!B26 -> 327825 | F4: =13506*Assumptions!B27 -> 337650
A5: Registration Fee | B5: =250*Assumptions!B23 -> 3000 | C5: =250*Assumptions!B24 -> 4500 | D5: =250*Assumptions!B25 -> 5500 | E5: =250*Assumptions!B26 -> 6250 | F5: =250*Assumptions!B27 -> 6250
A6: Total TUITION & STUDENT FEES | B6: =SUM(B4:B5) -> 147000 | C6: =SUM(C4:C5) -> 226980 | D6: =SUM(D4:D5) -> 285582 | E6: =SUM(E4:E5) -> 334075 | F6: =SUM(F4:F5) -> 343900
A7: TUITION OFFSETS
A8: Scholarship Discount | B8: =-B4*0.1 -> -14400 | C8: =-C4*0.1 -> -22248 | D8: =-D4*0.1 -> -28008.2 | E8: =-E4*0.1 -> -32782.5 | F8: =-F4*0.1 -> -33765
A9: Total TUITION OFFSETS | B9: =SUM(B8:B8) -> -14400 | C9: =SUM(C8:C8) -> -22248 | D9: =SUM(D8:D8) -> -28008 | E9: =SUM(E8:E8) -> -32782 | F9: =SUM(F8:F8) -> -33765
A10: SCHOOL CHOICE / CHOICE FUNDING
A11: AZ ESA Funds | B11: =7000*Assumptions!B23 -> 84000 | C11: =7210*Assumptions!B24 -> 129780 | D11: =7426*Assumptions!B25 -> 163372 | E11: =7649*Assumptions!B26 -> 191225 | F11: =7878*Assumptions!B27 -> 196950
A12: Total SCHOOL CHOICE / CHOICE FUNDING | B12: =SUM(B11:B11) -> 84000 | C12: =SUM(C11:C11) -> 129780 | D12: =SUM(D11:D11) -> 163372 | E12: =SUM(E11:E11) -> 191225 | F12: =SUM(F11:F11) -> 196950
A13: PHILANTHROPY
A14: Annual Fundraising | B14: 5000 | C14: 6000 | D14: 7000 | E14: 8000 | F14: 9000
A15: Total PHILANTHROPY | B15: =SUM(B14:B14) -> 5000 | C15: =SUM(C14:C14) -> 6000 | D15: =SUM(D14:D14) -> 7000 | E15: =SUM(E14:E14) -> 8000 | F15: =SUM(F14:F14) -> 9000
A17: TOTAL NET REVENUE | B17: =B6+B9+B12+B15 -> 221600 | C17: =C6+C9+C12+C15 -> 340512 | D17: =D6+D9+D12+D15 -> 427946 | E17: =E6+E9+E12+E15 -> 500518 | F17: =F6+F9+F12+F15 -> 516085

Sheet Staffing & Personnel
A1: SchoolStack Budget - Staffing & Personnel
A3: Role | B3: Function | C3: Type | D3: FTE | E3: Annual Rate | F3: Benefits % | G3: Payroll Tax % | H3: Total Annual Cost
A4: Founder / Head of School | B4: School Leadership | C4: Full-Time | D4: 1 | E4: 55000 | F4: 0.2 | G4: 0.0765 | H4: 70207.5
A5: Lead Teacher | B5: Instructional | C5: Full-Time | D5: 1 | E5: 45000 | F5: 0.2 | G5: 0.0765 | H5: 57442.5
A6: Teaching Assistant | B6: Instructional | C6: Part-Time | D6: 0.5 | E6: 28000 | F6: 0 | G6: 0.0765 | H6: 15071
A8: PERSONNEL COST SUMMARY
A9: Total Headcount | B9: 3
A10: Total FTE | B10: 2.5
A11: Salaries & Wages | B11: 114000
A12: Benefits | B12: 20000
A13: Payroll Taxes | B13: 8721
A14: Contracted Personnel | B14: 0
A15: Total Annual Personnel Cost | B15: 142721
A17: PERSONNEL COST PROJECTION
B18: Year 1 | C18: Year 2 | D18: Year 3 | E18: Year 4 | F18: Year 5
A19: Base Personnel Cost | B19: 142721 | C19: 142721 | D19: 142721 | E19: 142721 | F19: 142721
A20: Salary Escalation Factor | B20: =(1+Assumptions!B30)^0 -> 1 | C20: =(1+Assumptions!B30)^1 -> 1.03 | D20: =(1+Assumptions!B30)^2 -> 1.0609 | E20: =(1+Assumptions!B30)^3 -> 1.092727 | F20: =(1+Assumptions!B30)^4 -> 1.1255088
A21: Proration Factor | B21: =Assumptions!B32 -> 0.83333333 | C21: 1 | D21: 1 | E21: 1 | F21: 1
A22: Total Personnel Cost | B22: =B19*B20*B21 -> 118934 | C22: =C19*C20*C21 -> 147003 | D22: =D19*D20*D21 -> 151413 | E22: =E19*E20*E21 -> 155955 | F22: =F19*F20*F21 -> 160634

Sheet Operating Expenses
B1: Year 1 | C1: Year 2 | D1: Year 3 | E1: Year 4 | F1: Year 5
A2: Students | B2: =Assumptions!B23 -> 12 | C2: =Assumptions!B24 -> 18 | D2: =Assumptions!B25 -> 22 | E2: =Assumptions!B26 -> 25 | F2: =Assumptions!B27 -> 25
A3: INSTRUCTIONAL / PROGRAM
A4: Curriculum & Materials | B4: =500*Assumptions!B23 -> 6000 | C4: =515*Assumptions!B24 -> 9270 | D4: =530*Assumptions!B25 -> 11660 | E4: =546*Assumptions!B26 -> 13650 | F4: =562*Assumptions!B27 -> 14050
A5: Total INSTRUCTIONAL | B5: =SUM(B4:B4) -> 6000 | C5: =SUM(C4:C4) -> 9270 | D5: =SUM(D4:D4) -> 11660 | E5: =SUM(E4:E4) -> 13650 | F5: =SUM(F4:F4) -> 14050
A6: TECHNOLOGY
A7: Technology | B7: =300*Assumptions!B23 -> 3600 | C7: =309*Assumptions!B24 -> 5562 | D7: =318*Assumptions!B25 -> 6996 | E7: =328*Assumptions!B26 -> 8200 | F7: =338*Assumptions!B27 -> 8450
A8: Total TECHNOLOGY | B8: =SUM(B7:B7) -> 3600 | C8: =SUM(C7:C7) -> 5562 | D8: =SUM(D7:D7) -> 6996 | E8: =SUM(E7:E7) -> 8200 | F8: =SUM(F7:F7) -> 8450
A9: OCCUPANCY / FACILITY
A10: Rent | B10: =2500*12 -> 30000 | C10: =2575*12 -> 30900 | D10: =2652*12 -> 31824 | E10: =2732*12 -> 32784 | F10: =2814*12 -> 33768
A11: Utilities | B11: =300*12 -> 3600 | C11: =308*12 -> 3696 | D11: =316*12 -> 3792 | E11: =324*12 -> 3888 | F11: =332*12 -> 3984
A12: Insurance | B12: 2400 | C12: 2460 | D12: 2522 | E12: 2585 | F12: 2650
A13: Total OCCUPANCY | B13: =SUM(B10:B12) -> 36000 | C13: =SUM(C10:C12) -> 37056 | D13: =SUM(D10:D12) -> 38138 | E13: =SUM(E10:E12) -> 39257 | F13: =SUM(F10:F12) -> 40402
A14: ADMINISTRATIVE / GENERAL
A15: Marketing | B15: 3000 | C15: 3075 | D15: 3152 | E15: 3231 | F15: 3312
A16: Total ADMINISTRATIVE | B16: =SUM(B15:B15) -> 3000 | C16: =SUM(C15:C15) -> 3075 | D16: =SUM(D15:D15) -> 3152 | E16: =SUM(E15:E15) -> 3231 | F16: =SUM(F15:F15) -> 3312
A18: TOTAL OPERATING EXPENSES | B18: =B5+B8+B13+B16 -> 48600 | C18: =C5+C8+C13+C16 -> 54963 | D18: =D5+D8+D13+D16 -> 59946 | E18: =E5+E8+E13+E16 -> 64338 | F18: =F5+F8+F13+F16 -> 66214

Sheet Capital & Debt
B1: Year 1 | C1: Year 2 | D1: Year 3 | E1: Year 4 | F1: Year 5
A2: CAPITAL EXPENDITURES & DEBT SERVICE
A3: Equipment Loan | B3: 6959.8086 | C3: 6959.8086 | D3: 6959.8086 | E3: 6959.8086 | F3: 6959.8086
A4: TOTAL CAPITAL & DEBT | B4: =SUM(B3:B3) -> 6960 | C4: =SUM(C3:C3) -> 6960 | D4: =SUM(D3:D3) -> 6960 | E4: =SUM(E3:E3) -> 6960 | F4: =SUM(F3:F3) -> 6960

Sheet Financial Model
A1: 5-Year Financial Model | B1: Year 1 | C1: Year 2 | D1: Year 3 | E1: Year 4 | F1: Year 5
A2: Total Revenue | B2: ='Revenue Schedule'!B17 -> 221600 | C2: ='Revenue Schedule'!C17 -> 340512 | D2: ='Revenue Schedule'!D17 -> 427946 | E2: ='Revenue Schedule'!E17 -> 500518 | F2: ='Revenue Schedule'!F17 -> 516085
A3: Personnel Costs | B3: ='Staffing & Personnel'!B22 -> 118934 | C3: ='Staffing & Personnel'!C22 -> 147003 | D3: ='Staffing & Personnel'!D22 -> 151413 | E3: ='Staffing & Personnel'!E22 -> 155955 | F3: ='Staffing & Personnel'!F22 -> 160634
A4: Operating Expenses | B4: ='Operating Expenses'!B18 -> 48600 | C4: ='Operating Expenses'!C18 -> 54963 | D4: ='Operating Expenses'!D18 -> 59946 | E4: ='Operating Expenses'!E18 -> 64338 | F4: ='Operating Expenses'!F18 -> 66214
A5: Capital & Debt | B5: ='Capital & Debt'!B4 -> 6960 | C5: ='Capital & Debt'!C4 -> 6960 | D5: ='Capital & Debt'!D4 -> 6960 | E5: ='Capital & Debt'!E4 -> 6960 | F5: ='Capital & Debt'!F4 -> 6960
A6: Total Expenses | B6: =B3+B4+B5 -> 174494 | C6: =C3+C4+C5 -> 208926 | D6: =D3+D4+D5 -> 218319 | E6: =E3+E4+E5 -> 227253 | F6: =F3+F4+F5 -> 233808
A7: Profit | B7: =B2-B6 -> 47106 | C7: =C2-C6 -> 131586 | D7: =D2-D6 -> 209627 | E7: =E2-E6 -> 273265 | F7: =F2-F6 -> 282277
A8: Cumulative Profit | B8: =B7 -> 47106 | C8: =B8+C7 -> 178692 | D8: =C8+D7 -> 388319 | E8: =D8+E7 -> 661584 | F8: =E8+F7 -> 943861
A9: Operating Reserve (Months) | B9: =IF(B6=0,0,IF(B8>0,B8/(B6/12),0)) -> 3.2394925 | C9: =IF(C6=0,0,IF(C8>0,C8/(C6/12),0)) -> 10.263462 | D9: =IF(D6=0,0,IF(D8>0,D8/(D6/12),0)) -> 21.344125 | E9: =IF(E6=0,0,IF(E8>0,E8/(E6/12),0)) -> 34.934668 | F9: =IF(F6=0,0,IF(F8>0,F8/(F6/12),0)) -> 48.442876
A10: Break-even | B10: ✓ Break-even

Sheet Summary
A1: Financial Model Summary
A2: Prepared by SchoolStack Budget
A4: SCHOOL INFORMATION
A5: School Name | B5: Bright Horizons Microschool
A6: School Type | B6: Microschool
A7: Entity Type | B7: LLC - Single Member
A8: EIN | B8: 88-1234567
A9: School Stage | B9: New School
A10: State | B10: AZ
A11: Fiscal Year Start | B11: July
A12: Accounting Basis
A13: Max Student Capacity | B13: 25
A15: ENROLLMENT TREND
B16: Year 1 | C16: Year 2 | D16: Year 3 | E16: Year 4 | F16: Year 5
A17: Students | B17: ='Revenue Schedule'!B2 -> 12 | C17: ='Revenue Schedule'!C2 -> 18 | D17: ='Revenue Schedule'!D2 -> 22 | E17: ='Revenue Schedule'!E2 -> 25 | F17: ='Revenue Schedule'!F2 -> 25
A18: Enrollment Growth % | B18: - | C18: =IF(B17=0,0,(C17-B17)/B17) -> 0.5 | D18: =IF(C17=0,0,(D17-C17)/C17) -> 0.22222222 | E18: =IF(D17=0,0,(E17-D17)/D17) -> 0.13636364 | F18: =IF(E17=0,0,(F17-E17)/E17) -> 0
B20: Year 1 | C20: Year 2 | D20: Year 3 | E20: Year 4 | F20: Year 5
A21: Total Revenue | B21: ='Financial Model'!B2 -> 221600 | C21: ='Financial Model'!C2 -> 340512 | D21: ='Financial Model'!D2 -> 427946 | E21: ='Financial Model'!E2 -> 500518 | F21: ='Financial Model'!F2 -> 516085
A22: Personnel Costs | B22: ='Financial Model'!B3 -> 118934 | C22: ='Financial Model'!C3 -> 147003 | D22: ='Financial Model'!D3 -> 151413 | E22: ='Financial Model'!E3 -> 155955 | F22: ='Financial Model'!F3 -> 160634
A23: Operating Expenses | B23: ='Financial Model'!B4 -> 48600 | C23: ='Financial Model'!C4 -> 54963 | D23: ='Financial Model'!D4 -> 59946 | E23: ='Financial Model'!E4 -> 64338 | F23: ='Financial Model'!F4 -> 66214
A24: Total Expenses | B24: ='Financial Model'!B6 -> 174494 | C24: ='Financial Model'!C6 -> 208926 | D24: ='Financial Model'!D6 -> 218319 | E24: ='Financial Model'!E6 -> 227253 | F24: ='Financial Model'!F6 -> 233808
A25: Profit | B25: ='Financial Model'!B7 -> 47106 | C25: ='Financial Model'!C7 -> 131586 | D25: ='Financial Model'!D7 -> 209627 | E25: ='Financial Model'!E7 -> 273265 | F25: ='Financial Model'!F7 -> 282277
A26: Cumulative Profit | B26: ='Financial Model'!B8 -> 47106 | C26: ='Financial Model'!C8 -> 178692 | D26: ='Financial Model'!D8 -> 388319 | E26: ='Financial Model'!E8 -> 661584 | F26: ='Financial Model'!F8 -> 943861
A27: Operating Reserve (Months) | B27: ='Financial Model'!B9 -> 3.2394925 | C27: ='Financial Model'!C9 -> 10.263462 | D27: ='Financial Model'!D9 -> 21.344125 | E27: ='Financial Model'!E9 -> 34.934668 | F27: ='Financial Model'!F9 -> 48.442876
A29: KEY RATIOS
A30: Revenue per Student | B30: =IF('Revenue Schedule'!B2=0,0,B21/'Revenue Schedule'!B2) -> 18466.667 | C30: =IF('Revenue Schedule'!C2=0,0,C21/'Revenue Schedule'!C2) -> 18917.333 | D30: =IF('Revenue Schedule'!D2=0,0,D21/'Revenue Schedule'!D2) -> 19452.091 | E30: =IF('Revenue Schedule'!E2=0,0,E21/'Revenue Schedule'!E2) -> 20020.72 | F30: =IF('Revenue Schedule'!F2=0,0,F21/'Revenue Schedule'!F2) -> 20643.4
A31: Personnel Cost as % of Revenue | B31: =IF(B21=0,0,'Financial Model'!B3/B21) -> 0.53670578 | C31: =IF(C21=0,0,'Financial Model'!C3/C21) -> 0.43171166 | D31: =IF(D21=0,0,'Financial Model'!D3/D21) -> 0.35381333 | E31: =IF(E21=0,0,'Financial Model'!E3/E21) -> 0.3115872 | F31: =IF(F21=0,0,'Financial Model'!F3/F21) -> 0.31125493
A32: Operating Cost as % of Revenue | B32: =IF(B21=0,0,'Financial Model'!B4/B21) -> 0.21931408 | C32: =IF(C21=0,0,'Financial Model'!C4/C21) -> 0.16141281 | D32: =IF(D21=0,0,'Financial Model'!D4/D21) -> 0.14007842 | E32: =IF(E21=0,0,'Financial Model'!E4/E21) -> 0.12854283 | F32: =IF(F21=0,0,'Financial Model'!F4/F21) -> 0.12830057
A33: Profit Margin % | B33: =IF(B21=0,0,B25/B21) -> 0.2125722 | C33: =IF(C21=0,0,C25/C21) -> 0.38643572 | D33: =IF(D21=0,0,D25/D21) -> 0.48984451 | E33: =IF(E21=0,0,E25/E21) -> 0.54596438 | F33: =IF(F21=0,0,F25/F21) -> 0.54695835
A35: REVENUE MIX TREND
A36: Tuition & Fees % | B36: 0.59837545 | C36: 0.60124753 | D36: 0.60188416 | E36: 0.60196197 | F36: 0.60093783
A37: Public Funding % | B37: 0.37906137 | C37: 0.38113194 | D37: 0.38175862 | E37: 0.38205457 | F37: 0.38162318
A38: Philanthropy % | B38: 0.022563177 | C38: 0.017620524 | D38: 0.016357212 | E38: 0.015983457 | F38: 0.017438988

Sheet Decision History
B1: Decision History
B2: Track record of 5 tracked decisions (2 pursued, 1 on hold, 2 declined). Each entry shows the modeled change, the outcome the team logged, and any retrospective notes captured after the fact.
B4: Decision | C4: Type | D4: Outcome | E4: Applied to base model? | F4: Outcome logged | G4: Modeled change | H4: What happened (retrospective)
B5: Add Middle School program | C5: Add a program | D5: Pursued | E5: [APPLIED] Folded into the base model on Apr 12, 2025 | F5: Apr 10, 2025 | G5: • Program: Middle School (6-8) • Tuition $14,000/yr • Adds 72 cumulative students (5 yrs) • +2 FTE | H5: Launched in fall 2025; enrollment hit plan within 1 student.
B6: Increase retention focus | C6: Change enrollment | D6: Pursued | E6: [PENDING] Pending apply to base model | F6: Mar 5, 2025 | G6: • Enrollment +14 cumulative • Retention 92% | H6: Retention initiatives approved; planner will reflect after Q2 board review.
B7: Evaluate downtown campus | C7: Evaluate a site | D7: On hold | E7: — | F7: Mar 25, 2025 | G7: • Rent $8,500/mo • Rent escalation 4% • Sqft +1500 • Fit-out $75,000 (Y1) | H7: Landlord negotiations paused while waiting on city zoning ruling.
B8: Reduce K cohort | C8: Change enrollment | D8: Declined | E8: — | F8: Mar 15, 2025 | G8: • Enrollment -8 cumulative • Tuition -$500/student | H8: Board declined; enrollment goals retained as originally modeled.
B9: Move to larger building | C9: Evaluate a site | D9: Declined | E9: — | F9: Feb 10, 2025 | G9: • Rent $12,000/mo • Sqft +4000 | H9: Costs out of reach; revisited next year after capital campaign.
B11: Generated by SchoolStack Budget (budget.schoolstack.ai)

Sheet Financial Health
B2: Bright Horizons Microschool — Financial Health Dashboard
B3: Generated May 7, 2026
B4: ● Green = healthy | D4: ◐ Yellow = monitor | F4: ○ Red = action needed
B6: Metric | C6: Year 1 | D6: Year 2 | E6: Year 3 | F6: Year 4 | G6: Year 5 | H6: Benchmark
B7: Enrollment | C7: 12 | D7: 18 | E7: 22 | F7: 25 | G7: 25
B8: Revenue | C8: 221600 | D8: 340512 | E8: 427946 | F8: 500518 | G8: 516085
B9: Personnel | C9: 118934 | D9: 147003 | E9: 151413 | F9: 155955 | G9: 160634
B10: Operating Expenses | C10: 48600 | D10: 54963 | E10: 59946 | F10: 64338 | G10: 66214
B11: Debt Service | C11: 6959.8086 | D11: 6959.8086 | E11: 6959.8086 | F11: 6959.8086 | G11: 6959.8086
B12: Net Income | C12: 47106 | D12: 131586 | E12: 209627 | F12: 273265 | G12: 282277
B13: Ending Cash | C13: 47106 | D13: 178692 | E13: 388319 | F13: 661584 | G13: 943861
B14: Net Margin | C14: 0.2125722 | D14: 0.38643572 | E14: 0.48984451 | F14: 0.54596438 | G14: 0.54695835
B15: Revenue per Student | C15: 18466.667 | D15: 18917.333 | E15: 19452.091 | F15: 20020.72 | G15: 20643.4 | H15: ≥ $10,000
B16: Cost per Student | C16: 14541.151 | D16: 11606.989 | E16: 9923.5822 | F16: 9090.1123 | G16: 9352.3123
B17: Instructional / Student | C17: 500 | D17: 515 | E17: 530 | F17: 546 | G17: 562
B18: Facility / Student | C18: 3000 | D18: 2058.6667 | E18: 1733.6818 | F18: 1570.1924 | G18: 1615.9706 | H18: ≤ $2,000 / $2k–$3.5k / > $3,500
B19: Surplus per Student | C19: 3925.5 | D19: 7310.3333 | E19: 9528.5 | F19: 10930.6 | G19: 11291.08
B20: Payroll % | C20: 0.53670578 | D20: 0.43171166 | E20: 0.35381333 | F20: 0.3115872 | G20: 0.31125493 | H20: ≤ 55%
B21: Facility % | C21: 0.16245487 | D21: 0.10882436 | E21: 0.089125731 | F21: 0.078428368 | G21: 0.078280253 | H21: ≤ 15%
B22: Operating Margin | C22: 0.24398014 | D22: 0.40687553 | E22: 0.50610825 | F22: 0.55986997 | G22: 0.5604445 | H22: ≥ 10%
B23: Revenue Sources | C23: 3 | D23: 3 | E23: 3 | F23: 3 | G23: 3 | H23: ≥ 3 sources
B24: DSCR | C24: 7.7683171 | D24: 19.906582 | E24: 31.119678 | F24: 40.26332 | G24: 41.558183 | H24: ≥ 1.25x
B25: Break-even Year | C25: =IF('Financial Model'!B8>=0,"✓ Break-even","") -> ✓ Break-even | D25: =IF(AND('Financial Model'!C8>=0,'Financial Model'!B8<0),"✓ Break-even","") -> 0 | E25: =IF(AND('Financial Model'!D8>=0,'Financial Model'!C8<0),"✓ Break-even","") -> 0 | F25: =IF(AND('Financial Model'!E8>=0,'Financial Model'!D8<0),"✓ Break-even","") -> 0 | G25: =IF(AND('Financial Model'!F8>=0,'Financial Model'!E8<0),"✓ Break-even","") -> 0 | H25: Year 1
B26: Cash Runway (Months) | C26: 3 | D26: 10 | E26: 21 | F26: 35 | G26: 48 | H26: ≥ 24 months
B27: Days Cash on Hand | C27: 99 | D27: 312 | E27: 649 | F27: 1063 | G27: 1473 | H27: ≥ 90 days
B29: FINANCIAL HEALTH SIGNALS | C29: Status | D29: Assessment | F29: Watch Item
B30: Viability | C30: ● Healthy | D30: The model reaches profit early and sustains strong margins through Year 5. | F30: Compare your real Year 1 enrollment against this projection as students enroll.
B31: Liquidity | C31: ● Healthy | D31: Cash stays positive throughout the projection and reserves exceed 3 months of expenses. | F31: Maintain reserves as a buffer against seasonal revenue dips.
B32: Staffing Burden | C32: ● Healthy | D32: Staffing at 31% of revenue leaves room for facilities, programs, and reserves. | F32: As you add staff, ensure staffing stays below 60% of revenue.
B33: Facility Burden | C33: ● Healthy | D33: Facility costs at 8% of revenue are well-managed and leave budget for programs. | F33: Watch for rent escalation clauses that could push this higher over time.
B34: Debt Affordability | C34: ● Healthy | D34: DSCR of 41.56x provides comfortable coverage of debt payments with room to spare. | F34: Maintain this ratio as you take on any additional debt.
B35: Revenue Concentration | C35: ● Healthy | D35: Revenue is anchored to enrollment-driven income — the strongest foundation for a school model. A focused revenue stream is a strength when backed by dependable demand. | F35: Continue to pressure-test enrollment assumptions: recruitment pipeline, waitlist depth, retention rates, and collection reliability.
B36: Reserve Strength | C36: ● Healthy | D36: 48.4 months of reserves by Year 5 — a strong buffer for unexpected costs. | F36: Continue growing reserves toward 6 months for best-in-class financial health.
B38: Summary | C38: 7 Healthy | 0 Watch | 0 Needs Attention
B40: Built by SchoolStack Budget • budget.schoolstack.ai
