Workbook

Sheet Cover
B3: SchoolStack Budget
B4: 5-Year Financial Model
B8: Prepared for
B9: Heritage Academy Charter
B10: Charter School • 501(c)(3) Nonprofit • AZ
B12: Date Prepared | C12: March 17, 2026
B15: KEY HIGHLIGHTS
B16: Year 5 Revenue | C16: 5891500
B17: Year 5 Net Income | C17: 3426282
B18: Year 5 Net Margin | C18: 0.58156361
B19: Operating Reserve (Months) | C19: 37.98701
B20: Year 5 Enrollment | C20: 500
B23: TABLE OF CONTENTS
B24: Assumptions
B25: Revenue Schedule
B26: Staffing & Personnel
B27: Operating Expenses
B28: Capital & Debt
B29: Financial Model
B30: Summary
B33: Generated by SchoolStack Budget • budget.schoolstack.ai

Sheet Assumptions
A1: SchoolStack Budget - Assumptions
A3: SCHOOL INFORMATION
A4: School Name | B4: Heritage Academy Charter
A5: State | B5: AZ
A6: School Type | B6: Charter School
A7: Entity Type | B7: 501(c)(3) Nonprofit
A8: EIN | B8: 86-4441234
A9: School Stage | B9: New School
A10: Opening Year | B10: 2026
A11: Current Students | B11: 0
A12: Max Student Capacity | B12: 600
A13: Fiscal Year Start | B13: July
A14: Year 1 Operating Months | B14: 10
A15: Location Secured | B15: Yes
A16: Facility Address | B16: 1200 N Central Ave, Phoenix, AZ, 85004
A17: Facility Ownership | B17: Rented / Leased
A18: Monthly Rent | B18: $22,000
A19: Annual Rent Escalation | B19: 3%
A21: ENROLLMENT BY YEAR
A22: Year 1 Students | B22: 120
A23: Year 2 Students | B23: 200
A24: Year 3 Students | B24: 300
A25: Year 4 Students | B25: 400
A26: Year 5 Students | B26: 500
A28: GROWTH & ESCALATION ASSUMPTIONS
A29: Annual Salary Escalation | B29: 0
A30: General Cost Inflation | B30: 0
A31: Year 1 Proration Factor | B31: 0.83333333
A32: Projection Period | B32: 5 Years

Sheet Revenue Schedule
B1: Year 1 | C1: Year 2 | D1: Year 3 | E1: Year 4 | F1: Year 5
A2: Students | B2: =Assumptions!B22 -> 120 | C2: =Assumptions!B23 -> 200 | D2: =Assumptions!B24 -> 300 | E2: =Assumptions!B25 -> 400 | F2: =Assumptions!B26 -> 500
A3: PUBLIC FUNDING
A4: State Per-Pupil Funding | B4: =8500*Assumptions!B22 -> 1020000 | C4: =8670*Assumptions!B23 -> 1734000 | D4: =8843*Assumptions!B24 -> 2652900 | E4: =9020*Assumptions!B25 -> 3608000 | F4: =9200*Assumptions!B26 -> 4600000
A5: Federal Title I | B5: =750*Assumptions!B22 -> 90000 | C5: =765*Assumptions!B23 -> 153000 | D5: =780*Assumptions!B24 -> 234000 | E5: =796*Assumptions!B25 -> 318400 | F5: =812*Assumptions!B26 -> 406000
A6: IDEA Special Ed | B6: =1100*Assumptions!B22 -> 132000 | C6: =1122*Assumptions!B23 -> 224400 | D6: =1144*Assumptions!B24 -> 343200 | E6: =1167*Assumptions!B25 -> 466800 | F6: =1191*Assumptions!B26 -> 595500
A7: Total PUBLIC FUNDING | B7: =SUM(B4:B6) -> 1242000 | C7: =SUM(C4:C6) -> 2111400 | D7: =SUM(D4:D6) -> 3230100 | E7: =SUM(E4:E6) -> 4393200 | F7: =SUM(F4:F6) -> 5601500
A8: PHILANTHROPY
A9: CSP Startup Grant | B9: 150000 | C9: 100000 | D9: 50000 | E9: 0 | F9: 0
A10: Annual Fundraising | B10: 25000 | C10: 35000 | D10: 45000 | E10: 55000 | F10: 65000
A11: Total PHILANTHROPY | B11: =SUM(B9:B10) -> 0 | C11: =SUM(C9:C10) -> 0 | D11: =SUM(D9:D10) -> 0 | E11: =SUM(E9:E10) -> 0 | F11: =SUM(F9:F10) -> 0
A12: OTHER REVENUE
A13: Before/After Care | B13: =400*Assumptions!B22 -> 48000 | C13: =412*Assumptions!B23 -> 82400 | D13: =424*Assumptions!B24 -> 127200 | E13: =437*Assumptions!B25 -> 174800 | F13: =450*Assumptions!B26 -> 225000
A14: Total OTHER REVENUE | B14: =SUM(B13:B13) -> 48000 | C14: =SUM(C13:C13) -> 82400 | D14: =SUM(D13:D13) -> 127200 | E14: =SUM(E13:E13) -> 174800 | F14: =SUM(F13:F13) -> 225000
A16: TOTAL NET REVENUE | B16: =B7+B11+B14 -> 1465000 | C16: =C7+C11+C14 -> 2328800 | D16: =D7+D11+D14 -> 3452300 | E16: =E7+E11+E14 -> 4623000 | F16: =F7+F11+F14 -> 5891500

Sheet Staffing & Personnel
A1: SchoolStack Budget - Staffing & Personnel
A3: Role | B3: Function | C3: Type | D3: FTE | E3: Annual Rate | F3: Benefits % | G3: Payroll Tax % | H3: Total Annual Cost
A4: Head of School | B4: School Leadership | C4: Full-Time | D4: 1 | E4: 105000 | F4: 0.26 | G4: 0.0765 | H4: 140332.5
A5: Assistant Principal | B5: School Leadership | C5: Full-Time | D5: 1 | E5: 82000 | F5: 0.26 | G5: 0.0765 | H5: 109593
A6: Lead Teachers | B6: Instructional | C6: Full-Time | D6: 5 | E6: 50000 | F6: 0.26 | G6: 0.0765 | H6: 334125
A7: SPED Teacher | B7: Instructional | C7: Full-Time | D7: 1 | E7: 53000 | F7: 0.26 | G7: 0.0765 | H7: 70834.5
A8: Instructional Aides | B8: Instructional | C8: Full-Time | D8: 3 | E8: 28000 | F8: 0.18 | G8: 0.0765 | H8: 105546
A9: Business Manager | B9: Operations | C9: Full-Time | D9: 1 | E9: 62000 | F9: 0.26 | G9: 0.0765 | H9: 82863
A10: Front Office | B10: Administrative | C10: Full-Time | D10: 2 | E10: 36000 | F10: 0.22 | G10: 0.0765 | H10: 93348
A12: PERSONNEL COST SUMMARY
A13: Total Headcount | B13: 7
A14: Total FTE | B14: 14
A15: Salaries & Wages | B15: 708000
A16: Benefits | B16: 174480
A17: Payroll Taxes | B17: 54162
A18: Contracted Personnel | B18: 0
A19: Total Annual Personnel Cost | B19: 936642
A21: PERSONNEL COST PROJECTION
B22: Year 1 | C22: Year 2 | D22: Year 3 | E22: Year 4 | F22: Year 5
A23: Base Personnel Cost | B23: 936642 | C23: 936642 | D23: 936642 | E23: 936642 | F23: 936642
A24: Salary Escalation Factor | B24: =(1+Assumptions!B29)^0 -> 1 | C24: =(1+Assumptions!B29)^1 -> 1 | D24: =(1+Assumptions!B29)^2 -> 1 | E24: =(1+Assumptions!B29)^3 -> 1 | F24: =(1+Assumptions!B29)^4 -> 1
A25: Proration Factor | B25: =Assumptions!B31 -> 0.83333333 | C25: 1 | D25: 1 | E25: 1 | F25: 1
A26: Total Personnel Cost | B26: =B23*B24*B25 -> 780535 | C26: =C23*C24*C25 -> 936642 | D26: =D23*D24*D25 -> 936642 | E26: =E23*E24*E25 -> 936642 | F26: =F23*F24*F25 -> 936642

Sheet Operating Expenses
B1: Year 1 | C1: Year 2 | D1: Year 3 | E1: Year 4 | F1: Year 5
A2: Students | B2: =Assumptions!B22 -> 120 | C2: =Assumptions!B23 -> 200 | D2: =Assumptions!B24 -> 300 | E2: =Assumptions!B25 -> 400 | F2: =Assumptions!B26 -> 500
A3: INSTRUCTIONAL / PROGRAM
A4: Curriculum | B4: =650*Assumptions!B22 -> 78000 | C4: =670*Assumptions!B23 -> 134000 | D4: =690*Assumptions!B24 -> 207000 | E4: =710*Assumptions!B25 -> 284000 | F4: =732*Assumptions!B26 -> 366000
A5: Total INSTRUCTIONAL | B5: =SUM(B4:B4) -> 78000 | C5: =SUM(C4:C4) -> 134000 | D5: =SUM(D4:D4) -> 207000 | E5: =SUM(E4:E4) -> 284000 | F5: =SUM(F4:F4) -> 366000
A6: TECHNOLOGY
A7: Devices & Software | B7: =450*Assumptions!B22 -> 54000 | C7: =464*Assumptions!B23 -> 92800 | D7: =478*Assumptions!B24 -> 143400 | E7: =492*Assumptions!B25 -> 196800 | F7: =507*Assumptions!B26 -> 253500
A8: Total TECHNOLOGY | B8: =SUM(B7:B7) -> 54000 | C8: =SUM(C7:C7) -> 92800 | D8: =SUM(D7:D7) -> 143400 | E8: =SUM(E7:E7) -> 196800 | F8: =SUM(F7:F7) -> 253500
A9: OCCUPANCY / FACILITY
A10: Facility Lease | B10: =22000*12 -> 264000 | C10: =22660*12 -> 271920 | D10: =23340*12 -> 280080 | E10: =24040*12 -> 288480 | F10: =24761*12 -> 297132
A11: Utilities | B11: =3000*12 -> 36000 | C11: =3090*12 -> 37080 | D11: =3183*12 -> 38196 | E11: =3278*12 -> 39336 | F11: =3377*12 -> 40524
A12: Property Insurance | B12: 22000 | C12: 22660 | D12: 23340 | E12: 24040 | F12: 24761
A13: Total OCCUPANCY | B13: =SUM(B10:B12) -> 322000 | C13: =SUM(C10:C12) -> 331660 | D13: =SUM(D10:D12) -> 341616 | E13: =SUM(E10:E12) -> 351856 | F13: =SUM(F10:F12) -> 362417
A14: ADMINISTRATIVE / GENERAL
A15: Marketing | B15: 30000 | C15: 30900 | D15: 31827 | E15: 32782 | F15: 33765
A16: Professional Development | B16: 12000 | C16: 12360 | D16: 12731 | E16: 13113 | F16: 13506
A17: Legal & Audit | B17: 18000 | C17: 18540 | D17: 19096 | E17: 19669 | F17: 20259
A18: Food Service | B18: =750*Assumptions!B22 -> 90000 | C18: =773*Assumptions!B23 -> 154600 | D18: =796*Assumptions!B24 -> 238800 | E18: =820*Assumptions!B25 -> 328000 | F18: =845*Assumptions!B26 -> 422500
A19: Total ADMINISTRATIVE | B19: =SUM(B15:B18) -> 150000 | C19: =SUM(C15:C18) -> 216400 | D19: =SUM(D15:D18) -> 302454 | E19: =SUM(E15:E18) -> 393564 | F19: =SUM(F15:F18) -> 490030
A21: TOTAL OPERATING EXPENSES | B21: =B5+B8+B13+B19 -> 604000 | C21: =C5+C8+C13+C19 -> 774860 | D21: =D5+D8+D13+D19 -> 994470 | E21: =E5+E8+E13+E19 -> 1226220 | F21: =F5+F8+F13+F19 -> 1471947

Sheet Capital & Debt
B1: Year 1 | C1: Year 2 | D1: Year 3 | E1: Year 4 | F1: Year 5
A2: CAPITAL EXPENDITURES & DEBT SERVICE
A3: Startup Loan | B3: 46628.611 | C3: 46628.611 | D3: 46628.611 | E3: 46628.611 | F3: 46628.611
A4: FF&E | B4: 60000 | C4: 20000 | D4: 25000 | E4: 10000 | F4: 10000
A5: TOTAL CAPITAL & DEBT | B5: =SUM(B3:B4) -> 106629 | C5: =SUM(C3:C4) -> 66629 | D5: =SUM(D3:D4) -> 71629 | E5: =SUM(E3:E4) -> 56629 | F5: =SUM(F3:F4) -> 56629

Sheet Financial Model
A1: 5-Year Financial Model | B1: Year 1 | C1: Year 2 | D1: Year 3 | E1: Year 4 | F1: Year 5
A2: Total Revenue | B2: ='Revenue Schedule'!B16 -> 1465000 | C2: ='Revenue Schedule'!C16 -> 2328800 | D2: ='Revenue Schedule'!D16 -> 3452300 | E2: ='Revenue Schedule'!E16 -> 4623000 | F2: ='Revenue Schedule'!F16 -> 5891500
A3: Personnel Costs | B3: ='Staffing & Personnel'!B26 -> 780535 | C3: ='Staffing & Personnel'!C26 -> 936642 | D3: ='Staffing & Personnel'!D26 -> 936642 | E3: ='Staffing & Personnel'!E26 -> 936642 | F3: ='Staffing & Personnel'!F26 -> 936642
A4: Operating Expenses | B4: ='Operating Expenses'!B21 -> 604000 | C4: ='Operating Expenses'!C21 -> 774860 | D4: ='Operating Expenses'!D21 -> 994470 | E4: ='Operating Expenses'!E21 -> 1226220 | F4: ='Operating Expenses'!F21 -> 1471947
A5: Capital & Debt | B5: ='Capital & Debt'!B5 -> 106629 | C5: ='Capital & Debt'!C5 -> 66629 | D5: ='Capital & Debt'!D5 -> 71629 | E5: ='Capital & Debt'!E5 -> 56629 | F5: ='Capital & Debt'!F5 -> 56629
A6: Total Expenses | B6: =B3+B4+B5 -> 1491164 | C6: =C3+C4+C5 -> 1778131 | D6: =D3+D4+D5 -> 2002741 | E6: =E3+E4+E5 -> 2219491 | F6: =F3+F4+F5 -> 2465218
A7: Net Income | B7: =B2-B6 -> -26164 | C7: =C2-C6 -> 550669 | D7: =D2-D6 -> 1449559 | E7: =E2-E6 -> 2403509 | F7: =F2-F6 -> 3426282
A8: Cumulative Net Income | B8: =B7 -> -26164 | C8: =B8+C7 -> 524505 | D8: =C8+D7 -> 1974064 | E8: =D8+E7 -> 4377573 | F8: =E8+F7 -> 7803855
A9: Operating Reserve (Months) | B9: =IF(B6=0,0,IF(B8>0,B8/(B6/12),0)) -> 0 | C9: =IF(C6=0,0,IF(C8>0,C8/(C6/12),0)) -> 3.5397055 | D9: =IF(D6=0,0,IF(D8>0,D8/(D6/12),0)) -> 11.828173 | E9: =IF(E6=0,0,IF(E8>0,E8/(E6/12),0)) -> 23.667983 | F9: =IF(F6=0,0,IF(F8>0,F8/(F6/12),0)) -> 37.98701

Sheet Summary
A1: Financial Model Summary
A2: Prepared by SchoolStack Budget
A4: SCHOOL INFORMATION
A5: School Name | B5: Heritage Academy Charter
A6: School Type | B6: Charter School
A7: Entity Type | B7: 501(c)(3) Nonprofit
A8: EIN | B8: 86-4441234
A9: School Stage | B9: New School
A10: State | B10: AZ
A11: Fiscal Year Start | B11: July
A12: Max Student Capacity | B12: 600
A14: ENROLLMENT TREND
B15: Year 1 | C15: Year 2 | D15: Year 3 | E15: Year 4 | F15: Year 5
A16: Students | B16: ='Revenue Schedule'!B2 -> 120 | C16: ='Revenue Schedule'!C2 -> 200 | D16: ='Revenue Schedule'!D2 -> 300 | E16: ='Revenue Schedule'!E2 -> 400 | F16: ='Revenue Schedule'!F2 -> 500
A17: Enrollment Growth % | B17: - | C17: =IF(B16=0,0,(C16-B16)/B16) -> 0.66666667 | D17: =IF(C16=0,0,(D16-C16)/C16) -> 0.5 | E17: =IF(D16=0,0,(E16-D16)/D16) -> 0.33333333 | F17: =IF(E16=0,0,(F16-E16)/E16) -> 0.25
B19: Year 1 | C19: Year 2 | D19: Year 3 | E19: Year 4 | F19: Year 5
A20: Total Revenue | B20: ='Financial Model'!B2 -> 1465000 | C20: ='Financial Model'!C2 -> 2328800 | D20: ='Financial Model'!D2 -> 3452300 | E20: ='Financial Model'!E2 -> 4623000 | F20: ='Financial Model'!F2 -> 5891500
A21: Personnel Costs | B21: ='Financial Model'!B3 -> 780535 | C21: ='Financial Model'!C3 -> 936642 | D21: ='Financial Model'!D3 -> 936642 | E21: ='Financial Model'!E3 -> 936642 | F21: ='Financial Model'!F3 -> 936642
A22: Operating Expenses | B22: ='Financial Model'!B4 -> 604000 | C22: ='Financial Model'!C4 -> 774860 | D22: ='Financial Model'!D4 -> 994470 | E22: ='Financial Model'!E4 -> 1226220 | F22: ='Financial Model'!F4 -> 1471947
A23: Total Expenses | B23: ='Financial Model'!B6 -> 1491164 | C23: ='Financial Model'!C6 -> 1778131 | D23: ='Financial Model'!D6 -> 2002741 | E23: ='Financial Model'!E6 -> 2219491 | F23: ='Financial Model'!F6 -> 2465218
A24: Net Income | B24: ='Financial Model'!B7 -> -26164 | C24: ='Financial Model'!C7 -> 550669 | D24: ='Financial Model'!D7 -> 1449559 | E24: ='Financial Model'!E7 -> 2403509 | F24: ='Financial Model'!F7 -> 3426282
A25: Cumulative Net Income | B25: ='Financial Model'!B8 -> -26164 | C25: ='Financial Model'!C8 -> 524505 | D25: ='Financial Model'!D8 -> 1974064 | E25: ='Financial Model'!E8 -> 4377573 | F25: ='Financial Model'!F8 -> 7803855
A26: Operating Reserve (Months) | B26: ='Financial Model'!B9 -> 0 | C26: ='Financial Model'!C9 -> 3.5397055 | D26: ='Financial Model'!D9 -> 11.828173 | E26: ='Financial Model'!E9 -> 23.667983 | F26: ='Financial Model'!F9 -> 37.98701
A28: KEY RATIOS
A29: Revenue per Student | B29: =IF('Revenue Schedule'!B2=0,0,B20/'Revenue Schedule'!B2) -> 12208.333 | C29: =IF('Revenue Schedule'!C2=0,0,C20/'Revenue Schedule'!C2) -> 11644 | D29: =IF('Revenue Schedule'!D2=0,0,D20/'Revenue Schedule'!D2) -> 11507.667 | E29: =IF('Revenue Schedule'!E2=0,0,E20/'Revenue Schedule'!E2) -> 11557.5 | F29: =IF('Revenue Schedule'!F2=0,0,F20/'Revenue Schedule'!F2) -> 11783
A30: Personnel Cost as % of Revenue | B30: =IF(B20=0,0,'Financial Model'!B3/B20) -> 0.5327884 | C30: =IF(C20=0,0,'Financial Model'!C3/C20) -> 0.40219942 | D30: =IF(D20=0,0,'Financial Model'!D3/D20) -> 0.27130956 | E30: =IF(E20=0,0,'Financial Model'!E3/E20) -> 0.2026048 | F30: =IF(F20=0,0,'Financial Model'!F3/F20) -> 0.15898192
A31: Operating Cost as % of Revenue | B31: =IF(B20=0,0,'Financial Model'!B4/B20) -> 0.41228669 | C31: =IF(C20=0,0,'Financial Model'!C4/C20) -> 0.3327293 | D31: =IF(D20=0,0,'Financial Model'!D4/D20) -> 0.28806013 | E31: =IF(E20=0,0,'Financial Model'!E4/E20) -> 0.26524335 | F31: =IF(F20=0,0,'Financial Model'!F4/F20) -> 0.24984248
A32: Net Margin % | B32: =IF(B20=0,0,B24/B20) -> -0.017859386 | C32: =IF(C20=0,0,C24/C20) -> 0.23646041 | D32: =IF(D20=0,0,D24/D20) -> 0.41988211 | E32: =IF(E20=0,0,E24/E20) -> 0.51990244 | F32: =IF(F20=0,0,F24/F20) -> 0.58156361
A34: REVENUE MIX TREND
A35: Tuition & Fees % | B35: 0.032764505 | C35: 0.03538303 | D35: 0.036845002 | E35: 0.037810945 | F35: 0.038190614
A36: Public Funding % | B36: 0.84778157 | C36: 0.9066472 | D36: 0.93563711 | E36: 0.95029202 | F36: 0.95077654
A37: Philanthropy % | B37: 0.11945392 | C37: 0.05796977 | D37: 0.027517887 | E37: 0.011897037 | F37: 0.011032844
