Workbook

Sheet Assumptions
A1: SchoolStack - Assumptions & Drivers
A2: Edit the highlighted cells below to update the entire model
A3: SCHOOL INFORMATION
A4: School Name | B4: Civic Scholars Charter
A5: State | B5: OH
A6: School Type | B6: Charter School
A7: Entity Type | B7: 501(c)(3) Nonprofit
A8: School Stage | B8: New School
A9: Planned Opening Year
A10: Max Student Capacity | B10: 400
A11: Fiscal Year Start | B11: July
A12: EIN | B12: 31-5551234
A13: Year 1 Operating Months | B13: 10
A15: ENROLLMENT BY YEAR
B16: Year 1 | C16: Year 2 | D16: Year 3 | E16: Year 4 | F16: Year 5
A17: Students | B17: 120 | C17: 200 | D17: 300 | E17: 375 | F17: 400
A19: GROWTH & ESCALATION RATES
A20: Salary Escalation | B20: 0
A21: Cost Inflation | B21: 0
A22: Year 1 Proration Factor | B22: 0.83333333
A23: Projection Period | B23: 5 Years

Sheet Enrollment & Rev Drivers
B1: 2026-27 | C1: 2027-28 | D1: 2028-29 | E1: 2029-30 | F1: 2030-31
A2: Students | B2: 120 | C2: 200 | D2: 300 | E2: 375 | F2: 400
A3: Enrollment Growth % | B3: - | C3: =IF(B2=0,"-",(C2-B2)/B2) -> 0.67 | D3: =IF(C2=0,"-",(D2-C2)/C2) -> 0.5 | E3: =IF(D2=0,"-",(E2-D2)/D2) -> 0.25 | F3: =IF(E2=0,"-",(F2-E2)/E2) -> 0.07
A4: Capacity Utilization % | B4: 0.3 | C4: 0.5 | D4: 0.75 | E4: 0.9375 | F4: 1
A6: REVENUE PER STUDENT
A7: State Per-Pupil Funding (per student) | B7: 9500 | C7: 9690 | D7: 9884 | E7: 10081 | F7: 10283
A8: Federal Title I (per student) | B8: 800 | C8: 816 | D8: 832 | E8: 849 | F8: 866
A9: Special Education Funding (per student) | B9: 1200 | C9: 1224 | D9: 1248 | E9: 1273 | F9: 1299
A10: Food Service Revenue (per student) | B10: 300 | C10: 309 | D10: 318 | E10: 328 | F10: 338
A12: REVENUE MIX SUMMARY
A13: Public Funding | B13: 1380000 | C13: 2346000 | D13: 3589200 | E13: 4576125 | F13: 4979200
A14: Philanthropy | B14: 130000 | C14: 115000 | D14: 100000 | E14: 60000 | F14: 70000
A15: Other Revenue | B15: 36000 | C15: 61800 | D15: 95400 | E15: 123000 | F15: 135200

Sheet Tuition & Funding Detail
B1: 2026-27 | C1: 2027-28 | D1: 2028-29 | E1: 2029-30 | F1: 2030-31
A2: Students | B2: =Assumptions!$B$17 -> 120 | C2: =Assumptions!$C$17 -> 200 | D2: =Assumptions!$D$17 -> 300 | E2: =Assumptions!$E$17 -> 375 | F2: =Assumptions!$F$17 -> 400
A3: PUBLIC FUNDING
A4: State Per-Pupil Funding | B4: =ROUND(Assumptions!$B$17*9500,0) -> 1140000 | C4: =ROUND(Assumptions!$C$17*9690,0) -> 1938000 | D4: =ROUND(Assumptions!$D$17*9884,0) -> 2965200 | E4: =ROUND(Assumptions!$E$17*10081,0) -> 3780375 | F4: =ROUND(Assumptions!$F$17*10283,0) -> 4113200
A5: Federal Title I | B5: =ROUND(Assumptions!$B$17*800,0) -> 96000 | C5: =ROUND(Assumptions!$C$17*816,0) -> 163200 | D5: =ROUND(Assumptions!$D$17*832,0) -> 249600 | E5: =ROUND(Assumptions!$E$17*849,0) -> 318375 | F5: =ROUND(Assumptions!$F$17*866,0) -> 346400
A6: Special Education Funding | B6: =ROUND(Assumptions!$B$17*1200,0) -> 144000 | C6: =ROUND(Assumptions!$C$17*1224,0) -> 244800 | D6: =ROUND(Assumptions!$D$17*1248,0) -> 374400 | E6: =ROUND(Assumptions!$E$17*1273,0) -> 477375 | F6: =ROUND(Assumptions!$F$17*1299,0) -> 519600
A7: Total Public Funding | B7: =SUM(B4:B6) -> 1380000 | C7: =SUM(C4:C6) -> 2346000 | D7: =SUM(D4:D6) -> 3589200 | E7: =SUM(E4:E6) -> 4576125 | F7: =SUM(F4:F6) -> 4979200
A8: PHILANTHROPY
A9: CSP Startup Grant | B9: 100000 | C9: 75000 | D9: 50000 | E9: 0 | F9: 0
A10: Annual Fundraising | B10: 30000 | C10: 40000 | D10: 50000 | E10: 60000 | F10: 70000
A11: Total Philanthropy | B11: =SUM(B9:B10) -> 130000 | C11: =SUM(C9:C10) -> 115000 | D11: =SUM(D9:D10) -> 100000 | E11: =SUM(E9:E10) -> 60000 | F11: =SUM(F9:F10) -> 70000
A12: OTHER REVENUE
A13: Food Service Revenue | B13: =ROUND(Assumptions!$B$17*300,0) -> 36000 | C13: =ROUND(Assumptions!$C$17*309,0) -> 61800 | D13: =ROUND(Assumptions!$D$17*318,0) -> 95400 | E13: =ROUND(Assumptions!$E$17*328,0) -> 123000 | F13: =ROUND(Assumptions!$F$17*338,0) -> 135200
A14: Total Other Revenue | B14: =SUM(B13:B13) -> 36000 | C14: =SUM(C13:C13) -> 61800 | D14: =SUM(D13:D13) -> 95400 | E14: =SUM(E13:E13) -> 123000 | F14: =SUM(F13:F13) -> 135200
A16: TOTAL NET REVENUE | B16: =B7+B11+B14 -> 1546000 | C16: =C7+C11+C14 -> 2522800 | D16: =D7+D11+D14 -> 3784600 | E16: =E7+E11+E14 -> 4759125 | F16: =F7+F11+F14 -> 5184400

Sheet Staffing Plan
A1: SchoolStack - Staffing Plan
A3: Role | B3: Function | C3: Type | D3: FTE | E3: Annual Rate | F3: Benefits % | G3: Payroll Tax % | H3: Total Cost
A4: Executive Director | B4: School Leadership | C4: FT | D4: 1 | E4: 110000 | F4: 0.28 | G4: 0.0765 | H4: 149215
A5: Principal | B5: School Leadership | C5: FT | D5: 1 | E5: 90000 | F5: 0.28 | G5: 0.0765 | H5: 122085
A6: Dean of Students | B6: School Leadership | C6: FT | D6: 1 | E6: 72000 | F6: 0.28 | G6: 0.0765 | H6: 97668
A7: Core Teachers | B7: Instructional | C7: FT | D7: 6 | E7: 52000 | F7: 0.28 | G7: 0.0765 | H7: 423228
A8: Special Education Teacher | B8: Instructional | C8: FT | D8: 1 | E8: 55000 | F8: 0.28 | G8: 0.0765 | H8: 74608
A9: Instructional Aides | B9: Instructional | C9: FT | D9: 3 | E9: 30000 | F9: 0.2 | G9: 0.0765 | H9: 114885
A10: School Counselor | B10: Student Support | C10: FT | D10: 1 | E10: 55000 | F10: 0.28 | G10: 0.0765 | H10: 74608
A11: Operations Manager | B11: Operations | C11: FT | D11: 1 | E11: 55000 | F11: 0.28 | G11: 0.0765 | H11: 74608
A12: Office Staff | B12: Administrative | C12: FT | D12: 2 | E12: 38000 | F12: 0.25 | G12: 0.0765 | H12: 100814
A14: PERSONNEL COST SUMMARY
A15: Total Headcount | B15: 9
A16: Total FTE | B16: 17
A17: Salaries & Wages | B17: 915000
A18: Benefits | B18: 246720
A19: Payroll Taxes | B19: 69998
A20: Contracted Personnel | B20: 0
A21: Total Base Personnel Cost | B21: 1231718
A23: MULTI-YEAR PERSONNEL PROJECTION
B24: 2026-27 | C24: 2027-28 | D24: 2028-29 | E24: 2029-30 | F24: 2030-31
A25: Base Cost | B25: 1231718 | C25: 1231718 | D25: 1231718 | E25: 1231718 | F25: 1231718
A26: Escalation Factor | B26: =(1+Assumptions!$B$20)^0 -> 1 | C26: =(1+Assumptions!$B$20)^1 -> 1 | D26: =(1+Assumptions!$B$20)^2 -> 1 | E26: =(1+Assumptions!$B$20)^3 -> 1 | F26: =(1+Assumptions!$B$20)^4 -> 1
A27: Proration | B27: =Assumptions!$B$22 -> 0.83 | C27: 1 | D27: 1 | E27: 1 | F27: 1
A28: Total Personnel | B28: =B25*B26*B27 -> 1026431 | C28: =C25*C26*C27 -> 1231718 | D28: =D25*D26*D27 -> 1231718 | E28: =E25*E26*E27 -> 1231718 | F28: =F25*F26*F27 -> 1231718

Sheet Operating Expenses
B1: 2026-27 | C1: 2027-28 | D1: 2028-29 | E1: 2029-30 | F1: 2030-31
A2: INSTRUCTIONAL / PROGRAM
A3: Curriculum & Textbooks | B3: =ROUND(Assumptions!$B$17*700,0) -> 84000 | C3: =ROUND(Assumptions!$C$17*721,0) -> 144200 | D3: =ROUND(Assumptions!$D$17*743,0) -> 222900 | E3: =ROUND(Assumptions!$E$17*765,0) -> 286875 | F3: =ROUND(Assumptions!$F$17*788,0) -> 315200
A4: Total Instructional / Program | B4: =SUM(B3:B3) -> 84000 | C4: =SUM(C3:C3) -> 144200 | D4: =SUM(D3:D3) -> 222900 | E4: =SUM(E3:E3) -> 286875 | F4: =SUM(F3:F3) -> 315200
A5: TECHNOLOGY
A6: Technology & Devices | B6: =ROUND(Assumptions!$B$17*500,0) -> 60000 | C6: =ROUND(Assumptions!$C$17*515,0) -> 103000 | D6: =ROUND(Assumptions!$D$17*530,0) -> 159000 | E6: =ROUND(Assumptions!$E$17*546,0) -> 204750 | F6: =ROUND(Assumptions!$F$17*562,0) -> 224800
A7: Total Technology | B7: =SUM(B6:B6) -> 60000 | C7: =SUM(C6:C6) -> 103000 | D7: =SUM(D6:D6) -> 159000 | E7: =SUM(E6:E6) -> 204750 | F7: =SUM(F6:F6) -> 224800
A8: ADMINISTRATIVE / GENERAL
A9: Marketing & Recruitment | B9: 25000 | C9: 25750 | D9: 26523 | E9: 27318 | F9: 28138
A10: Professional Development | B10: 15000 | C10: 15450 | D10: 15914 | E10: 16391 | F10: 16883
A11: Legal & Compliance | B11: 20000 | C11: 20600 | D11: 21218 | E11: 21855 | F11: 22510
A12: Food Service | B12: =ROUND(Assumptions!$B$17*800,0) -> 96000 | C12: =ROUND(Assumptions!$C$17*824,0) -> 164800 | D12: =ROUND(Assumptions!$D$17*849,0) -> 254700 | E12: =ROUND(Assumptions!$E$17*874,0) -> 327750 | F12: =ROUND(Assumptions!$F$17*900,0) -> 360000
A13: Transportation | B13: =ROUND(Assumptions!$B$17*600,0) -> 72000 | C13: =ROUND(Assumptions!$C$17*618,0) -> 123600 | D13: =ROUND(Assumptions!$D$17*637,0) -> 191100 | E13: =ROUND(Assumptions!$E$17*656,0) -> 246000 | F13: =ROUND(Assumptions!$F$17*675,0) -> 270000
A14: Total Administrative / General | B14: =SUM(B9:B13) -> 228000 | C14: =SUM(C9:C13) -> 350200 | D14: =SUM(D9:D13) -> 509455 | E14: =SUM(E9:E13) -> 639314 | F14: =SUM(F9:F13) -> 697531
A16: TOTAL OPERATING EXPENSES | B16: =B4+B7+B14 -> 372000 | C16: =C4+C7+C14 -> 597400 | D16: =D4+D7+D14 -> 891355 | E16: =E4+E7+E14 -> 1130939 | F16: =F4+F7+F14 -> 1237531

Sheet Facilities & Occupancy
B1: 2026-27 | C1: 2027-28 | D1: 2028-29 | E1: 2029-30 | F1: 2030-31
A2: OCCUPANCY / FACILITY COSTS
A3: Facility Lease | B3: 216000 | C3: 222480 | D3: 229154 | E3: 236029 | F3: 243110
A4: Utilities | B4: 30000 | C4: 30900 | D4: 31824 | E4: 32784 | F4: 33768
A5: Insurance | B5: 18000 | C5: 18540 | D5: 19096 | E5: 19669 | F5: 20259
A6: Janitorial | B6: 18000 | C6: 18540 | D6: 19092 | E6: 19668 | F6: 20256
A7: Total Facility Costs | B7: =SUM(B3:B6) -> 282000 | C7: =SUM(C3:C6) -> 290460 | D7: =SUM(D3:D6) -> 299166 | E7: =SUM(E3:E6) -> 308150 | F7: =SUM(F3:F6) -> 317393
A9: Cost per Student | B9: 2350 | C9: 1452 | D9: 997 | E9: 822 | F9: 793
A10: % of Revenue | B10: 0.21888751 | C10: 0.11513398 | D10: 0.079048354 | E10: 0.064749304 | F10: 0.061220759

Sheet Capital Stack & Startup Uses
A1: SchoolStack - Capital Stack (2026-27)
A3: SOURCES OF CAPITAL
A4: Founder Equity / Starting Cash | B4: 0
A5: Loan: Facility Improvement Loan | B5: 500000
A6: TOTAL CAPITAL SOURCES | B6: =SUM(B4:B5) -> 500000
A8: STARTUP / PRE-OPENING USES
A9: Deposits & Prepaid Occupancy (2 mo) | B9: 47000
A10: Equipment / FF&E / Technology | B10: 30000
A11: Curriculum & Program Launch Costs | B11: 84000
A12: FF&E Purchase | B12: 75000
A13: Technology Infrastructure | B13: 40000
A14: Working Capital Reserve (2 mo) | B14: 261905
A15: Contingency (5%) | B15: 26895
A16: TOTAL STARTUP USES | B16: =SUM(B9:B15) -> 564800
A18: CAPITAL SURPLUS / (GAP) | B18: =B6-B16 -> -64800
A19: ⚠ Funding gap - additional capital needed

Sheet Debt Schedule
A1: SchoolStack - Debt Schedule
A3: Loan / Facility | B3: Principal | C3: Rate | D3: Term (yrs) | E3: Annual Payment | F3: Monthly Payment | G3: Total Interest
A4: Facility Improvement Loan | B4: 500000 | C4: 0.0575 | D4: 15 | E4: 49825 | F4: 4152 | G4: 247369
A6: TOTAL DEBT SERVICE
A7: Annual Debt Service | B7: 49825
A8: Monthly Debt Service | B8: 4152
A10: AMORTIZATION SCHEDULE (ANNUAL)
A11: Year | B11: Facility Improvement Loan Balance
A12: Year 1 | B12: 478925
A13: Year 2 | B13: 456639
A14: Year 3 | B14: 433071
A15: Year 4 | B15: 408148
A16: Year 5 | B16: 381792

Sheet Cash Flow Monthly Y1
B1: July | C1: August | D1: September | E1: October | F1: November | G1: December | H1: January | I1: February | J1: March | K1: April | L1: May | M1: June | N1: 2026-27 Total
A2: Revenue | B2: 154600 | C2: 154600 | D2: 154600 | E2: 154600 | F2: 154600 | G2: 154600 | H2: 154600 | I2: 154600 | J2: 154600 | K2: -103067 | L2: 0 | M2: 0 | N2: =SUM(B2:M2) -> 1288333
A3: Personnel | B3: 102643 | C3: 102643 | D3: 102643 | E3: 102643 | F3: 102643 | G3: 102643 | H3: 102643 | I3: 102643 | J3: 102643 | K3: 102644 | L3: 0 | M3: 0 | N3: =SUM(B3:M3) -> 1026431
A4: Operating Expenses | B4: 54500 | C4: 54500 | D4: 54500 | E4: 54500 | F4: 54500 | G4: 54500 | H4: 54500 | I4: 54500 | J4: 54500 | K4: 54500 | L4: 0 | M4: 0 | N4: =SUM(B4:M4) -> 545000
A5: Debt Service | B5: 13735 | C5: 13735 | D5: 13735 | E5: 13735 | F5: 13735 | G5: 13735 | H5: 13735 | I5: 13735 | J5: 13735 | K5: 13735 | L5: 13735 | M5: 13740 | N5: =SUM(B5:M5) -> 164825
A6: Total Expenses | B6: =SUM(B3:B5) -> 170878 | C6: =SUM(C3:C5) -> 170878 | D6: =SUM(D3:D5) -> 170878 | E6: =SUM(E3:E5) -> 170878 | F6: =SUM(F3:F5) -> 170878 | G6: =SUM(G3:G5) -> 170878 | H6: =SUM(H3:H5) -> 170878 | I6: =SUM(I3:I5) -> 170878 | ... M6: =SUM(M3:M5) -> 13740 | N6: =SUM(B6:M6) -> 1736256
A7: Net Cash Flow | B7: =B2-B6 -> -16278 | C7: =C2-C6 -> -16278 | D7: =D2-D6 -> -16278 | E7: =E2-E6 -> -16278 | F7: =F2-F6 -> -16278 | G7: =G2-G6 -> -16278 | H7: =H2-H6 -> -16278 | I7: =I2-I6 -> -16278 | ... M7: =M2-M6 -> -13740 | N7: =SUM(B7:M7) -> -447923
A8: Cumulative Cash | B8: =500000+B7 -> 483722 | C8: =B8+C7 -> 467444 | D8: =C8+D7 -> 451166 | E8: =D8+E7 -> 434888 | F8: =E8+F7 -> 418610 | G8: =F8+G7 -> 402332 | H8: =G8+H7 -> 386054 | I8: =H8+I7 -> 369776 | J8: =I8+J7 -> 353498 | ... M8: =L8+M7 -> 52077 | N8: =M8 -> 52077
A10: CASH FLOW METRICS
A11: Starting Cash | B11: 500000
A12: Ending Cash (Month 12) | B12: =M8 -> 52077
A13: Minimum Cash Month | B13: =MIN(B8:M8) -> 52077

Sheet 5-Year P&L
B1: 2026-27 | C1: 2027-28 | D1: 2028-29 | E1: 2029-30 | F1: 2030-31
A2: Total Revenue | B2: ='Tuition & Funding Detail'!B16 -> 1288333 | C2: ='Tuition & Funding Detail'!C16 -> 2522800 | D2: ='Tuition & Funding Detail'!D16 -> 3784600 | E2: ='Tuition & Funding Detail'!E16 -> 4759125 | F2: ='Tuition & Funding Detail'!F16 -> 5184400
A3: Personnel | B3: ='Staffing Plan'!B28 -> 1026431 | C3: ='Staffing Plan'!C28 -> 1231718 | D3: ='Staffing Plan'!D28 -> 1231718 | E3: ='Staffing Plan'!E28 -> 1231718 | F3: ='Staffing Plan'!F28 -> 1231718
A4: Operating Expenses | B4: ='Operating Expenses'!B16+'Facilities & Occupancy'!B7 -> 545000 | C4: ='Operating Expenses'!C16+'Facilities & Occupancy'!C7 -> 887860 | D4: ='Operating Expenses'!D16+'Facilities & Occupancy'!D7 -> 1190521 | E4: ='Operating Expenses'!E16+'Facilities & Occupancy'!E7 -> 1439089 | F4: ='Operating Expenses'!F16+'Facilities & Occupancy'!F7 -> 1554924
A5: Capital & Debt Service | B5: 164825 | C5: 89825 | D5: 89825 | E5: 74825 | F5: 69825
A6: Total Expenses | B6: =SUM(B3:B5) -> 1736256 | C6: =SUM(C3:C5) -> 2209403 | D6: =SUM(D3:D5) -> 2512064 | E6: =SUM(E3:E5) -> 2745632 | F6: =SUM(F3:F5) -> 2856467
A7: Net Income | B7: =B2-B6 -> -447923 | C7: =C2-C6 -> 313398 | D7: =D2-D6 -> 1272536 | E7: =E2-E6 -> 2013494 | F7: =F2-F6 -> 2327934
A8: Net Margin % | B8: =IF(B2=0,0,B7/B2) -> -0.35 | C8: =IF(C2=0,0,C7/C2) -> 0.12 | D8: =IF(D2=0,0,D7/D2) -> 0.34 | E8: =IF(E2=0,0,E7/E2) -> 0.42 | F8: =IF(F2=0,0,F7/F2) -> 0.45
A9: Cumulative Net Income | B9: =B7 -> -447923 | C9: =B9+C7 -> -134525 | D9: =C9+D7 -> 1138011 | E9: =D9+E7 -> 3151505 | F9: =E9+F7 -> 5479439

Sheet 5-Year Balance Sheet
B1: 2026-27 | C1: 2027-28 | D1: 2028-29 | E1: 2029-30 | F1: 2030-31
A2: ASSETS
A3: Cash & Equivalents | B3: 52077 | C3: 365475 | D3: 1638011 | E3: 3651505 | F3: 5979439
A4: Other Assets | B4: 0 | C4: 0 | D4: 0 | E4: 0 | F4: 0
A5: Total Assets | B5: =SUM(B3:B4) -> 52077 | C5: =SUM(C3:C4) -> 365475 | D5: =SUM(D3:D4) -> 1638011 | E5: =SUM(E3:E4) -> 3651505 | F5: =SUM(F3:F4) -> 5979439
A7: LIABILITIES
A8: Debt Outstanding | B8: 478925 | C8: 456639 | D8: 433071 | E8: 408148 | F8: 381792
A9: Other Liabilities | B9: 0 | C9: 0 | D9: 0 | E9: 0 | F9: 0
A10: Total Liabilities | B10: =SUM(B8:B9) -> 478925 | C10: =SUM(C8:C9) -> 456639 | D10: =SUM(D8:D9) -> 433071 | E10: =SUM(E8:E9) -> 408148 | F10: =SUM(F8:F9) -> 381792
A12: EQUITY / NET ASSETS
A13: Beginning Net Position | B13: 0 | C13: -426848 | D13: -91164 | E13: 1204940 | F13: 3243357
A14: Change in Net Position | B14: -426848 | C14: 335684 | D14: 1296104 | E14: 2038417 | F14: 2354290
A15: Total Equity / Net Assets | B15: =B5-B10 -> -426848 | C15: =C5-C10 -> -91164 | D15: =D5-D10 -> 1204940 | E15: =E5-E10 -> 3243357 | F15: =F5-F10 -> 5597647
A17: BALANCE CHECK (Assets − Liab − Equity) | B17: =B5-B10-B15 -> 0 | C17: =C5-C10-C15 -> 0 | D17: =D5-D10-D15 -> 0 | E17: =E5-E10-E15 -> 0 | F17: =F5-F10-F15 -> 0

Sheet DSCR & Covenants
B1: 2026-27 | C1: 2027-28 | D1: 2028-29 | E1: 2029-30 | F1: 2030-31
A2: DEBT SERVICE COVERAGE RATIO (DSCR)
A3: Net Operating Income (NOI) | B3: -283098 | C3: 403222 | D3: 1362361 | E3: 2088318 | F3: 2397758
A4: Annual Debt Service | B4: 49825 | C4: 49825 | D4: 49825 | E4: 49825 | F4: 49825
A5: DSCR | B5: =IF(B4=0,"N/A",B3/B4) -> -5.68 | C5: =IF(C4=0,"N/A",C3/C4) -> 8.09 | D5: =IF(D4=0,"N/A",D3/D4) -> 27.34 | E5: =IF(E4=0,"N/A",E3/E4) -> 41.91 | F5: =IF(F4=0,"N/A",F3/F4) -> 48.12
A7: LIQUIDITY METRICS
A8: Ending Cash Balance | B8: 52077 | C8: 365475 | D8: 1638011 | E8: 3651505 | F8: 5979439
A9: Monthly Operating Cost | B9: 130953 | C9: 176632 | D9: 201853 | E9: 222567 | F9: 232220
A10: Cash Reserve (Months) | B10: =IF(B9=0,0,B8/B9) -> 0.4 | C10: =IF(C9=0,0,C8/C9) -> 2.07 | D10: =IF(D9=0,0,D8/D9) -> 8.11 | E10: =IF(E9=0,0,E8/E9) -> 16.41 | F10: =IF(F9=0,0,F8/F9) -> 25.75
A11: Days Cash on Hand | B11: 12 | C11: 63 | D11: 247 | E11: 499 | F11: 783
A13: COVENANT CHECKS
A14: DSCR ≥ 1.20x | B14: =IF(B5>=1.2,"PASS","FAIL") -> FAIL | C14: =IF(C5>=1.2,"PASS","FAIL") -> PASS | D14: =IF(D5>=1.2,"PASS","FAIL") -> PASS | E14: =IF(E5>=1.2,"PASS","FAIL") -> PASS | F14: =IF(F5>=1.2,"PASS","FAIL") -> PASS
A15: Cash Reserve ≥ 2.0 Months | B15: =IF(B10>=2,"PASS","FAIL") -> FAIL | C15: =IF(C10>=2,"PASS","FAIL") -> PASS | D15: =IF(D10>=2,"PASS","FAIL") -> PASS | E15: =IF(E10>=2,"PASS","FAIL") -> PASS | F15: =IF(F10>=2,"PASS","FAIL") -> PASS
A16: Positive Net Income | B16: FAIL | C16: PASS | D16: PASS | E16: PASS | F16: PASS
A17: Enrollment ≥ 70% Capacity | B17: FAIL | C17: FAIL | D17: PASS | E17: PASS | F17: PASS

Sheet Underwriting Snapshot
A1: SchoolStack - Underwriting Snapshot
A2: Civic Scholars Charter | Charter School | OH
A4: POLICY FLAGS
A5: DSCR ≥ 1.20x (2026-27) | B5: FAIL | C5: -5.68x
A6: Min 2 Months Cash Reserve (2026-27) | B6: FAIL | C6: 0.4 months
A7: Positive Net Income (2026-27) | B7: FAIL | C7: No
A8: Break-Even Within Projection Period | B8: PASS | C8: 2027-28
A9: Enrollment ≥ 70% Capacity (2026-27) | B9: FAIL | C9: 30%
A10: Positive Ending Cash (Final Year) | B10: PASS | C10: Yes
A12: UNDERWRITING ASSESSMENT
A13: Flags Passed | B13: 2 / 6
A14: Overall Assessment | B14: Not Ready
A16: KEY METRICS SUMMARY
A17: 2026-27 Revenue | B17: 1288333
A18: 2026-27 Total Expenses | B18: 1736256
A19: 2026-27 Net Income | B19: -447923
A20: 2026-27 Net Margin | B20: -0.34767642
A21: Starting Cash | B21: 500000
A22: 2026-27 Ending Cash | B22: 52077
A23: Total Debt | B23: 500000
A24: 2026-27 DSCR | B24: -5.68x
A25: 2026-27 Cash Reserve (Months) | B25: 0.4
A26: Break-Even Year | B26: 2027-28
A27: Revenue per Student (2026-27) | B27: 10736
A28: Cost per Student (2026-27) | B28: 14469

Sheet Summary
A1: Civic Scholars Charter
A2: 5-Year Financial Model
A3: Charter School | OH | Est. 2026
A4: Prepared March 17, 2026
B6: 2026-27 | C6: 2027-28 | D6: 2028-29 | E6: 2029-30 | F6: 2030-31
A7: Students | B7: =Assumptions!$B$17 -> 120 | C7: =Assumptions!$C$17 -> 200 | D7: =Assumptions!$D$17 -> 300 | E7: =Assumptions!$E$17 -> 375 | F7: =Assumptions!$F$17 -> 400
A8: Total Revenue | B8: ='5-Year P&L'!B2 -> 1288333 | C8: ='5-Year P&L'!C2 -> 2522800 | D8: ='5-Year P&L'!D2 -> 3784600 | E8: ='5-Year P&L'!E2 -> 4759125 | F8: ='5-Year P&L'!F2 -> 5184400
A9: Total Expenses | B9: ='5-Year P&L'!B6 -> 1736256 | C9: ='5-Year P&L'!C6 -> 2209403 | D9: ='5-Year P&L'!D6 -> 2512064 | E9: ='5-Year P&L'!E6 -> 2745632 | F9: ='5-Year P&L'!F6 -> 2856467
A10: Net Income | B10: ='5-Year P&L'!B7 -> -447923 | C10: ='5-Year P&L'!C7 -> 313398 | D10: ='5-Year P&L'!D7 -> 1272536 | E10: ='5-Year P&L'!E7 -> 2013494 | F10: ='5-Year P&L'!F7 -> 2327934
A11: Net Margin % | B11: =IF(B8=0,0,B10/B8) -> -0.35 | C11: =IF(C8=0,0,C10/C8) -> 0.12 | D11: =IF(D8=0,0,D10/D8) -> 0.34 | E11: =IF(E8=0,0,E10/E8) -> 0.42 | F11: =IF(F8=0,0,F10/F8) -> 0.45
A12: Cumulative Net Income | B12: =B10 -> -447923 | C12: =B12+C10 -> -134525 | D12: =C12+D10 -> 1138011 | E12: =D12+E10 -> 3151505 | F12: =E12+F10 -> 5479439
A13: Cash Balance | B13: 52077 | C13: 365475 | D13: 1638011 | E13: 3651505 | F13: 5979439
A14: Revenue per Student | B14: 10736 | C14: 12614 | D14: 12615 | E14: 12691 | F14: 12961
A15: Cost per Student | B15: 14469 | C15: 11047 | D15: 8374 | E15: 7322 | F15: 7141
A16: DSCR | B16: -5.68 | C16: 8.09 | D16: 27.34 | E16: 41.91 | F16: 48.12
A18: Generated by SchoolStack Budget • budget.schoolstack.ai

Sheet Cover
B3: SchoolStack Budget
B4: Underwriting Package
B8: Prepared for
B9: Civic Scholars Charter
B10: Charter School • 501(c)(3) Nonprofit • OH
B12: Date Prepared | C12: March 17, 2026
B15: UNDERWRITING HIGHLIGHTS
B16: Year 5 Revenue | C16: 5184400
B17: Year 5 Net Income | C17: 2327934
B18: Ending Cash Balance | C18: 5479439
B19: Overall Assessment | C19: Strong
B22: TABLE OF CONTENTS
B23: Assumptions
B24: Enrollment & Rev Drivers
B25: Tuition & Funding Detail
B26: Staffing Plan
B27: Operating Expenses
B28: Facilities & Occupancy
B29: Capital Stack & Startup Uses
B30: Debt Schedule
B31: Cash Flow Monthly Y1
B32: 5-Year P&L
B33: 5-Year Balance Sheet
... B39: Generated by SchoolStack Budget • budget.schoolstack.ai
