Workbook

Sheet Assumptions
A1: SchoolStack - Assumptions & Drivers
B2: Editable assumption — change this value | E2: Calculated — driven by formula
A3: SCHOOL INFORMATION
A4: School Name | B4: Bright Horizons Microschool
A5: State | B5: AZ
A6: School Type | B6: Microschool
A7: Entity Type | B7: LLC (Single Member)
A8: School Stage | B8: New School
A9: Planned Opening Year
A10: Max Student Capacity | B10: 25
A11: Fiscal Year Start | B11: July
A12: EIN | B12: 88-1234567
A13: Year 1 Operating Months | B13: 10
A15: ENROLLMENT BY YEAR
B16: Year 1 | C16: Year 2 | D16: Year 3 | E16: Year 4 | F16: Year 5
A17: Students | B17: 12 | C17: 18 | D17: 22 | E17: 25 | F17: 25
A19: GROWTH & ESCALATION RATES
A20: Salary Escalation | B20: 0.03
A21: Cost Inflation | B21: 0.025
A22: Year 1 Proration Factor | B22: 0.83333333
A23: Projection Period | B23: 5 Years

Sheet Enrollment & Rev Drivers
B1: 2026-27 | C1: 2027-28 | D1: 2028-29 | E1: 2029-30 | F1: 2030-31
A2: Students | B2: 12 | C2: 18 | D2: 22 | E2: 25 | F2: 25
A3: Enrollment Growth % | B3: - | C3: =IF(B2=0,"-",(C2-B2)/B2) -> 0.5 | D3: =IF(C2=0,"-",(D2-C2)/C2) -> 0.22 | E3: =IF(D2=0,"-",(E2-D2)/D2) -> 0.14 | F3: =IF(E2=0,"-",(F2-E2)/E2) -> 0
A4: Capacity Utilization % | B4: 0.48 | C4: 0.72 | D4: 0.88 | E4: 1 | F4: 1
A6: REVENUE PER STUDENT
A7: Tuition (per student) | B7: 12000 | C7: 12360 | D7: 12731 | E7: 13113 | F7: 13506
A8: Registration Fee (per student) | B8: 250 | C8: 250 | D8: 250 | E8: 250 | F8: 250
A9: AZ ESA Funds (per student) | B9: 7000 | C9: 7210 | D9: 7426 | E9: 7649 | F9: 7878
A11: REVENUE MIX SUMMARY
A12: Tuition & Student Fees | B12: 147000 | C12: 226980 | D12: 285582 | E12: 334075 | F12: 343900
A13: Tuition Offsets | B13: -14400 | C13: -22248 | D13: -28008 | E13: -32782 | F13: -33765
A14: School Choice Funding | B14: 84000 | C14: 129780 | D14: 163372 | E14: 191225 | F14: 196950
A15: Philanthropy | B15: 5000 | C15: 6000 | D15: 7000 | E15: 8000 | F15: 9000

Sheet Tuition & Funding Detail
B1: 2026-27 | C1: 2027-28 | D1: 2028-29 | E1: 2029-30 | F1: 2030-31
A2: Students | B2: =Assumptions!$B$17 -> 12 | C2: =Assumptions!$C$17 -> 18 | D2: =Assumptions!$D$17 -> 22 | E2: =Assumptions!$E$17 -> 25 | F2: =Assumptions!$F$17 -> 25
A3: TUITION & STUDENT FEES
A4: Tuition | B4: =ROUND(Assumptions!$B$17*12000,0) -> 144000 | C4: =ROUND(Assumptions!$C$17*12360,0) -> 222480 | D4: =ROUND(Assumptions!$D$17*12731,0) -> 280082 | E4: =ROUND(Assumptions!$E$17*13113,0) -> 327825 | F4: =ROUND(Assumptions!$F$17*13506,0) -> 337650
A5: Registration Fee | B5: =ROUND(Assumptions!$B$17*250,0) -> 3000 | C5: =ROUND(Assumptions!$C$17*250,0) -> 4500 | D5: =ROUND(Assumptions!$D$17*250,0) -> 5500 | E5: =ROUND(Assumptions!$E$17*250,0) -> 6250 | F5: =ROUND(Assumptions!$F$17*250,0) -> 6250
A6: Total Tuition & Student Fees | B6: =SUM(B4:B5) -> 147000 | C6: =SUM(C4:C5) -> 226980 | D6: =SUM(D4:D5) -> 285582 | E6: =SUM(E4:E5) -> 334075 | F6: =SUM(F4:F5) -> 343900
A7: TUITION OFFSETS
A8: Scholarship Discount | B8: -14400 | C8: -22248 | D8: -28008 | E8: -32783 | F8: -33765
A9: Total Tuition Offsets | B9: =SUM(B8:B8) -> -14400 | C9: =SUM(C8:C8) -> -22248 | D9: =SUM(D8:D8) -> -28008 | E9: =SUM(E8:E8) -> -32783 | F9: =SUM(F8:F8) -> -33765
A10: SCHOOL CHOICE FUNDING
A11: AZ ESA Funds | B11: =ROUND(Assumptions!$B$17*7000,0) -> 84000 | C11: =ROUND(Assumptions!$C$17*7210,0) -> 129780 | D11: =ROUND(Assumptions!$D$17*7426,0) -> 163372 | E11: =ROUND(Assumptions!$E$17*7649,0) -> 191225 | F11: =ROUND(Assumptions!$F$17*7878,0) -> 196950
A12: Total School Choice Funding | B12: =SUM(B11:B11) -> 84000 | C12: =SUM(C11:C11) -> 129780 | D12: =SUM(D11:D11) -> 163372 | E12: =SUM(E11:E11) -> 191225 | F12: =SUM(F11:F11) -> 196950
A13: PHILANTHROPY
A14: Annual Fundraising | B14: 5000 | C14: 6000 | D14: 7000 | E14: 8000 | F14: 9000
A15: Total Philanthropy | B15: =SUM(B14:B14) -> 5000 | C15: =SUM(C14:C14) -> 6000 | D15: =SUM(D14:D14) -> 7000 | E15: =SUM(E14:E14) -> 8000 | F15: =SUM(F14:F14) -> 9000
A17: TOTAL NET REVENUE | B17: =B6+B9+B12+B15 -> 221600 | C17: =C6+C9+C12+C15 -> 340512 | D17: =D6+D9+D12+D15 -> 427946 | E17: =E6+E9+E12+E15 -> 500517 | F17: =F6+F9+F12+F15 -> 516085

Sheet Staffing Plan
A1: SchoolStack - Staffing Plan
A3: Role | B3: Function | C3: Type | D3: FTE | E3: Annual Rate | F3: Benefits % | G3: Payroll Tax % | H3: Total Cost
A4: Founder / Head of School | B4: School Leadership | C4: FT | D4: 1 | E4: 55000 | F4: 0.2 | G4: 0.0765 | H4: 70208
A5: Lead Teacher | B5: Instructional | C5: FT | D5: 1 | E5: 45000 | F5: 0.2 | G5: 0.0765 | H5: 57443
A6: Teaching Assistant | B6: Instructional | C6: PT | D6: 0.5 | E6: 28000 | F6: 0 | G6: 0.0765 | H6: 15071
A8: PERSONNEL COST SUMMARY
A9: Total Headcount | B9: 3
A10: Total FTE | B10: 2.5
A11: Salaries & Wages | B11: 114000
A12: Benefits | B12: 20000
A13: Payroll Taxes | B13: 8721
A14: Contracted Personnel | B14: 0
A15: Total Base Personnel Cost | B15: 142721
A17: MULTI-YEAR PERSONNEL PROJECTION
B18: 2026-27 | C18: 2027-28 | D18: 2028-29 | E18: 2029-30 | F18: 2030-31
A19: Base Cost | B19: 142721 | C19: 142721 | D19: 142721 | E19: 142721 | F19: 142721
A20: Escalation Factor | B20: =(1+Assumptions!$B$20)^0 -> 1 | C20: =(1+Assumptions!$B$20)^1 -> 1.03 | D20: =(1+Assumptions!$B$20)^2 -> 1.06 | E20: =(1+Assumptions!$B$20)^3 -> 1.09 | F20: =(1+Assumptions!$B$20)^4 -> 1.13
A21: Proration | B21: =Assumptions!$B$22 -> 0.83 | C21: 1 | D21: 1 | E21: 1 | F21: 1
A22: Total Personnel | B22: =B19*B20*B21 -> 118934 | C22: =C19*C20*C21 -> 147003 | D22: =D19*D20*D21 -> 151413 | E22: =E19*E20*E21 -> 155955 | F22: =F19*F20*F21 -> 160634

Sheet Operating Expenses
B1: 2026-27 | C1: 2027-28 | D1: 2028-29 | E1: 2029-30 | F1: 2030-31
A2: INSTRUCTIONAL / PROGRAM
A3: Curriculum & Materials | B3: =ROUND(Assumptions!$B$17*500,0) -> 6000 | C3: =ROUND(Assumptions!$C$17*500*(1+Assumptions!$B$21)^1,0) -> 9225 | D3: =ROUND(Assumptions!$D$17*500*(1+Assumptions!$B$21)^2,0) -> 11557 | E3: =ROUND(Assumptions!$E$17*500*(1+Assumptions!$B$21)^3,0) -> 13461 | F3: =ROUND(Assumptions!$F$17*500*(1+Assumptions!$B$21)^4,0) -> 13798
A4: Total Instructional / Program | B4: =SUM(B3:B3) -> 6000 | C4: =SUM(C3:C3) -> 9225 | D4: =SUM(D3:D3) -> 11557 | E4: =SUM(E3:E3) -> 13461 | F4: =SUM(F3:F3) -> 13798
A5: TECHNOLOGY
A6: Technology | B6: =ROUND(Assumptions!$B$17*300,0) -> 3600 | C6: =ROUND(Assumptions!$C$17*300*(1+Assumptions!$B$21)^1,0) -> 5535 | D6: =ROUND(Assumptions!$D$17*300*(1+Assumptions!$B$21)^2,0) -> 6934 | E6: =ROUND(Assumptions!$E$17*300*(1+Assumptions!$B$21)^3,0) -> 8077 | F6: =ROUND(Assumptions!$F$17*300*(1+Assumptions!$B$21)^4,0) -> 8279
A7: Total Technology | B7: =SUM(B6:B6) -> 3600 | C7: =SUM(C6:C6) -> 5535 | D7: =SUM(D6:D6) -> 6934 | E7: =SUM(E6:E6) -> 8077 | F7: =SUM(F6:F6) -> 8279
A8: ADMINISTRATIVE / GENERAL
A9: Marketing | B9: 3000 | C9: 3075 | D9: 3152 | E9: 3231 | F9: 3311
A10: Total Administrative / General | B10: =SUM(B9:B9) -> 3000 | C10: =SUM(C9:C9) -> 3075 | D10: =SUM(D9:D9) -> 3152 | E10: =SUM(E9:E9) -> 3231 | F10: =SUM(F9:F9) -> 3311
A12: TOTAL OPERATING EXPENSES | B12: =B4+B7+B10 -> 12600 | C12: =C4+C7+C10 -> 17835 | D12: =D4+D7+D10 -> 21643 | E12: =E4+E7+E10 -> 24769 | F12: =F4+F7+F10 -> 25388

Sheet Facilities & Occupancy
B1: 2026-27 | C1: 2027-28 | D1: 2028-29 | E1: 2029-30 | F1: 2030-31
A2: OCCUPANCY / FACILITY COSTS
A3: Rent | B3: 30000 | C3: 30900 | D3: 31827 | E3: 32782 | F3: 33765
A4: Utilities | B4: 3600 | C4: 3690 | D4: 3782 | E4: 3877 | F4: 3974
A5: Insurance | B5: 2400 | C5: 2460 | D5: 2522 | E5: 2585 | F5: 2649
A6: Total Facility Costs | B6: =SUM(B3:B5) -> 36000 | C6: =SUM(C3:C5) -> 37050 | D6: =SUM(D3:D5) -> 38131 | E6: =SUM(E3:E5) -> 39244 | F6: =SUM(F3:F5) -> 40388
A8: Cost per Student | B8: 3000 | C8: 2058 | D8: 1733 | E8: 1570 | F8: 1616
A9: % of Revenue | B9: 0.1949455 | C9: 0.10880674 | D9: 0.089101779 | E9: 0.07840508 | F9: 0.078258701

Sheet Capital Stack & Startup Uses
A1: SchoolStack - Capital Stack (2026-27)
A3: SOURCES OF CAPITAL
A4: Founder Equity / Starting Cash | B4: 0
A5: Loan: Equipment Loan | B5: 30000
A6: TOTAL CAPITAL SOURCES | B6: =SUM(B4:B5) -> 30000
A8: STARTUP / PRE-OPENING USES
A9: Deposits & Prepaid Occupancy (2 mo) | B9: 6000
A10: Equipment / FF&E / Technology | B10: 1800
A11: Curriculum & Program Launch Costs | B11: 6000
A12: Working Capital Reserve (2 mo) | B12: 26572
A13: Contingency (5%) | B13: 2019
A14: TOTAL STARTUP USES | B14: =SUM(B9:B13) -> 42391
A16: CAPITAL SURPLUS / (GAP) | B16: =B6-B14 -> -12391
A17: ⚠ Funding gap - additional capital needed

Sheet Debt Schedule
A1: SchoolStack - Debt Schedule
A3: Loan / Facility | B3: Principal | C3: Rate | D3: Term (yrs) | E3: Annual Payment | F3: Monthly Payment | G3: Total Interest
A4: Equipment Loan | B4: 30000 | C4: 0.06 | D4: 5 | E4: 6960 | F4: 580 | G4: 4799
A6: TOTAL DEBT SERVICE
A7: Annual Debt Service | B7: 6960
A8: Monthly Debt Service | B8: 580
A10: AMORTIZATION SCHEDULE (ANNUAL)
A11: Year | B11: Equipment Loan Balance
A12: Year 1 | B12: 24840
A13: Year 2 | B13: 19371
A14: Year 3 | B14: 13573
A15: Year 4 | B15: 7428
A16: Year 5 | B16: 914

Sheet Cash Flow Monthly Y1
B1: July | C1: August | D1: September | E1: October | F1: November | G1: December | H1: January | I1: February | J1: March | K1: April | L1: May | M1: June | N1: 2026-27 Total
A2: Revenue | B2: 155900 | C2: 7460 | D2: 7460 | E2: 7460 | F2: 7460 | G2: 7460 | H2: 7460 | I2: 7460 | J2: 7460 | K2: -29473 | L2: -1440 | M2: 0 | N2: =SUM(B2:M2) -> 184667
A3: Personnel | B3: 11893 | C3: 11893 | D3: 11893 | E3: 11893 | F3: 11893 | G3: 11893 | H3: 11893 | I3: 11893 | J3: 11893 | K3: 11897 | L3: 0 | M3: 0 | N3: =SUM(B3:M3) -> 118934
A4: Operating Expenses | B4: 4050 | C4: 4050 | D4: 4050 | E4: 4050 | F4: 4050 | G4: 4050 | H4: 4050 | I4: 4050 | J4: 4050 | K4: 4050 | L4: 0 | M4: 0 | N4: =SUM(B4:M4) -> 40500
A5: Debt Service | B5: 580 | C5: 580 | D5: 580 | E5: 580 | F5: 580 | G5: 580 | H5: 580 | I5: 580 | J5: 580 | K5: 580 | L5: 580 | M5: 580 | N5: =SUM(B5:M5) -> 6960
A6: Total Expenses | B6: =SUM(B3:B5) -> 16523 | C6: =SUM(C3:C5) -> 16523 | D6: =SUM(D3:D5) -> 16523 | E6: =SUM(E3:E5) -> 16523 | F6: =SUM(F3:F5) -> 16523 | G6: =SUM(G3:G5) -> 16523 | H6: =SUM(H3:H5) -> 16523 | I6: =SUM(I3:I5) -> 16523 | ... M6: =SUM(M3:M5) -> 580 | N6: =SUM(B6:M6) -> 166394
A7: Net Cash Flow | B7: =B2-B6 -> 139377 | C7: =C2-C6 -> -9063 | D7: =D2-D6 -> -9063 | E7: =E2-E6 -> -9063 | F7: =F2-F6 -> -9063 | G7: =G2-G6 -> -9063 | H7: =H2-H6 -> -9063 | I7: =I2-I6 -> -9063 | ... M7: =M2-M6 -> -580 | N7: =SUM(B7:M7) -> 18273
A8: Cumulative Cash | B8: =30000+B7 -> 169377 | C8: =B8+C7 -> 160314 | D8: =C8+D7 -> 151251 | E8: =D8+E7 -> 142188 | F8: =E8+F7 -> 133125 | G8: =F8+G7 -> 124062 | H8: =G8+H7 -> 114999 | I8: =H8+I7 -> 105936 | J8: =I8+J7 -> 96873 | ... M8: =L8+M7 -> 48273 | N8: =M8 -> 48273
A10: CASH FLOW METRICS
A11: Starting Cash | B11: 30000
A12: Ending Cash (Month 12) | B12: =M8 -> 48273
A13: Minimum Cash Month | B13: =MIN(B8:M8) -> 48273

Sheet 5-Year P&L
B1: 2026-27 | C1: 2027-28 | D1: 2028-29 | E1: 2029-30 | F1: 2030-31
A2: Total Revenue | B2: ='Tuition & Funding Detail'!B17 -> 184667 | C2: ='Tuition & Funding Detail'!C17 -> 340512 | D2: ='Tuition & Funding Detail'!D17 -> 427946 | E2: ='Tuition & Funding Detail'!E17 -> 500518 | F2: ='Tuition & Funding Detail'!F17 -> 516085
A3: Personnel | B3: ='Staffing Plan'!B22 -> 118934 | C3: ='Staffing Plan'!C22 -> 147003 | D3: ='Staffing Plan'!D22 -> 151413 | E3: ='Staffing Plan'!E22 -> 155955 | F3: ='Staffing Plan'!F22 -> 160634
A4: Operating Expenses | B4: ='Operating Expenses'!B12+'Facilities & Occupancy'!B6 -> 40500 | C4: ='Operating Expenses'!C12+'Facilities & Occupancy'!C6 -> 54885 | D4: ='Operating Expenses'!D12+'Facilities & Occupancy'!D6 -> 59774 | E4: ='Operating Expenses'!E12+'Facilities & Occupancy'!E6 -> 64012 | F4: ='Operating Expenses'!F12+'Facilities & Occupancy'!F6 -> 65776
A5: Capital & Debt Service | B5: 6960 | C5: 6960 | D5: 6960 | E5: 6960 | F5: 6960
A6: Total Expenses | B6: =SUM(B3:B5) -> 166394 | C6: =SUM(C3:C5) -> 208848 | D6: =SUM(D3:D5) -> 218147 | E6: =SUM(E3:E5) -> 226927 | F6: =SUM(F3:F5) -> 233370
A7: Profit / (Loss) | B7: =B2-B6 -> 18273 | C7: =C2-C6 -> 131665 | D7: =D2-D6 -> 209800 | E7: =E2-E6 -> 273591 | F7: =F2-F6 -> 282716
A8: Net Margin % | B8: =IF(B2=0,0,B7/B2) -> 0.1 | C8: =IF(C2=0,0,C7/C2) -> 0.39 | D8: =IF(D2=0,0,D7/D2) -> 0.49 | E8: =IF(E2=0,0,E7/E2) -> 0.55 | F8: =IF(F2=0,0,F7/F2) -> 0.55
A9: Cumulative Net Income | B9: =B7 -> 18273 | C9: =B9+C7 -> 149938 | D9: =C9+D7 -> 359738 | E9: =D9+E7 -> 633329 | F9: =E9+F7 -> 916045
A10: Break-even | B10: ✓ Break-even

Sheet 5-Year Balance Sheet
B1: 2026-27 | C1: 2027-28 | D1: 2028-29 | E1: 2029-30 | F1: 2030-31
A2: ASSETS
A3: Cash & Equivalents | B3: 48273 | C3: 179938 | D3: 389738 | E3: 663329 | F3: 946045
A4: Other Assets | B4: 0 | C4: 0 | D4: 0 | E4: 0 | F4: 0
A5: Total Assets | B5: =SUM(B3:B4) -> 48273 | C5: =SUM(C3:C4) -> 179938 | D5: =SUM(D3:D4) -> 389738 | E5: =SUM(E3:E4) -> 663329 | F5: =SUM(F3:F4) -> 946045
A7: LIABILITIES
A8: Debt Outstanding | B8: 24840 | C8: 19371 | D8: 13573 | E8: 7428 | F8: 914
A9: Other Liabilities | B9: 0 | C9: 0 | D9: 0 | E9: 0 | F9: 0
A10: Total Liabilities | B10: =SUM(B8:B9) -> 24840 | C10: =SUM(C8:C9) -> 19371 | D10: =SUM(D8:D9) -> 13573 | E10: =SUM(E8:E9) -> 7428 | F10: =SUM(F8:F9) -> 914
A12: EQUITY / NET ASSETS
A13: Beginning Net Position | B13: 0 | C13: 23433 | D13: 160567 | E13: 376165 | F13: 655901
A14: Change in Net Position | B14: 23433 | C14: 137134 | D14: 215598 | E14: 279736 | F14: 289230
A15: Total Equity / Net Assets | B15: =B5-B10 -> 23433 | C15: =C5-C10 -> 160567 | D15: =D5-D10 -> 376165 | E15: =E5-E10 -> 655901 | F15: =F5-F10 -> 945131
A17: BALANCE CHECK (Assets − Liab − Equity) | B17: =B5-B10-B15 -> 0 | C17: =C5-C10-C15 -> 0 | D17: =D5-D10-D15 -> 0 | E17: =E5-E10-E15 -> 0 | F17: =F5-F10-F15 -> 0

Sheet DSCR & Covenants
B1: 2026-27 | C1: 2027-28 | D1: 2028-29 | E1: 2029-30 | F1: 2030-31
A2: DEBT SERVICE COVERAGE RATIO (DSCR)
A3: Net Operating Income (NOI) | B3: 25233 | C3: 138624 | D3: 216759 | E3: 280551 | F3: 289675
A4: Annual Debt Service | B4: 6960 | C4: 6960 | D4: 6960 | E4: 6960 | F4: 6960
A5: DSCR | B5: =IF(B4=0,"N/A",B3/B4) -> 3.63 | C5: =IF(C4=0,"N/A",C3/C4) -> 19.92 | D5: =IF(D4=0,"N/A",D3/D4) -> 31.14 | E5: =IF(E4=0,"N/A",E3/E4) -> 40.31 | F5: =IF(F4=0,"N/A",F3/F4) -> 41.62
A7: LIQUIDITY METRICS
A8: Ending Cash Balance | B8: 48273 | C8: 179938 | D8: 389738 | E8: 663329 | F8: 946045
A9: Monthly Operating Cost | B9: 13286 | C9: 16824 | D9: 17599 | E9: 18331 | F9: 18868
A10: Cash Reserve (Months) | B10: =IF(B9=0,0,B8/B9) -> 3.63 | C10: =IF(C9=0,0,C8/C9) -> 10.7 | D10: =IF(D9=0,0,D8/D9) -> 22.15 | E10: =IF(E9=0,0,E8/E9) -> 36.19 | F10: =IF(F9=0,0,F8/F9) -> 50.14
A11: Days Cash on Hand | B11: 111 | C11: 325 | D11: 674 | E11: 1101 | F11: 1525
A13: COVENANT CHECKS
A14: DSCR ≥ 1.25x | B14: =IF(B5>=1.25,"PASS","FAIL") -> PASS | C14: =IF(C5>=1.25,"PASS","FAIL") -> PASS | D14: =IF(D5>=1.25,"PASS","FAIL") -> PASS | E14: =IF(E5>=1.25,"PASS","FAIL") -> PASS | F14: =IF(F5>=1.25,"PASS","FAIL") -> PASS
A15: Cash Reserve ≥ 2.0 Months | B15: =IF(B10>=2,"PASS","FAIL") -> PASS | C15: =IF(C10>=2,"PASS","FAIL") -> PASS | D15: =IF(D10>=2,"PASS","FAIL") -> PASS | E15: =IF(E10>=2,"PASS","FAIL") -> PASS | F15: =IF(F10>=2,"PASS","FAIL") -> PASS
A16: Positive Net Income | B16: PASS | C16: PASS | D16: PASS | E16: PASS | F16: PASS
A17: Enrollment ≥ 70% Capacity | B17: FAIL | C17: PASS | D17: PASS | E17: PASS | F17: PASS

Sheet Underwriting Snapshot
A1: SchoolStack - Underwriting Snapshot
A2: Bright Horizons Microschool | Microschool | AZ
A4: POLICY FLAGS
A5: DSCR ≥ 1.25x (2026-27) | B5: PASS | C5: 3.63x
A6: Min 2 Months Cash Reserve (2026-27) | B6: PASS | C6: 3.6 months
A7: Positive Net Income (2026-27) | B7: PASS | C7: Yes
A8: Break-Even Within Projection Period | B8: PASS | C8: 2026-27
A9: Enrollment ≥ 70% Capacity (2026-27) | B9: FAIL | C9: 48%
A10: Positive Ending Cash (Final Year) | B10: PASS | C10: Yes
A12: UNDERWRITING ASSESSMENT
A13: Flags Passed | B13: 5 / 6
A14: Overall Assessment | B14: Conditional
A16: KEY METRICS SUMMARY
A17: 2026-27 Revenue | B17: 184667
A18: 2026-27 Total Expenses | B18: 166394
A19: 2026-27 Net Income | B19: 18273
A20: 2026-27 Net Margin | B20: 0.098951085
A21: Starting Cash | B21: 30000
A22: 2026-27 Ending Cash | B22: 48273
A23: Total Debt | B23: 30000
A24: 2026-27 DSCR | B24: 3.63x
A25: 2026-27 Cash Reserve (Months) | B25: 3.6
A26: Break-Even Year | B26: 2026-27
A27: Revenue per Student (2026-27) | B27: 15389
A28: Cost per Student (2026-27) | B28: 13866

Sheet Summary
A1: Bright Horizons Microschool
A2: 5-Year Financial Model
A3: Microschool | AZ | Est. 2026
A4: Prepared April 29, 2026
B6: 2026-27 | C6: 2027-28 | D6: 2028-29 | E6: 2029-30 | F6: 2030-31
A7: Students | B7: =Assumptions!$B$17 -> 12 | C7: =Assumptions!$C$17 -> 18 | D7: =Assumptions!$D$17 -> 22 | E7: =Assumptions!$E$17 -> 25 | F7: =Assumptions!$F$17 -> 25
A8: Total Revenue | B8: ='5-Year P&L'!B2 -> 184667 | C8: ='5-Year P&L'!C2 -> 340512 | D8: ='5-Year P&L'!D2 -> 427946 | E8: ='5-Year P&L'!E2 -> 500518 | F8: ='5-Year P&L'!F2 -> 516085
A9: Total Expenses | B9: ='5-Year P&L'!B6 -> 166394 | C9: ='5-Year P&L'!C6 -> 208848 | D9: ='5-Year P&L'!D6 -> 218147 | E9: ='5-Year P&L'!E6 -> 226927 | F9: ='5-Year P&L'!F6 -> 233370
A10: Profit / (Loss) | B10: ='5-Year P&L'!B7 -> 18273 | C10: ='5-Year P&L'!C7 -> 131665 | D10: ='5-Year P&L'!D7 -> 209800 | E10: ='5-Year P&L'!E7 -> 273591 | F10: ='5-Year P&L'!F7 -> 282716
A11: Net Margin % | B11: =IF(B8=0,0,B10/B8) -> 0.1 | C11: =IF(C8=0,0,C10/C8) -> 0.39 | D11: =IF(D8=0,0,D10/D8) -> 0.49 | E11: =IF(E8=0,0,E10/E8) -> 0.55 | F11: =IF(F8=0,0,F10/F8) -> 0.55
A12: Cumulative Net Income | B12: =B10 -> 18273 | C12: =B12+C10 -> 149938 | D12: =C12+D10 -> 359738 | E12: =D12+E10 -> 633329 | F12: =E12+F10 -> 916045
A13: Cash Balance | B13: 48273 | C13: 179938 | D13: 389738 | E13: 663329 | F13: 946045
A14: Revenue per Student | B14: 15389 | C14: 18917 | D14: 19452 | E14: 20021 | F14: 20643
A15: Cost per Student | B15: 13866 | C15: 11603 | D15: 9916 | E15: 9077 | F15: 9335
A16: DSCR | B16: 3.63 | C16: 19.92 | D16: 31.14 | E16: 40.31 | F16: 41.62
A18: Generated by SchoolStack Budget • budget.schoolstack.ai

Sheet Cover
B3: SchoolStack Budget
B4: Underwriting Package
B8: Prepared for
B9: Bright Horizons Microschool
B10: Microschool • LLC (Single Member) • AZ
B12: Date Prepared | C12: April 29, 2026
B15: UNDERWRITING HIGHLIGHTS
B16: Year 5 Revenue | C16: 516085
B17: Year 5 Net Income | C17: 282716
B18: Ending Cash Balance | C18: 916045
B19: Overall Assessment | C19: Strong
B22: TABLE OF CONTENTS
B23: Assumptions
B24: Enrollment & Rev Drivers
B25: Tuition & Funding Detail
B26: Staffing Plan
B27: Operating Expenses
B28: Facilities & Occupancy
B29: Capital Stack & Startup Uses
B30: Debt Schedule
B31: Cash Flow Monthly Y1
B32: 5-Year P&L
B33: 5-Year Balance Sheet
... B39: Generated by SchoolStack Budget • budget.schoolstack.ai

Sheet Financial Health
B2: Bright Horizons Microschool — Financial Health Dashboard
B3: Generated April 29, 2026
B4: ● Green = healthy | D4: ◐ Yellow = monitor | F4: ○ Red = action needed
B6: Metric | C6: Year 1 | D6: Year 2 | E6: Year 3 | F6: Year 4 | G6: Year 5 | H6: Benchmark
B7: Enrollment | C7: 12 | D7: 18 | E7: 22 | F7: 25 | G7: 25
B8: Revenue | C8: 184667 | D8: 340512 | E8: 427946 | F8: 500518 | G8: 516085
B9: Personnel | C9: 118934 | D9: 147003 | E9: 151413 | F9: 155955 | G9: 160634
B10: Operating Expenses | C10: 40500 | D10: 54885 | E10: 59774 | F10: 64012 | G10: 65776
B11: Debt Service | C11: 6960 | D11: 6960 | E11: 6960 | F11: 6960 | G11: 6960
B12: Net Income | C12: 18273 | D12: 131665 | E12: 209800 | F12: 273591 | G12: 282716
B13: Ending Cash | C13: 48273 | D13: 179938 | E13: 389738 | F13: 663329 | G13: 946045
B14: Net Margin | C14: 0.098951085 | D14: 0.38666772 | E14: 0.49024877 | F14: 0.54661571 | G14: 0.54780898
B15: Revenue per Student | C15: 15388.917 | D15: 18917.333 | E15: 19452.091 | F15: 20020.72 | G15: 20643.4 | H15: ≥ $10,000
B16: Cost per Student | C16: 13866.167 | D16: 11602.667 | E16: 9915.7727 | F16: 9077.08 | G16: 9334.8
B17: Instructional / Student | C17: 0 | D17: 0 | E17: 0 | F17: 0 | G17: 0
B18: Facility / Student | C18: 3000 | D18: 2058.3333 | E18: 1733.2159 | F18: 1569.7261 | G18: 1615.5257 | H18: ≤ $2,000 / $2k–$3.5k / > $3,500
B19: Surplus per Student | C19: 1522.75 | D19: 7314.7222 | E19: 9536.3636 | F19: 10943.64 | G19: 11308.64
B20: Payroll % | C20: 0.64404577 | D20: 0.43171166 | E20: 0.35381333 | F20: 0.3115872 | G20: 0.31125493 | H20: ≤ 55%
B21: Facility % | C21: 0.1949455 | D21: 0.10880674 | E21: 0.089101779 | F21: 0.07840508 | G21: 0.078258701 | H21: ≤ 15%
B22: Operating Margin | C22: 0.13664055 | D22: 0.4071046 | E22: 0.50651017 | F22: 0.5605213 | G22: 0.5612932 | H22: ≥ 10%
B23: Revenue Sources | C23: 3 | D23: 3 | E23: 3 | F23: 3 | G23: 3 | H23: ≥ 3 sources
B24: DSCR | C24: 3.625431 | D24: 19.917241 | E24: 31.143534 | F24: 40.309052 | G24: 41.619971 | H24: ≥ 1.25x
B25: Break-even Year | C25: =IF('5-Year P&L'!B9>=0,"✓ Break-even","") -> ✓ Break-even | D25: =IF(AND('5-Year P&L'!C9>=0,'5-Year P&L'!B9<0),"✓ Break-even","") -> 0 | E25: =IF(AND('5-Year P&L'!D9>=0,'5-Year P&L'!C9<0),"✓ Break-even","") -> 0 | F25: =IF(AND('5-Year P&L'!E9>=0,'5-Year P&L'!D9<0),"✓ Break-even","") -> 0 | G25: =IF(AND('5-Year P&L'!F9>=0,'5-Year P&L'!E9<0),"✓ Break-even","") -> 0 | H25: Year 1
B26: Cash Runway (Months) | C26: 3 | D26: 10 | E26: 21 | F26: 35 | G26: 49 | H26: ≥ 24 months
B27: Days Cash on Hand | C27: 106 | D27: 314 | E27: 652 | F27: 1067 | G27: 1480 | H27: ≥ 90 days
B29: FINANCIAL HEALTH SIGNALS | C29: Status | D29: Assessment | F29: Watch Item
B30: Viability | C30: ● Healthy | D30: The model reaches profit early and sustains strong margins through Year 5. | F30: Monitor enrollment actuals vs. projections in Year 1.
B31: Liquidity | C31: ● Healthy | D31: Cash stays positive throughout the projection and reserves exceed 3 months of expenses. | F31: Maintain reserves as a buffer against seasonal revenue dips.
B32: Staffing Burden | C32: ● Healthy | D32: Staffing at 31% of revenue leaves room for facilities, programs, and reserves. | F32: As you add staff, ensure staffing stays below 60% of revenue.
B33: Facility Burden | C33: ● Healthy | D33: Facility costs at 8% of revenue are well-managed and leave budget for programs. | F33: Watch for rent escalation clauses that could push this higher over time.
B34: Debt Affordability | C34: ● Healthy | D34: DSCR of 41.62x provides comfortable coverage of debt payments with room to spare. | F34: Maintain this ratio as you take on any additional debt.
B35: Revenue Concentration | C35: ● Healthy | D35: Revenue is anchored to enrollment-driven income — the strongest foundation for a school model. A focused revenue stream is a strength when backed by dependable demand. | F35: Continue to pressure-test enrollment assumptions: recruitment pipeline, waitlist depth, retention rates, and collection reliability.
B36: Reserve Strength | C36: ● Healthy | D36: 48.6 months of reserves by Year 5 — a strong buffer for unexpected costs. | F36: Continue growing reserves toward 6 months for best-in-class financial health.
B38: Summary | C38: 7 Healthy | 0 Watch | 0 Needs Attention
B40: Built by SchoolStack Budget • budget.schoolstack.ai
